Workbook

Sheet Introduction
B4: Financial Model — 5-Year Projections and Valuation
B5: Prepared for [Client Name]
B9: Prepared by | F9: Version / Date | J9: Currency / Units
B10: Dhananjay Anil Raut | F10: v1.0 — July 2026 | J10: AED — Monthly build, yearly summary
B13: Color Legend
B15: 123 | C15: Input cell — safe to change (gray-blue fill, navy bold font)
B16: 123 | C16: Formula cell — do not edit (white, black font)
B17: 123 | C17: Cross-sheet link (green font)
B18: -1 | C18: Error / check flag (red — investigate immediately)
B21: Workbook Tabs
B22: Assumptions → Revenue Buildup → Cost Buildup → FAS → IS → BS → CFS → Valuation
B25: Disclaimer: These are estimates provided to the best of our knowledge based on logical assumptions and current market conditions; actual results may vary materially.

Sheet Assumptions
A1: Assumptions
A2: Cells in Orange are assumptions | M2: MONTHLY | BV2: YEARLY
A3: Year | M3: 1 | N3: 1 | O3: 1 | P3: 1 | Q3: 1 | R3: 1 | S3: 1 | T3: 1 | U3: 1 | V3: 1 | W3: 1 | X3: 1 | Y3: =X3+1 -> 2 | Z3: =Y3 -> 2 | AA3: =Z3 -> 2 | AB3: =AA3 -> 2 | AC3: =AB3 -> 2 | AD3: =AC3 -> 2 | AE3: =AD3 -> 2 | AF3: =AE3 -> 2 | AG3: =AF3 -> 2 | ... AJ3: =AI3 -> 2 | AK3: 3 | AL3: 3 | AM3: 3 | AN3: 3 | AO3: 3 | AP3: 3 | AQ3: 3 | AR3: 3 | AS3: 3 | AT3: 3 | AU3: 3 | AV3: 3 | AW3: 4 | AX3: 4 | AY3: 4 | AZ3: 4 | BA3: 4 | BB3: 4 | BC3: 4 | BD3: 4 | BE3: 4 | BF3: 4 | BG3: 4 | BH3: 4 | BI3: 5 | BJ3: 5 | BK3: 5 | BL3: 5 | BM3: 5 | BN3: 5 | BO3: 5 | BP3: 5 | BQ3: 5 | BR3: 5 | BS3: 5 | BT3: 5 | BV3: 1 | BW3: 2 | BX3: 3 | BY3: 4 | BZ3: 5
A4: Months | M4: 1 | N4: =M4+1 -> 2 | O4: =N4+1 -> 3 | P4: =O4+1 -> 4 | Q4: =P4+1 -> 5 | R4: =Q4+1 -> 6 | S4: =R4+1 -> 7 | T4: =S4+1 -> 8 | U4: =T4+1 -> 9 | ... BT4: =BS4+1 -> 60 | BV4: 12 | BW4: 24 | BX4: 36 | BY4: 48 | BZ4: 60
A5: General Assumptions
A6: Base Currency | G6: USD
A7: INR:USD | F7: as on 25/05/25 | G7: 85.17
A8: Revenue Assumptions
A9: Existing Clients | G9: 1
A10: New Clients | M10: 0 | N10: 0 | O10: 1 | P10: 0 | Q10: 0 | R10: 1 | S10: 0 | T10: 0 | U10: 1 | V10: 0 | W10: 0 | X10: 1 | Y10: 0 | Z10: 0 | AA10: 1 | AB10: 0 | AC10: 0 | AD10: 1 | AE10: 0 | AF10: 0 | AG10: 1 | AH10: 0 | AI10: 0 | AJ10: 1 | AK10: 0 | AL10: 0 | AM10: 0 | AN10: 0 | AO10: 0 | AP10: 1 | AQ10: 0 | AR10: 0 | AS10: 0 | AT10: 0 | AU10: 0 | AV10: 1 | AW10: 0 | AX10: 0 | AY10: 0 | AZ10: 1 | BA10: 0 | BB10: 0 | BC10: 0 | BD10: 1 | BE10: 0 | BF10: 0 | BG10: 0 | BH10: 1 | BI10: 0 | BJ10: 1 | BK10: 0 | BL10: 1 | BM10: 0 | BN10: 1 | BO10: 0 | BP10: 1 | BQ10: 0 | BR10: 1 | BS10: 0 | BT10: 1 | BV10: =SUMIF($M$3:$BT$3,BV$3,$M10:$BT10) -> 4 | BW10: =SUMIF($M$3:$BT$3,BW$3,$M10:$BT10) -> 4 | BX10: =SUMIF($M$3:$BT$3,BX$3,$M10:$BT10) -> 2 | BY10: =SUMIF($M$3:$BT$3,BY$3,$M10:$BT10) -> 3 | BZ10: =SUMIF($M$3:$BT$3,BZ$3,$M10:$BT10) -> 6
A11: Annual SaaS Subscription Price (Median Price) | F11: USD | G11: 75000 | H11: =G11 -> 75000 | M11: =G11 -> 75000 | N11: =M11+($H11-$G11)/COUNT($N$4:$BT$4) -> 75000 | O11: =N11+($H11-$G11)/COUNT($N$4:$BT$4) -> 75000 | P11: =O11+($H11-$G11)/COUNT($N$4:$BT$4) -> 75000 | Q11: =P11+($H11-$G11)/COUNT($N$4:$BT$4) -> 75000 | R11: =Q11+($H11-$G11)/COUNT($N$4:$BT$4) -> 75000 | S11: =R11+($H11-$G11)/COUNT($N$4:$BT$4) -> 75000 | T11: =S11+($H11-$G11)/COUNT($N$4:$BT$4) -> 75000 | U11: =T11+($H11-$G11)/COUNT($N$4:$BT$4) -> 75000 | ... BT11: =BS11+($H11-$G11)/COUNT($N$4:$BT$4) -> 75000
A12: Duration of Contract | F12: Months | G12: 12 | H12: 12 | M12: =G12 -> 12 | N12: =M12+($H12-$G12)/COUNT($N$4:$BT$4) -> 12 | O12: =N12+($H12-$G12)/COUNT($N$4:$BT$4) -> 12 | P12: =O12+($H12-$G12)/COUNT($N$4:$BT$4) -> 12 | Q12: =P12+($H12-$G12)/COUNT($N$4:$BT$4) -> 12 | R12: =Q12+($H12-$G12)/COUNT($N$4:$BT$4) -> 12 | S12: =R12+($H12-$G12)/COUNT($N$4:$BT$4) -> 12 | T12: =S12+($H12-$G12)/COUNT($N$4:$BT$4) -> 12 | U12: =T12+($H12-$G12)/COUNT($N$4:$BT$4) -> 12 | ... BT12: =BS12+($H12-$G12)/COUNT($N$4:$BT$4) -> 12
A13: Churn & Expansion Revenue
A14: Annual Churn Rate | F14: % | G14: 0.1 | H14: 0.1 | M14: =G14 -> 0.1 | N14: =M14+($H14-$G14)/COUNT($N$4:$BT$4) -> 0.1 | O14: =N14+($H14-$G14)/COUNT($N$4:$BT$4) -> 0.1 | P14: =O14+($H14-$G14)/COUNT($N$4:$BT$4) -> 0.1 | Q14: =P14+($H14-$G14)/COUNT($N$4:$BT$4) -> 0.1 | R14: =Q14+($H14-$G14)/COUNT($N$4:$BT$4) -> 0.1 | S14: =R14+($H14-$G14)/COUNT($N$4:$BT$4) -> 0.1 | T14: =S14+($H14-$G14)/COUNT($N$4:$BT$4) -> 0.1 | U14: =T14+($H14-$G14)/COUNT($N$4:$BT$4) -> 0.1 | ... BT14: =BS14+($H14-$G14)/COUNT($N$4:$BT$4) -> 0.1
A15: Recurring Contracts | F15: % | G15: =1-G14 -> 0.9 | H15: =1-H14 -> 0.9 | M15: =G15 -> 0.9 | N15: =M15+($H15-$G15)/COUNT($N$4:$BT$4) -> 0.9 | O15: =N15+($H15-$G15)/COUNT($N$4:$BT$4) -> 0.9 | P15: =O15+($H15-$G15)/COUNT($N$4:$BT$4) -> 0.9 | Q15: =P15+($H15-$G15)/COUNT($N$4:$BT$4) -> 0.9 | R15: =Q15+($H15-$G15)/COUNT($N$4:$BT$4) -> 0.9 | S15: =R15+($H15-$G15)/COUNT($N$4:$BT$4) -> 0.9 | T15: =S15+($H15-$G15)/COUNT($N$4:$BT$4) -> 0.9 | U15: =T15+($H15-$G15)/COUNT($N$4:$BT$4) -> 0.9 | ... BT15: =BS15+($H15-$G15)/COUNT($N$4:$BT$4) -> 0.9
A16: Cost Assumptions
A17: Direct Cost
A18: Hosting & Infrastructure Costs
A19: Hosting & Infrastructure Costs | F19: as % of revenue | G19: 0.06 | H19: =G19 -> 0.06 | M19: =G19 -> 0.06 | N19: =M19+($H19-$G19)/COUNT($N$4:$BT$4) -> 0.06 | O19: =N19+($H19-$G19)/COUNT($N$4:$BT$4) -> 0.06 | P19: =O19+($H19-$G19)/COUNT($N$4:$BT$4) -> 0.06 | Q19: =P19+($H19-$G19)/COUNT($N$4:$BT$4) -> 0.06 | R19: =Q19+($H19-$G19)/COUNT($N$4:$BT$4) -> 0.06 | S19: =R19+($H19-$G19)/COUNT($N$4:$BT$4) -> 0.06 | T19: =S19+($H19-$G19)/COUNT($N$4:$BT$4) -> 0.06 | U19: =T19+($H19-$G19)/COUNT($N$4:$BT$4) -> 0.06 | ... BT19: =BS19+($H19-$G19)/COUNT($N$4:$BT$4) -> 0.06 | BV19: =SUMIF($M$3:$BT$3,BV$3,$M19:$BT19) -> 0.72 | BW19: =SUMIF($M$3:$BT$3,BW$3,$M19:$BT19) -> 0.72 | BX19: =SUMIF($M$3:$BT$3,BX$3,$M19:$BT19) -> 0.72 | BY19: =SUMIF($M$3:$BT$3,BY$3,$M19:$BT19) -> 0.72 | BZ19: =SUMIF($M$3:$BT$3,BZ$3,$M19:$BT19) -> 0.72
A20: Third-Party Software & API Costs
A21: Payment gateway/ Bank Charges | F21: as a % of bookings | G21: 0 | H21: 0 | M21: =G21 -> 0 | N21: =M21+($H21-$G21)/COUNT($N$4:$BT$4) -> 0 | O21: =N21+($H21-$G21)/COUNT($N$4:$BT$4) -> 0 | P21: =O21+($H21-$G21)/COUNT($N$4:$BT$4) -> 0 | Q21: =P21+($H21-$G21)/COUNT($N$4:$BT$4) -> 0 | R21: =Q21+($H21-$G21)/COUNT($N$4:$BT$4) -> 0 | S21: =R21+($H21-$G21)/COUNT($N$4:$BT$4) -> 0 | T21: =S21+($H21-$G21)/COUNT($N$4:$BT$4) -> 0 | U21: =T21+($H21-$G21)/COUNT($N$4:$BT$4) -> 0 | ... BT21: =BS21+($H21-$G21)/COUNT($N$4:$BT$4) -> 0
A22: Headcount
A23: Customer Support | F23: Customer support/Account | G23: 5 | H23: 5 | M23: =G23 -> 5 | N23: =M23+($H23-$G23)/COUNT($N$4:$BT$4) -> 5 | O23: =N23+($H23-$G23)/COUNT($N$4:$BT$4) -> 5 | P23: =O23+($H23-$G23)/COUNT($N$4:$BT$4) -> 5 | Q23: =P23+($H23-$G23)/COUNT($N$4:$BT$4) -> 5 | R23: =Q23+($H23-$G23)/COUNT($N$4:$BT$4) -> 5 | S23: =R23+($H23-$G23)/COUNT($N$4:$BT$4) -> 5 | T23: =S23+($H23-$G23)/COUNT($N$4:$BT$4) -> 5 | U23: =T23+($H23-$G23)/COUNT($N$4:$BT$4) -> 5 | ... BT23: =BS23+($H23-$G23)/COUNT($N$4:$BT$4) -> 5
A24: Customer Support | F24: Monthly Salary | G24: =70000/$G$7 -> 821.88564 | H24: 0.05 | I24: Annual Increment
A25: Operating Expense
A26: Sales & Marketing Expense
A27: Sales
A28: Sales-SDR-Outsourced | F28: Monthly expense | G28: 1800 | H28: 0 | I28: Annual Increment | M28: =G28 -> 1800 | N28: =M28*(1+$H$28) -> 1800 | O28: =N28*(1+$H$28) -> 1800 | P28: =O28*(1+$H$28) -> 1800 | Q28: =P28*(1+$H$28) -> 1800 | R28: =Q28*(1+$H$28) -> 1800 | S28: =R28*(1+$H$28) -> 1800 | T28: =S28*(1+$H$28) -> 1800 | U28: =T28*(1+$H$28) -> 1800 | ... BT28: =BS28*(1+$H$28) -> 1800
A29: Cost/Lead | F29: 300-300$/qualified lead | G29: 300 | H29: =G29 -> 300 | M29: =G29 -> 300 | N29: =M29+($H29-$G29)/COUNT($N$4:$BT$4) -> 300 | O29: =N29+($H29-$G29)/COUNT($N$4:$BT$4) -> 300 | P29: =O29+($H29-$G29)/COUNT($N$4:$BT$4) -> 300 | Q29: =P29+($H29-$G29)/COUNT($N$4:$BT$4) -> 300 | R29: =Q29+($H29-$G29)/COUNT($N$4:$BT$4) -> 300 | S29: =R29+($H29-$G29)/COUNT($N$4:$BT$4) -> 300 | T29: =S29+($H29-$G29)/COUNT($N$4:$BT$4) -> 300 | U29: =T29+($H29-$G29)/COUNT($N$4:$BT$4) -> 300 | ... BT29: =BS29+($H29-$G29)/COUNT($N$4:$BT$4) -> 300 | BV29: =SUMIF($M$3:$BT$3,BV$3,$M28:$BT28) -> 21600 | BW29: =SUMIF($M$3:$BT$3,BW$3,$M28:$BT28) -> 21600 | BX29: =SUMIF($M$3:$BT$3,BX$3,$M28:$BT28) -> 21600 | BY29: =SUMIF($M$3:$BT$3,BY$3,$M28:$BT28) -> 21600 | BZ29: =SUMIF($M$3:$BT$3,BZ$3,$M28:$BT28) -> 21600
A30: Additional Cost for Qualified Leads | G30: 300 | H30: =G30 -> 300 | M30: =G30 -> 300 | N30: =M30+($H30-$G30)/COUNT($N$4:$BT$4) -> 300 | O30: =N30+($H30-$G30)/COUNT($N$4:$BT$4) -> 300 | P30: =O30+($H30-$G30)/COUNT($N$4:$BT$4) -> 300 | Q30: =P30+($H30-$G30)/COUNT($N$4:$BT$4) -> 300 | R30: =Q30+($H30-$G30)/COUNT($N$4:$BT$4) -> 300 | S30: =R30+($H30-$G30)/COUNT($N$4:$BT$4) -> 300 | T30: =S30+($H30-$G30)/COUNT($N$4:$BT$4) -> 300 | U30: =T30+($H30-$G30)/COUNT($N$4:$BT$4) -> 300 | ... BT30: =BS30+($H30-$G30)/COUNT($N$4:$BT$4) -> 300
A31: Sales Commission %
A32: New Bookings | F32: as a % respective bookings | G32: 0.03 | H32: =G32 -> 0.03 | M32: =G32 -> 0.03 | N32: =M32+($H32-$G32)/COUNT($N$4:$BT$4) -> 0.03 | O32: =N32+($H32-$G32)/COUNT($N$4:$BT$4) -> 0.03 | P32: =O32+($H32-$G32)/COUNT($N$4:$BT$4) -> 0.03 | Q32: =P32+($H32-$G32)/COUNT($N$4:$BT$4) -> 0.03 | R32: =Q32+($H32-$G32)/COUNT($N$4:$BT$4) -> 0.03 | S32: =R32+($H32-$G32)/COUNT($N$4:$BT$4) -> 0.03 | T32: =S32+($H32-$G32)/COUNT($N$4:$BT$4) -> 0.03 | U32: =T32+($H32-$G32)/COUNT($N$4:$BT$4) -> 0.03 | ... BT32: =BS32+($H32-$G32)/COUNT($N$4:$BT$4) -> 0.03
A33: Renewals | F33: as a % respective bookings | G33: 0 | H33: 0 | M33: =G33 -> 0 | N33: =M33+($H33-$G33)/COUNT($N$4:$BT$4) -> 0 | O33: =N33+($H33-$G33)/COUNT($N$4:$BT$4) -> 0 | P33: =O33+($H33-$G33)/COUNT($N$4:$BT$4) -> 0 | Q33: =P33+($H33-$G33)/COUNT($N$4:$BT$4) -> 0 | R33: =Q33+($H33-$G33)/COUNT($N$4:$BT$4) -> 0 | S33: =R33+($H33-$G33)/COUNT($N$4:$BT$4) -> 0 | T33: =S33+($H33-$G33)/COUNT($N$4:$BT$4) -> 0 | U33: =T33+($H33-$G33)/COUNT($N$4:$BT$4) -> 0 | ... BT33: =BS33+($H33-$G33)/COUNT($N$4:$BT$4) -> 0
A34: Expansion | F34: as a % respective bookings | G34: 0 | H34: 0 | M34: =G34 -> 0 | N34: =M34+($H34-$G34)/COUNT($N$4:$BT$4) -> 0 | O34: =N34+($H34-$G34)/COUNT($N$4:$BT$4) -> 0 | P34: =O34+($H34-$G34)/COUNT($N$4:$BT$4) -> 0 | Q34: =P34+($H34-$G34)/COUNT($N$4:$BT$4) -> 0 | R34: =Q34+($H34-$G34)/COUNT($N$4:$BT$4) -> 0 | S34: =R34+($H34-$G34)/COUNT($N$4:$BT$4) -> 0 | T34: =S34+($H34-$G34)/COUNT($N$4:$BT$4) -> 0 | U34: =T34+($H34-$G34)/COUNT($N$4:$BT$4) -> 0 | ... BT34: =BS34+($H34-$G34)/COUNT($N$4:$BT$4) -> 0
A35: Sales Team-Headcount
A36: Client Success Manager | F36: Qualified Leads/CSM/Month | G36: 10 | H36: 10 | M36: =G36 -> 10 | N36: =M36+($H36-$G36)/COUNT($N$4:$BT$4) -> 10 | O36: =N36+($H36-$G36)/COUNT($N$4:$BT$4) -> 10 | P36: =O36+($H36-$G36)/COUNT($N$4:$BT$4) -> 10 | Q36: =P36+($H36-$G36)/COUNT($N$4:$BT$4) -> 10 | R36: =Q36+($H36-$G36)/COUNT($N$4:$BT$4) -> 10 | S36: =R36+($H36-$G36)/COUNT($N$4:$BT$4) -> 10 | T36: =S36+($H36-$G36)/COUNT($N$4:$BT$4) -> 10 | U36: =T36+($H36-$G36)/COUNT($N$4:$BT$4) -> 10 | ... BT36: =BS36+($H36-$G36)/COUNT($N$4:$BT$4) -> 10
A37: XYZ(For any additional role)
A38: Sales Team Salaries
A39: =A36 -> Client Success Manager | F39: Monthly Salary/Headcount | G39: 1200 | H39: 0.05 | I39: Annual Increment
F40: Monthly Salary/Headcount | G40: 0 | H40: 0.05 | I40: Annual Increment
A41: Marketing | G41: Year 1 | H41: Year 2 | I41: Year 3 | J41: Year 4 | K41: Year 5
A42: Marketing Budget | G42: 500 | H42: =G42*(1+20%) -> 600 | I42: =H42*(1+40%) -> 840 | J42: =I42*(1+0%) -> 840 | K42: =J42 -> 840 | M42: =$H$42 -> 600 | N42: =$H$42 -> 600 | O42: =$H$42 -> 600 | P42: =$H$42 -> 600 | Q42: =$H$42 -> 600 | R42: =$H$42 -> 600 | S42: =$H$42 -> 600 | T42: =$H$42 -> 600 | ... AJ42: =$H$42 -> 600 | AK42: =$I$42 -> 840 | AL42: =$I$42 -> 840 | AM42: =$I$42 -> 840 | AN42: =$I$42 -> 840 | AO42: =$I$42 -> 840 | AP42: =$I$42 -> 840 | AQ42: =$I$42 -> 840 | AR42: =$I$42 -> 840 | ... AV42: =$I$42 -> 840 | AW42: =$J$42 -> 840 | AX42: =$J$42 -> 840 | AY42: =$J$42 -> 840 | AZ42: =$J$42 -> 840 | BA42: =$J$42 -> 840 | BB42: =$J$42 -> 840 | BC42: =$J$42 -> 840 | BD42: =$J$42 -> 840 | ... BH42: =$J$42 -> 840 | BI42: =$K$42 -> 840 | BJ42: =$K$42 -> 840 | BK42: =$K$42 -> 840 | BL42: =$K$42 -> 840 | BM42: =$K$42 -> 840 | BN42: =$K$42 -> 840 | BO42: =$K$42 -> 840 | BP42: =$K$42 -> 840 | ... BT42: =$K$42 -> 840
A43: Marketing Team Roles & Headcount | BV43: =SUMIF($M$3:$BT$3,BV$3,$M42:$BT42) -> 7200 | BW43: =SUMIF($M$3:$BT$3,BW$3,$M42:$BT42) -> 7200 | BX43: =SUMIF($M$3:$BT$3,BX$3,$M42:$BT42) -> 10080 | BY43: =SUMIF($M$3:$BT$3,BY$3,$M42:$BT42) -> 10080 | BZ43: =SUMIF($M$3:$BT$3,BZ$3,$M42:$BT42) -> 10080
A44: ABC | F44: Monthly Salary/Headcount | G44: 0 | H44: 0.05 | I44: Annual Increment | M44: 0 | N44: =M44 -> 0 | O44: =N44 -> 0 | P44: =O44 -> 0 | Q44: =P44 -> 0 | R44: =Q44 -> 0 | S44: =R44 -> 0 | T44: =S44 -> 0 | U44: =T44 -> 0 | ... BT44: =BS44 -> 0
A45: ABC | F45: Monthly Salary/Headcount | G45: 0 | H45: 0.05 | I45: Annual Increment | M45: 0 | N45: =M45 -> 0 | O45: =N45 -> 0 | P45: =O45 -> 0 | Q45: =P45 -> 0 | R45: =Q45 -> 0 | S45: =R45 -> 0 | T45: =S45 -> 0 | U45: =T45 -> 0 | ... BT45: =BS45 -> 0
A46: ABC | F46: Monthly Salary/Headcount | G46: 0 | H46: 0.05 | I46: Annual Increment | M46: 0 | N46: =M46 -> 0 | O46: =N46 -> 0 | P46: =O46 -> 0 | Q46: =P46 -> 0 | R46: =Q46 -> 0 | S46: =R46 -> 0 | T46: =S46 -> 0 | U46: =T46 -> 0 | ... BT46: =BS46 -> 0
A47: ABC | F47: Monthly Salary/Headcount | G47: 0 | H47: 0.05 | I47: Annual Increment | M47: 0 | N47: =M47 -> 0 | O47: =N47 -> 0 | P47: =O47 -> 0 | Q47: =P47 -> 0 | R47: =Q47 -> 0 | S47: =R47 -> 0 | T47: =S47 -> 0 | U47: =T47 -> 0 | ... BT47: =BS47 -> 0
A48: ABC | F48: Monthly Salary/Headcount | G48: 0 | H48: 0.05 | I48: Annual Increment | M48: 0 | N48: =M48 -> 0 | O48: =N48 -> 0 | P48: =O48 -> 0 | Q48: =P48 -> 0 | R48: =Q48 -> 0 | S48: =R48 -> 0 | T48: =S48 -> 0 | U48: =T48 -> 0 | ... BT48: =BS48 -> 0
A49: ABC | F49: Monthly Salary/Headcount | G49: 0 | H49: 0.05 | I49: Annual Increment | M49: 0 | N49: =M49 -> 0 | O49: =N49 -> 0 | P49: =O49 -> 0 | Q49: =P49 -> 0 | R49: =Q49 -> 0 | S49: =R49 -> 0 | T49: =S49 -> 0 | U49: =T49 -> 0 | ... BT49: =BS49 -> 0
A50: G&A
A51: Office Rent | F51: Chair/Employee/Monthly | G51: =7000/$G$7 -> 82.188564 | H51: =G51*(1+6%)^5 -> 109.98684 | M51: =G51 -> 82.188564 | N51: =M51+($H51-$G51)/COUNT($N$4:$BT$4) -> 82.659721 | O51: =N51+($H51-$G51)/COUNT($N$4:$BT$4) -> 83.130878 | P51: =O51+($H51-$G51)/COUNT($N$4:$BT$4) -> 83.602036 | Q51: =P51+($H51-$G51)/COUNT($N$4:$BT$4) -> 84.073193 | R51: =Q51+($H51-$G51)/COUNT($N$4:$BT$4) -> 84.54435 | S51: =R51+($H51-$G51)/COUNT($N$4:$BT$4) -> 85.015507 | T51: =S51+($H51-$G51)/COUNT($N$4:$BT$4) -> 85.486664 | U51: =T51+($H51-$G51)/COUNT($N$4:$BT$4) -> 85.957822 | ... BT51: =BS51+($H51-$G51)/COUNT($N$4:$BT$4) -> 109.98684 | BV51: =SUMIF($M$3:$BT$3,BV$3,$M51:$BT51) -> 1017.3591 | BW51: =SUMIF($M$3:$BT$3,BW$3,$M51:$BT51) -> 1085.2058 | BX51: =SUMIF($M$3:$BT$3,BX$3,$M51:$BT51) -> 1153.0524 | BY51: =SUMIF($M$3:$BT$3,BY$3,$M51:$BT51) -> 1220.8991 | BZ51: =SUMIF($M$3:$BT$3,BZ$3,$M51:$BT51) -> 1288.7457
A52: Utilities | F52: Emp/Monthly | G52: =5000/$G$7 -> 58.706117 | H52: =G52*(1+6%)^5 -> 78.562028 | M52: =G52 -> 58.706117 | N52: =M52+($H52-$G52)/COUNT($N$4:$BT$4) -> 59.042658 | O52: =N52+($H52-$G52)/COUNT($N$4:$BT$4) -> 59.379199 | P52: =O52+($H52-$G52)/COUNT($N$4:$BT$4) -> 59.71574 | Q52: =P52+($H52-$G52)/COUNT($N$4:$BT$4) -> 60.052281 | R52: =Q52+($H52-$G52)/COUNT($N$4:$BT$4) -> 60.388821 | S52: =R52+($H52-$G52)/COUNT($N$4:$BT$4) -> 60.725362 | T52: =S52+($H52-$G52)/COUNT($N$4:$BT$4) -> 61.061903 | U52: =T52+($H52-$G52)/COUNT($N$4:$BT$4) -> 61.398444 | ... BT52: =BS52+($H52-$G52)/COUNT($N$4:$BT$4) -> 78.562028 | BV52: =SUMIF($M$3:$BT$3,BV$3,$M52:$BT52) -> 726.6851 | BW52: =SUMIF($M$3:$BT$3,BW$3,$M52:$BT52) -> 775.14699 | BX52: =SUMIF($M$3:$BT$3,BX$3,$M52:$BT52) -> 823.60887 | BY52: =SUMIF($M$3:$BT$3,BY$3,$M52:$BT52) -> 872.07075 | BZ52: =SUMIF($M$3:$BT$3,BZ$3,$M52:$BT52) -> 920.53263
A53: Advisory | F53: Monthly Expense | G53: 2583.0692 | H53: 0
A54: G&A Team Roles & Headcount
A55: Account & Finance | F55: Monthly Salary/Headcount | G55: =40000/$G$7 -> 469.64894 | H55: 0.05 | I55: Annual Increment | M55: 1 | N55: =M55 -> 1 | O55: =N55 -> 1 | P55: =O55 -> 1 | Q55: =P55 -> 1 | R55: =Q55 -> 1 | S55: =R55 -> 1 | T55: =S55 -> 1 | U55: =T55 -> 1 | ... X55: =W55 -> 1 | Y55: 2 | Z55: =Y55 -> 2 | AA55: =Z55 -> 2 | AB55: =AA55 -> 2 | AC55: =AB55 -> 2 | AD55: =AC55 -> 2 | AE55: =AD55 -> 2 | AF55: =AE55 -> 2 | AG55: =AF55 -> 2 | ... BT55: =BS55 -> 2
A56: Legal | F56: Monthly Salary/Headcount | G56: =25000/$G$7 -> 293.53059 | H56: 0 | I56: Annual Increment | M56: 1 | N56: =M56 -> 1 | O56: =N56 -> 1 | P56: =O56 -> 1 | Q56: =P56 -> 1 | R56: =Q56 -> 1 | S56: =R56 -> 1 | T56: =S56 -> 1 | U56: =T56 -> 1 | ... X56: =W56 -> 1 | Y56: 2 | Z56: =Y56 -> 2 | AA56: =Z56 -> 2 | AB56: =AA56 -> 2 | AC56: =AB56 -> 2 | AD56: =AC56 -> 2 | AE56: =AD56 -> 2 | AF56: =AE56 -> 2 | AG56: =AF56 -> 2 | ... BT56: =BS56 -> 2
A57: HR | F57: Monthly Salary/Headcount | G57: =60000/G7 -> 704.47341 | H57: 0.05 | I57: Annual Increment | M57: 0 | N57: =M57 -> 0 | O57: =N57 -> 0 | P57: =O57 -> 0 | Q57: =P57 -> 0 | R57: =Q57 -> 0 | S57: 1 | T57: =S57 -> 1 | U57: =T57 -> 1 | V57: =U57 -> 1 | W57: =V57 -> 1 | X57: =W57 -> 1 | Y57: 1 | Z57: =Y57 -> 1 | AA57: =Z57 -> 1 | AB57: =AA57 -> 1 | AC57: =AB57 -> 1 | AD57: =AC57 -> 1 | AE57: =AD57 -> 1 | AF57: =AE57 -> 1 | AG57: =AF57 -> 1 | ... BT57: =BS57 -> 1
A58: Management-Co-Found | F58: Monthly Salary/Headcount | G58: 2583.0692 | H58: 0 | I58: Annual Increment | M58: 1 | N58: =M58 -> 1 | O58: =N58 -> 1 | P58: =O58 -> 1 | Q58: =P58 -> 1 | R58: =Q58 -> 1 | S58: =R58 -> 1 | T58: =S58 -> 1 | U58: =T58 -> 1 | ... BT58: =BS58 -> 1
A59: Management-Co-Found | F59: Monthly Salary/Headcount | G59: 2583.0692 | H59: 0 | I59: Annual Increment | M59: 1 | N59: =M59 -> 1 | O59: =N59 -> 1 | P59: =O59 -> 1 | Q59: =P59 -> 1 | R59: =Q59 -> 1 | S59: =R59 -> 1 | T59: =S59 -> 1 | U59: =T59 -> 1 | ... BT59: =BS59 -> 1
A60: Product Development Expense
A61: Infrastructure | G61: 1585.0652 | H61: 0.02 | M61: =G61 -> 1585.0652 | N61: =M61*(1+$H$61) -> 1616.7665 | O61: =N61*(1+$H$61) -> 1649.1018 | P61: =O61*(1+$H$61) -> 1682.0838 | Q61: =P61*(1+$H$61) -> 1715.7255 | R61: =Q61*(1+$H$61) -> 1750.04 | S61: =R61*(1+$H$61) -> 1785.0408 | T61: =S61*(1+$H$61) -> 1820.7416 | U61: =T61*(1+$H$61) -> 1857.1565 | ... BT61: =BS61*(1+$H$61) -> 5098.6741 | BV61: =SUMIF($M$3:$BT$3,BV$3,$M61:$BT61) -> 21259.036 | BW61: =SUMIF($M$3:$BT$3,BW$3,$M61:$BT61) -> 26961.598 | BX61: =SUMIF($M$3:$BT$3,BX$3,$M61:$BT61) -> 34193.826 | BY61: =SUMIF($M$3:$BT$3,BY$3,$M61:$BT61) -> 43366.039 | BZ61: =SUMIF($M$3:$BT$3,BZ$3,$M61:$BT61) -> 54998.623
A62: Product Development Team Roles & Headcount
A63: Project Manager | B63: Headcount | C63: 1 | D63: 10 | F63: Monthly Salary | G63: 2000 | H63: 0.1 | I63: Annual Increment | M63: =CEILING('Revenue Buildup'!M$11,$D63)/$D63 -> 1 | N63: =CEILING('Revenue Buildup'!N$11,$D63)/$D63 -> 1 | O63: =CEILING('Revenue Buildup'!O$11,$D63)/$D63 -> 1 | P63: =CEILING('Revenue Buildup'!P$11,$D63)/$D63 -> 1 | Q63: =CEILING('Revenue Buildup'!Q$11,$D63)/$D63 -> 1 | R63: =CEILING('Revenue Buildup'!R$11,$D63)/$D63 -> 1 | S63: =CEILING('Revenue Buildup'!S$11,$D63)/$D63 -> 1 | T63: =CEILING('Revenue Buildup'!T$11,$D63)/$D63 -> 1 | ... BT63: =CEILING('Revenue Buildup'!BT$11,$D63)/$D63 -> 2
A64: UI,UX Designer | B64: Headcount | C64: 1 | D64: 18 | F64: Monthly Salary | G64: 1408.9468 | H64: 0.1 | I64: Annual Increment | M64: =CEILING('Revenue Buildup'!M$11,$D64)/$D64 -> 1 | N64: =CEILING('Revenue Buildup'!N$11,$D64)/$D64 -> 1 | O64: =CEILING('Revenue Buildup'!O$11,$D64)/$D64 -> 1 | P64: =CEILING('Revenue Buildup'!P$11,$D64)/$D64 -> 1 | Q64: =CEILING('Revenue Buildup'!Q$11,$D64)/$D64 -> 1 | R64: =CEILING('Revenue Buildup'!R$11,$D64)/$D64 -> 1 | S64: =CEILING('Revenue Buildup'!S$11,$D64)/$D64 -> 1 | T64: =CEILING('Revenue Buildup'!T$11,$D64)/$D64 -> 1 | ... BT64: =CEILING('Revenue Buildup'!BT$11,$D64)/$D64 -> 2
A65: Sr. Software | B65: Headcount | C65: 1 | D65: 18 | F65: Monthly Salary | G65: 2500 | H65: 0.1 | I65: Annual Increment | M65: =CEILING('Revenue Buildup'!M$11,$D65)/$D65 -> 1 | N65: =CEILING('Revenue Buildup'!N$11,$D65)/$D65 -> 1 | O65: =CEILING('Revenue Buildup'!O$11,$D65)/$D65 -> 1 | P65: =CEILING('Revenue Buildup'!P$11,$D65)/$D65 -> 1 | Q65: =CEILING('Revenue Buildup'!Q$11,$D65)/$D65 -> 1 | R65: =CEILING('Revenue Buildup'!R$11,$D65)/$D65 -> 1 | S65: =CEILING('Revenue Buildup'!S$11,$D65)/$D65 -> 1 | T65: =CEILING('Revenue Buildup'!T$11,$D65)/$D65 -> 1 | ... BT65: =CEILING('Revenue Buildup'!BT$11,$D65)/$D65 -> 2
A66: Solution Architect | B66: Headcount | C66: 1 | D66: 18 | F66: Monthly Salary | G66: 3000 | H66: 0.1 | I66: Annual Increment | M66: =CEILING('Revenue Buildup'!M$11,$D66)/$D66 -> 1 | N66: =CEILING('Revenue Buildup'!N$11,$D66)/$D66 -> 1 | O66: =CEILING('Revenue Buildup'!O$11,$D66)/$D66 -> 1 | P66: =CEILING('Revenue Buildup'!P$11,$D66)/$D66 -> 1 | Q66: =CEILING('Revenue Buildup'!Q$11,$D66)/$D66 -> 1 | R66: =CEILING('Revenue Buildup'!R$11,$D66)/$D66 -> 1 | S66: =CEILING('Revenue Buildup'!S$11,$D66)/$D66 -> 1 | T66: =CEILING('Revenue Buildup'!T$11,$D66)/$D66 -> 1 | ... BT66: =CEILING('Revenue Buildup'!BT$11,$D66)/$D66 -> 2
A67: Test Er | B67: Headcount | C67: 1 | D67: 18 | F67: Monthly Salary | G67: 1174.1223 | H67: 0.1 | I67: Annual Increment | M67: =CEILING('Revenue Buildup'!M$11,$D67)/$D67 -> 1 | N67: =CEILING('Revenue Buildup'!N$11,$D67)/$D67 -> 1 | O67: =CEILING('Revenue Buildup'!O$11,$D67)/$D67 -> 1 | P67: =CEILING('Revenue Buildup'!P$11,$D67)/$D67 -> 1 | Q67: =CEILING('Revenue Buildup'!Q$11,$D67)/$D67 -> 1 | R67: =CEILING('Revenue Buildup'!R$11,$D67)/$D67 -> 1 | S67: =CEILING('Revenue Buildup'!S$11,$D67)/$D67 -> 1 | T67: =CEILING('Revenue Buildup'!T$11,$D67)/$D67 -> 1 | ... BT67: =CEILING('Revenue Buildup'!BT$11,$D67)/$D67 -> 2
A68: Jr. Test Er | B68: Headcount | C68: 1 | D68: 18 | F68: Monthly Salary | G68: 821.88564 | H68: 0.1 | I68: Annual Increment | M68: =CEILING('Revenue Buildup'!M$11,$D68)/$D68 -> 1 | N68: =CEILING('Revenue Buildup'!N$11,$D68)/$D68 -> 1 | O68: =CEILING('Revenue Buildup'!O$11,$D68)/$D68 -> 1 | P68: =CEILING('Revenue Buildup'!P$11,$D68)/$D68 -> 1 | Q68: =CEILING('Revenue Buildup'!Q$11,$D68)/$D68 -> 1 | R68: =CEILING('Revenue Buildup'!R$11,$D68)/$D68 -> 1 | S68: =CEILING('Revenue Buildup'!S$11,$D68)/$D68 -> 1 | T68: =CEILING('Revenue Buildup'!T$11,$D68)/$D68 -> 1 | ... BT68: =CEILING('Revenue Buildup'!BT$11,$D68)/$D68 -> 2
A69: Infra Er | B69: Headcount | C69: 1 | D69: 18 | F69: Monthly Salary | G69: 1408.9468 | H69: 0.1 | I69: Annual Increment | M69: =CEILING('Revenue Buildup'!M$11,$D69)/$D69 -> 1 | N69: =CEILING('Revenue Buildup'!N$11,$D69)/$D69 -> 1 | O69: =CEILING('Revenue Buildup'!O$11,$D69)/$D69 -> 1 | P69: =CEILING('Revenue Buildup'!P$11,$D69)/$D69 -> 1 | Q69: =CEILING('Revenue Buildup'!Q$11,$D69)/$D69 -> 1 | R69: =CEILING('Revenue Buildup'!R$11,$D69)/$D69 -> 1 | S69: =CEILING('Revenue Buildup'!S$11,$D69)/$D69 -> 1 | T69: =CEILING('Revenue Buildup'!T$11,$D69)/$D69 -> 1 | ... BT69: =CEILING('Revenue Buildup'!BT$11,$D69)/$D69 -> 2
A70: Jr. Infra Er | B70: Headcount | C70: 1 | D70: 18 | F70: Monthly Salary | G70: 763.17952 | H70: 0.1 | I70: Annual Increment | M70: =CEILING('Revenue Buildup'!M$11,$D70)/$D70 -> 1 | N70: =CEILING('Revenue Buildup'!N$11,$D70)/$D70 -> 1 | O70: =CEILING('Revenue Buildup'!O$11,$D70)/$D70 -> 1 | P70: =CEILING('Revenue Buildup'!P$11,$D70)/$D70 -> 1 | Q70: =CEILING('Revenue Buildup'!Q$11,$D70)/$D70 -> 1 | R70: =CEILING('Revenue Buildup'!R$11,$D70)/$D70 -> 1 | S70: =CEILING('Revenue Buildup'!S$11,$D70)/$D70 -> 1 | T70: =CEILING('Revenue Buildup'!T$11,$D70)/$D70 -> 1 | ... BT70: =CEILING('Revenue Buildup'!BT$11,$D70)/$D70 -> 2
A71: Frontend Developer | B71: Headcount | C71: 2 | D71: 18 | F71: Monthly Salary | G71: 1000 | H71: 0.1 | I71: Annual Increment | M71: =CEILING('Revenue Buildup'!M$11,$D71)/$D71 -> 1 | N71: =CEILING('Revenue Buildup'!N$11,$D71)/$D71 -> 1 | O71: =CEILING('Revenue Buildup'!O$11,$D71)/$D71 -> 1 | P71: =CEILING('Revenue Buildup'!P$11,$D71)/$D71 -> 1 | Q71: =CEILING('Revenue Buildup'!Q$11,$D71)/$D71 -> 1 | R71: =CEILING('Revenue Buildup'!R$11,$D71)/$D71 -> 1 | S71: =CEILING('Revenue Buildup'!S$11,$D71)/$D71 -> 1 | T71: =CEILING('Revenue Buildup'!T$11,$D71)/$D71 -> 1 | ... BT71: =CEILING('Revenue Buildup'!BT$11,$D71)/$D71 -> 2
A72: Backend Developer | B72: Headcount | C72: 2 | D72: 18 | F72: Monthly Salary | G72: 1000 | H72: 0.1 | I72: Annual Increment | M72: =CEILING('Revenue Buildup'!M$11,$D72)/$D72 -> 1 | N72: =CEILING('Revenue Buildup'!N$11,$D72)/$D72 -> 1 | O72: =CEILING('Revenue Buildup'!O$11,$D72)/$D72 -> 1 | P72: =CEILING('Revenue Buildup'!P$11,$D72)/$D72 -> 1 | Q72: =CEILING('Revenue Buildup'!Q$11,$D72)/$D72 -> 1 | R72: =CEILING('Revenue Buildup'!R$11,$D72)/$D72 -> 1 | S72: =CEILING('Revenue Buildup'!S$11,$D72)/$D72 -> 1 | T72: =CEILING('Revenue Buildup'!T$11,$D72)/$D72 -> 1 | ... BT72: =CEILING('Revenue Buildup'!BT$11,$D72)/$D72 -> 2

Sheet Revenue Buildup
A1: Revenue Buildup
A2: Cells in Orange are assumptions | M2: MONTHLY | BV2: YEARLY
A3: Year | M3: 1 | N3: 1 | O3: 1 | P3: 1 | Q3: 1 | R3: 1 | S3: 1 | T3: 1 | U3: 1 | V3: 1 | W3: 1 | X3: 1 | Y3: =X3+1 -> 2 | Z3: =Y3 -> 2 | AA3: =Z3 -> 2 | AB3: =AA3 -> 2 | AC3: =AB3 -> 2 | AD3: =AC3 -> 2 | AE3: =AD3 -> 2 | AF3: =AE3 -> 2 | AG3: =AF3 -> 2 | ... AJ3: =AI3 -> 2 | AK3: 3 | AL3: 3 | AM3: 3 | AN3: 3 | AO3: 3 | AP3: 3 | AQ3: 3 | AR3: 3 | AS3: 3 | AT3: 3 | AU3: 3 | AV3: 3 | AW3: 4 | AX3: 4 | AY3: 4 | AZ3: 4 | BA3: 4 | BB3: 4 | BC3: 4 | BD3: 4 | BE3: 4 | BF3: 4 | BG3: 4 | BH3: 4 | BI3: 5 | BJ3: 5 | BK3: 5 | BL3: 5 | BM3: 5 | BN3: 5 | BO3: 5 | BP3: 5 | BQ3: 5 | BR3: 5 | BS3: 5 | BT3: 5 | BV3: 1 | BW3: 2 | BX3: 3 | BY3: 4 | BZ3: 5
A4: Months | M4: 1 | N4: =M4+1 -> 2 | O4: =N4+1 -> 3 | P4: =O4+1 -> 4 | Q4: =P4+1 -> 5 | R4: =Q4+1 -> 6 | S4: =R4+1 -> 7 | T4: =S4+1 -> 8 | U4: =T4+1 -> 9 | ... BT4: =BS4+1 -> 60 | BV4: 12 | BW4: 24 | BX4: 36 | BY4: 48 | BZ4: 60
A5: SpoviX
A6: Qualified Leads | M6: =ROUND(Assumptions!M28/Assumptions!M29,0) -> 6 | N6: =ROUND(Assumptions!N28/Assumptions!N29,0) -> 6 | O6: =ROUND(Assumptions!O28/Assumptions!O29,0) -> 6 | P6: =ROUND(Assumptions!P28/Assumptions!P29,0) -> 6 | Q6: =ROUND(Assumptions!Q28/Assumptions!Q29,0) -> 6 | R6: =ROUND(Assumptions!R28/Assumptions!R29,0) -> 6 | S6: =ROUND(Assumptions!S28/Assumptions!S29,0) -> 6 | T6: =ROUND(Assumptions!T28/Assumptions!T29,0) -> 6 | ... BT6: =ROUND(Assumptions!BT28/Assumptions!BT29,0) -> 6 | BV6: =SUMIF($M$3:$BT$3,BV$3,$M6:$BT6) -> 72 | BW6: =SUMIF($M$3:$BT$3,BW$3,$M6:$BT6) -> 72 | BX6: =SUMIF($M$3:$BT$3,BX$3,$M6:$BT6) -> 72 | BY6: =SUMIF($M$3:$BT$3,BY$3,$M6:$BT6) -> 72 | BZ6: =SUMIF($M$3:$BT$3,BZ$3,$M6:$BT6) -> 72
A7: Active Customers
A8: New Clients | M8: =Assumptions!M10 -> 0 | N8: =Assumptions!N10 -> 0 | O8: =Assumptions!O10 -> 1 | P8: =Assumptions!P10 -> 0 | Q8: =Assumptions!Q10 -> 0 | R8: =Assumptions!R10 -> 1 | S8: =Assumptions!S10 -> 0 | T8: =Assumptions!T10 -> 0 | ... BT8: =Assumptions!BT10 -> 1 | BV8: =SUMIF($M$3:$BT$3,BV$3,$M8:$BT8) -> 4 | BW8: =SUMIF($M$3:$BT$3,BW$3,$M8:$BT8) -> 4 | BX8: =SUMIF($M$3:$BT$3,BX$3,$M8:$BT8) -> 2 | BY8: =SUMIF($M$3:$BT$3,BY$3,$M8:$BT8) -> 3 | BZ8: =SUMIF($M$3:$BT$3,BZ$3,$M8:$BT8) -> 6
A9: Existing Clients | M9: =Assumptions!G9 -> 1 | N9: =M11 -> 1 | O9: =N11 -> 1 | P9: =O11 -> 2 | Q9: =P11 -> 2 | R9: =Q11 -> 2 | S9: =R11 -> 3 | T9: =S11 -> 3 | U9: =T11 -> 3 | ... BT9: =BS11 -> 19 | BV9: =M9 -> 1 | BW9: =BV11 -> 5 | BX9: =BW11 -> 9 | BY9: =BX11 -> 11 | BZ9: =BY11 -> 14
A10: Churned | X10: =-ROUND(M8*Assumptions!X14,0) -> 0 | Y10: =-ROUND(N8*Assumptions!Y14,0) -> 0 | Z10: =-ROUND(O8*Assumptions!Z14,0) -> 0 | AA10: =-ROUND(P8*Assumptions!AA14,0) -> 0 | AB10: =-ROUND(Q8*Assumptions!AB14,0) -> 0 | AC10: =-ROUND(R8*Assumptions!AC14,0) -> 0 | AD10: =-ROUND(S8*Assumptions!AD14,0) -> 0 | AE10: =-ROUND(T8*Assumptions!AE14,0) -> 0 | ... BT10: =-ROUND(BI8*Assumptions!BT14,0) -> 0 | BV10: =SUMIF($M$3:$BT$3,BV$3,$M10:$BT10) -> 0 | BW10: =SUMIF($M$3:$BT$3,BW$3,$M10:$BT10) -> 0 | BX10: =SUMIF($M$3:$BT$3,BX$3,$M10:$BT10) -> 0 | BY10: =SUMIF($M$3:$BT$3,BY$3,$M10:$BT10) -> 0 | BZ10: =SUMIF($M$3:$BT$3,BZ$3,$M10:$BT10) -> 0
A11: Total Clients | M11: =SUM(M8:M10) -> 1 | N11: =SUM(N8:N10) -> 1 | O11: =SUM(O8:O10) -> 2 | P11: =SUM(P8:P10) -> 2 | Q11: =SUM(Q8:Q10) -> 2 | R11: =SUM(R8:R10) -> 3 | S11: =SUM(S8:S10) -> 3 | T11: =SUM(T8:T10) -> 3 | ... BT11: =SUM(BT8:BT10) -> 20 | BV11: =SUM(BV8:BV10) -> 5 | BW11: =SUM(BW8:BW10) -> 9 | BX11: =SUM(BX8:BX10) -> 11 | BY11: =SUM(BY8:BY10) -> 14 | BZ11: =SUM(BZ8:BZ10) -> 20
A12: Bookings
A13: New Bookings | M13: =M8*Assumptions!M11 -> 0 | N13: =N8*Assumptions!N11 -> 0 | O13: =O8*Assumptions!O11 -> 75000 | P13: =P8*Assumptions!P11 -> 0 | Q13: =Q8*Assumptions!Q11 -> 0 | R13: =R8*Assumptions!R11 -> 75000 | S13: =S8*Assumptions!S11 -> 0 | T13: =T8*Assumptions!T11 -> 0 | ... BT13: =BT8*Assumptions!BT11 -> 75000 | BV13: =SUMIF($M$3:$BT$3,BV$3,$M13:$BT13) -> 300000 | BW13: =SUMIF($M$3:$BT$3,BW$3,$M13:$BT13) -> 300000 | BX13: =SUMIF($M$3:$BT$3,BX$3,$M13:$BT13) -> 150000 | BY13: =SUMIF($M$3:$BT$3,BY$3,$M13:$BT13) -> 225000 | BZ13: =SUMIF($M$3:$BT$3,BZ$3,$M13:$BT13) -> 450000
A15: Revenue
A16: Revenue (MRR) | M16: =M11*Assumptions!M11/12 -> 6250 | N16: =N11*Assumptions!N11/12 -> 6250 | O16: =O11*Assumptions!O11/12 -> 12500 | P16: =P11*Assumptions!P11/12 -> 12500 | Q16: =Q11*Assumptions!Q11/12 -> 12500 | R16: =R11*Assumptions!R11/12 -> 18750 | S16: =S11*Assumptions!S11/12 -> 18750 | T16: =T11*Assumptions!T11/12 -> 18750 | ... BT16: =BT11*Assumptions!BT11/12 -> 125000 | BV16: =SUMIF($M$3:$BT$3,BV$3,$M16:$BT16) -> 212500 | BW16: =SUMIF($M$3:$BT$3,BW$3,$M16:$BT16) -> 512500 | BX16: =SUMIF($M$3:$BT$3,BX$3,$M16:$BT16) -> 725000 | BY16: =SUMIF($M$3:$BT$3,BY$3,$M16:$BT16) -> 918750 | BZ16: =SUMIF($M$3:$BT$3,BZ$3,$M16:$BT16) -> 1275000
A17: ARR | M17: =M16*12 -> 75000 | N17: =N16*12 -> 75000 | O17: =O16*12 -> 150000 | P17: =P16*12 -> 150000 | Q17: =Q16*12 -> 150000 | R17: =R16*12 -> 225000 | S17: =S16*12 -> 225000 | T17: =T16*12 -> 225000 | ... BT17: =BT16*12 -> 1500000

Sheet Cost Buildup
A1: Cost Buildup
A2: Cells in Orange are assumptions | M2: MONTHLY | BV2: YEARLY
A3: Year | M3: 1 | N3: 1 | O3: 1 | P3: 1 | Q3: 1 | R3: 1 | S3: 1 | T3: 1 | U3: 1 | V3: 1 | W3: 1 | X3: 1 | Y3: =X3+1 -> 2 | Z3: =Y3 -> 2 | AA3: =Z3 -> 2 | AB3: =AA3 -> 2 | AC3: =AB3 -> 2 | AD3: =AC3 -> 2 | AE3: =AD3 -> 2 | AF3: =AE3 -> 2 | AG3: =AF3 -> 2 | ... AJ3: =AI3 -> 2 | AK3: 3 | AL3: 3 | AM3: 3 | AN3: 3 | AO3: 3 | AP3: 3 | AQ3: 3 | AR3: 3 | AS3: 3 | AT3: 3 | AU3: 3 | AV3: 3 | AW3: 4 | AX3: 4 | AY3: 4 | AZ3: 4 | BA3: 4 | BB3: 4 | BC3: 4 | BD3: 4 | BE3: 4 | BF3: 4 | BG3: 4 | BH3: 4 | BI3: 5 | BJ3: 5 | BK3: 5 | BL3: 5 | BM3: 5 | BN3: 5 | BO3: 5 | BP3: 5 | BQ3: 5 | BR3: 5 | BS3: 5 | BT3: 5 | BV3: 1 | BW3: 2 | BX3: 3 | BY3: 4 | BZ3: 5
A4: Months | M4: 1 | N4: =M4+1 -> 2 | O4: =N4+1 -> 3 | P4: =O4+1 -> 4 | Q4: =P4+1 -> 5 | R4: =Q4+1 -> 6 | S4: =R4+1 -> 7 | T4: =S4+1 -> 8 | U4: =T4+1 -> 9 | ... BT4: =BS4+1 -> 60 | BV4: 12 | BW4: 24 | BX4: 36 | BY4: 48 | BZ4: 60
A5: =Assumptions!A17 -> Direct Cost
A6: =Assumptions!A18 -> Hosting & Infrastructure Costs | M6: =SUM(M7:M7) -> 375 | N6: =SUM(N7:N7) -> 375 | O6: =SUM(O7:O7) -> 750 | P6: =SUM(P7:P7) -> 750 | Q6: =SUM(Q7:Q7) -> 750 | R6: =SUM(R7:R7) -> 1125 | S6: =SUM(S7:S7) -> 1125 | T6: =SUM(T7:T7) -> 1125 | ... BT6: =SUM(BT7:BT7) -> 7500 | BV6: =SUMIF($M$3:$BT$3,BV$3,$M6:$BT6) -> 12750 | BW6: =SUMIF($M$3:$BT$3,BW$3,$M6:$BT6) -> 30750 | BX6: =SUMIF($M$3:$BT$3,BX$3,$M6:$BT6) -> 43500 | BY6: =SUMIF($M$3:$BT$3,BY$3,$M6:$BT6) -> 55125 | BZ6: =SUMIF($M$3:$BT$3,BZ$3,$M6:$BT6) -> 76500
A7: =Assumptions!A19 -> Hosting & Infrastructure Costs | M7: ='Revenue Buildup'!M16*Assumptions!M19 -> 375 | N7: ='Revenue Buildup'!N16*Assumptions!N19 -> 375 | O7: ='Revenue Buildup'!O16*Assumptions!O19 -> 750 | P7: ='Revenue Buildup'!P16*Assumptions!P19 -> 750 | Q7: ='Revenue Buildup'!Q16*Assumptions!Q19 -> 750 | R7: ='Revenue Buildup'!R16*Assumptions!R19 -> 1125 | S7: ='Revenue Buildup'!S16*Assumptions!S19 -> 1125 | T7: ='Revenue Buildup'!T16*Assumptions!T19 -> 1125 | ... BT7: ='Revenue Buildup'!BT16*Assumptions!BT19 -> 7500 | BV7: =SUMIF($M$3:$BT$3,BV$3,$M7:$BT7) -> 12750 | BW7: =SUMIF($M$3:$BT$3,BW$3,$M7:$BT7) -> 30750 | BX7: =SUMIF($M$3:$BT$3,BX$3,$M7:$BT7) -> 43500 | BY7: =SUMIF($M$3:$BT$3,BY$3,$M7:$BT7) -> 55125 | BZ7: =SUMIF($M$3:$BT$3,BZ$3,$M7:$BT7) -> 76500
A8: =Assumptions!A22 -> Headcount
A9: =Assumptions!A23 -> Customer Support | C9: Base | F9: =Assumptions!F23 -> Customer support/Account | G9: =Assumptions!G23 -> 5 | H9: =Assumptions!H23 -> 5 | M9: =Assumptions!M23 -> 5 | N9: =Assumptions!N23 -> 5 | O9: =Assumptions!O23 -> 5 | P9: =Assumptions!P23 -> 5 | Q9: =Assumptions!Q23 -> 5 | R9: =Assumptions!R23 -> 5 | S9: =Assumptions!S23 -> 5 | T9: =Assumptions!T23 -> 5 | ... BT9: =Assumptions!BT23 -> 5
A10: Customer Support | M10: =ROUND('Revenue Buildup'!M11/Assumptions!M23,0) -> 0 | N10: =ROUND('Revenue Buildup'!N11/Assumptions!N23,0) -> 0 | O10: =ROUND('Revenue Buildup'!O11/Assumptions!O23,0) -> 0 | P10: =ROUND('Revenue Buildup'!P11/Assumptions!P23,0) -> 0 | Q10: =ROUND('Revenue Buildup'!Q11/Assumptions!Q23,0) -> 0 | R10: =ROUND('Revenue Buildup'!R11/Assumptions!R23,0) -> 1 | S10: =ROUND('Revenue Buildup'!S11/Assumptions!S23,0) -> 1 | T10: =ROUND('Revenue Buildup'!T11/Assumptions!T23,0) -> 1 | ... BT10: =ROUND('Revenue Buildup'!BT11/Assumptions!BT23,0) -> 4
A11: Customer Support Team Salary
A12: =Assumptions!A24 -> Customer Support | F12: =Assumptions!F24 -> Monthly Salary | G12: =Assumptions!G24 -> 821.88564 | H12: =Assumptions!H24 -> 0.05 | I12: =Assumptions!I24 -> Annual Increment | M12: =(M10*$G$12)*(1+$H$12)^(M$3-1) -> 0 | N12: =(N10*$G$12)*(1+$H$12)^(N$3-1) -> 0 | O12: =(O10*$G$12)*(1+$H$12)^(O$3-1) -> 0 | P12: =(P10*$G$12)*(1+$H$12)^(P$3-1) -> 0 | Q12: =(Q10*$G$12)*(1+$H$12)^(Q$3-1) -> 0 | R12: =(R10*$G$12)*(1+$H$12)^(R$3-1) -> 821.88564 | S12: =(S10*$G$12)*(1+$H$12)^(S$3-1) -> 821.88564 | T12: =(T10*$G$12)*(1+$H$12)^(T$3-1) -> 821.88564 | ... BT12: =(BT10*$G$12)*(1+$H$12)^(BT$3-1) -> 3996.0285 | BV12: =SUMIF($M$3:$BT$3,BV$3,$M12:$BT12) -> 5753.1995 | BW12: =SUMIF($M$3:$BT$3,BW$3,$M12:$BT12) -> 13807.679 | BX12: =SUMIF($M$3:$BT$3,BX$3,$M12:$BT12) -> 21747.094 | BY12: =SUMIF($M$3:$BT$3,BY$3,$M12:$BT12) -> 27591.626 | BZ12: =SUMIF($M$3:$BT$3,BZ$3,$M12:$BT12) -> 40959.292
A13: Total Direct Cost | M13: =M7+M12 -> 375 | N13: =N7+N12 -> 375 | O13: =O7+O12 -> 750 | P13: =P7+P12 -> 750 | Q13: =Q7+Q12 -> 750 | R13: =R7+R12 -> 1946.8856 | S13: =S7+S12 -> 1946.8856 | T13: =T7+T12 -> 1946.8856 | ... BT13: =BT7+BT12 -> 11496.029 | BV13: =SUMIF($M$3:$BT$3,BV$3,$M13:$BT13) -> 18503.199 | BW13: =SUMIF($M$3:$BT$3,BW$3,$M13:$BT13) -> 44557.679 | BX13: =SUMIF($M$3:$BT$3,BX$3,$M13:$BT13) -> 65247.094 | BY13: =SUMIF($M$3:$BT$3,BY$3,$M13:$BT13) -> 82716.626 | BZ13: =SUMIF($M$3:$BT$3,BZ$3,$M13:$BT13) -> 117459.29
A14: =Assumptions!A25 -> Operating Expense
A15: =Assumptions!A26 -> Sales & Marketing Expense
A16: =Assumptions!A27 -> Sales
A17: =Assumptions!A28 -> Sales-SDR-Outsourced | M17: =Assumptions!M28 -> 1800 | N17: =Assumptions!N28 -> 1800 | O17: =Assumptions!O28 -> 1800 | P17: =Assumptions!P28 -> 1800 | Q17: =Assumptions!Q28 -> 1800 | R17: =Assumptions!R28 -> 1800 | S17: =Assumptions!S28 -> 1800 | T17: =Assumptions!T28 -> 1800 | ... BT17: =Assumptions!BT28 -> 1800 | BV17: =SUMIF($M$3:$BT$3,BV$3,$M17:$BT17) -> 21600 | BW17: =SUMIF($M$3:$BT$3,BW$3,$M17:$BT17) -> 21600 | BX17: =SUMIF($M$3:$BT$3,BX$3,$M17:$BT17) -> 21600 | BY17: =SUMIF($M$3:$BT$3,BY$3,$M17:$BT17) -> 21600 | BZ17: =SUMIF($M$3:$BT$3,BZ$3,$M17:$BT17) -> 21600
A18: =Assumptions!A29 -> Cost/Lead | M18: =Assumptions!M29 -> 300 | N18: =Assumptions!N29 -> 300 | O18: =Assumptions!O29 -> 300 | P18: =Assumptions!P29 -> 300 | Q18: =Assumptions!Q29 -> 300 | R18: =Assumptions!R29 -> 300 | S18: =Assumptions!S29 -> 300 | T18: =Assumptions!T29 -> 300 | ... BT18: =Assumptions!BT29 -> 300
A19: Qualified Leads | M19: =ROUND(M17/M18,0) -> 6 | N19: =ROUND(N17/N18,0) -> 6 | O19: =ROUND(O17/O18,0) -> 6 | P19: =ROUND(P17/P18,0) -> 6 | Q19: =ROUND(Q17/Q18,0) -> 6 | R19: =ROUND(R17/R18,0) -> 6 | S19: =ROUND(S17/S18,0) -> 6 | T19: =ROUND(T17/T18,0) -> 6 | ... BT19: =ROUND(BT17/BT18,0) -> 6
A20: =Assumptions!A30 -> Additional Cost for Qualified Leads | M20: =M19*Assumptions!M30 -> 1800 | N20: =N19*Assumptions!N30 -> 1800 | O20: =O19*Assumptions!O30 -> 1800 | P20: =P19*Assumptions!P30 -> 1800 | Q20: =Q19*Assumptions!Q30 -> 1800 | R20: =R19*Assumptions!R30 -> 1800 | S20: =S19*Assumptions!S30 -> 1800 | T20: =T19*Assumptions!T30 -> 1800 | ... BT20: =BT19*Assumptions!BT30 -> 1800
A21: =Assumptions!A31 -> Sales Commission %
A22: =Assumptions!A32 -> New Bookings | M22: =Assumptions!M32*'Revenue Buildup'!M13 -> 0 | N22: =Assumptions!N32*'Revenue Buildup'!N13 -> 0 | O22: =Assumptions!O32*'Revenue Buildup'!O13 -> 2250 | P22: =Assumptions!P32*'Revenue Buildup'!P13 -> 0 | Q22: =Assumptions!Q32*'Revenue Buildup'!Q13 -> 0 | R22: =Assumptions!R32*'Revenue Buildup'!R13 -> 2250 | S22: =Assumptions!S32*'Revenue Buildup'!S13 -> 0 | T22: =Assumptions!T32*'Revenue Buildup'!T13 -> 0 | ... BT22: =Assumptions!BT32*'Revenue Buildup'!BT13 -> 2250 | BV22: =SUMIF($M$3:$BT$3,BV$3,$M22:$BT22) -> 9000 | BW22: =SUMIF($M$3:$BT$3,BW$3,$M22:$BT22) -> 9000 | BX22: =SUMIF($M$3:$BT$3,BX$3,$M22:$BT22) -> 4500 | BY22: =SUMIF($M$3:$BT$3,BY$3,$M22:$BT22) -> 6750 | BZ22: =SUMIF($M$3:$BT$3,BZ$3,$M22:$BT22) -> 13500
A23: Total Commissions | M23: =SUM(M22:M22) -> 0 | N23: =SUM(N22:N22) -> 0 | O23: =SUM(O22:O22) -> 2250 | P23: =SUM(P22:P22) -> 0 | Q23: =SUM(Q22:Q22) -> 0 | R23: =SUM(R22:R22) -> 2250 | S23: =SUM(S22:S22) -> 0 | T23: =SUM(T22:T22) -> 0 | ... BT23: =SUM(BT22:BT22) -> 2250
A24: =Assumptions!A35 -> Sales Team-Headcount
A25: =Assumptions!A36 -> Client Success Manager | C25: Base | F25: =Assumptions!F36 -> Qualified Leads/CSM/Month | G25: =Assumptions!G36 -> 10 | H25: =Assumptions!H36 -> 10 | M25: =Assumptions!M36 -> 10 | N25: =Assumptions!N36 -> 10 | O25: =Assumptions!O36 -> 10 | P25: =Assumptions!P36 -> 10 | Q25: =Assumptions!Q36 -> 10 | R25: =Assumptions!R36 -> 10 | S25: =Assumptions!S36 -> 10 | T25: =Assumptions!T36 -> 10 | ... BT25: =Assumptions!BT36 -> 10
M26: =ROUND(M19/M25,0) -> 1 | N26: =ROUND(N19/N25,0) -> 1 | O26: =ROUND(O19/O25,0) -> 1 | P26: =ROUND(P19/P25,0) -> 1 | Q26: =ROUND(Q19/Q25,0) -> 1 | R26: =ROUND(R19/R25,0) -> 1 | S26: =ROUND(S19/S25,0) -> 1 | T26: =ROUND(T19/T25,0) -> 1 | ... BT26: =ROUND(BT19/BT25,0) -> 1
A27: =Assumptions!A38 -> Sales Team Salaries
A28: =Assumptions!A39 -> Client Success Manager | F28: =Assumptions!F39 -> Monthly Salary/Headcount | G28: =Assumptions!G39 -> 1200 | H28: =Assumptions!H39 -> 0.05 | I28: =Assumptions!I39 -> Annual Increment | M28: =($G28*M26)*(1+$H28)^(M$3-1) -> 1200 | N28: =($G28*N26)*(1+$H28)^(N$3-1) -> 1200 | O28: =($G28*O26)*(1+$H28)^(O$3-1) -> 1200 | P28: =($G28*P26)*(1+$H28)^(P$3-1) -> 1200 | Q28: =($G28*Q26)*(1+$H28)^(Q$3-1) -> 1200 | R28: =($G28*R26)*(1+$H28)^(R$3-1) -> 1200 | S28: =($G28*S26)*(1+$H28)^(S$3-1) -> 1200 | T28: =($G28*T26)*(1+$H28)^(T$3-1) -> 1200 | ... BT28: =($G28*BT26)*(1+$H28)^(BT$3-1) -> 1458.6075 | BV28: =SUMIF($M$3:$BT$3,BV$3,$M28:$BT28) -> 14400 | BW28: =SUMIF($M$3:$BT$3,BW$3,$M28:$BT28) -> 15120 | BX28: =SUMIF($M$3:$BT$3,BX$3,$M28:$BT28) -> 15876 | BY28: =SUMIF($M$3:$BT$3,BY$3,$M28:$BT28) -> 16669.8 | BZ28: =SUMIF($M$3:$BT$3,BZ$3,$M28:$BT28) -> 17503.29
A29: Total Sales Salary | M29: =SUM(M28:M28) -> 1200 | N29: =SUM(N28:N28) -> 1200 | O29: =SUM(O28:O28) -> 1200 | P29: =SUM(P28:P28) -> 1200 | Q29: =SUM(Q28:Q28) -> 1200 | R29: =SUM(R28:R28) -> 1200 | S29: =SUM(S28:S28) -> 1200 | T29: =SUM(T28:T28) -> 1200 | ... BT29: =SUM(BT28:BT28) -> 1458.6075 | BV29: =SUMIF($M$3:$BT$3,BV$3,$M29:$BT29) -> 14400 | BW29: =SUMIF($M$3:$BT$3,BW$3,$M29:$BT29) -> 15120 | BX29: =SUMIF($M$3:$BT$3,BX$3,$M29:$BT29) -> 15876 | BY29: =SUMIF($M$3:$BT$3,BY$3,$M29:$BT29) -> 16669.8 | BZ29: =SUMIF($M$3:$BT$3,BZ$3,$M29:$BT29) -> 17503.29
A30: Total Sales Expenses | M30: =SUM(M17,M20,M23,M29) -> 4800 | N30: =SUM(N17,N20,N23,N29) -> 4800 | O30: =SUM(O17,O20,O23,O29) -> 7050 | P30: =SUM(P17,P20,P23,P29) -> 4800 | Q30: =SUM(Q17,Q20,Q23,Q29) -> 4800 | R30: =SUM(R17,R20,R23,R29) -> 7050 | S30: =SUM(S17,S20,S23,S29) -> 4800 | T30: =SUM(T17,T20,T23,T29) -> 4800 | ... BT30: =SUM(BT17,BT20,BT23,BT29) -> 7308.6075 | BV30: =SUMIF($M$3:$BT$3,BV$3,$M30:$BT30) -> 66600 | BW30: =SUMIF($M$3:$BT$3,BW$3,$M30:$BT30) -> 67320 | BX30: =SUMIF($M$3:$BT$3,BX$3,$M30:$BT30) -> 63576 | BY30: =SUMIF($M$3:$BT$3,BY$3,$M30:$BT30) -> 66619.8 | BZ30: =SUMIF($M$3:$BT$3,BZ$3,$M30:$BT30) -> 74203.29
A31: =Assumptions!A41 -> Marketing
A32: =Assumptions!A42 -> Marketing Budget | M32: =Assumptions!M42 -> 600 | N32: =Assumptions!N42 -> 600 | O32: =Assumptions!O42 -> 600 | P32: =Assumptions!P42 -> 600 | Q32: =Assumptions!Q42 -> 600 | R32: =Assumptions!R42 -> 600 | S32: =Assumptions!S42 -> 600 | T32: =Assumptions!T42 -> 600 | ... BT32: =Assumptions!BT42 -> 840
A33: =Assumptions!A43 -> Marketing Team Roles & Headcount
A34: =Assumptions!A44 -> ABC | F34: =Assumptions!F44 -> Monthly Salary/Headcount | G34: =Assumptions!G44 -> 0 | H34: =Assumptions!H44 -> 0.05 | I34: =Assumptions!I44 -> Annual Increment | M34: =($G34*Assumptions!M44)*(1+'Cost Buildup'!$H34)^(M$3-1) -> 0 | N34: =($G34*Assumptions!N44)*(1+'Cost Buildup'!$H34)^(N$3-1) -> 0 | O34: =($G34*Assumptions!O44)*(1+'Cost Buildup'!$H34)^(O$3-1) -> 0 | P34: =($G34*Assumptions!P44)*(1+'Cost Buildup'!$H34)^(P$3-1) -> 0 | Q34: =($G34*Assumptions!Q44)*(1+'Cost Buildup'!$H34)^(Q$3-1) -> 0 | R34: =($G34*Assumptions!R44)*(1+'Cost Buildup'!$H34)^(R$3-1) -> 0 | S34: =($G34*Assumptions!S44)*(1+'Cost Buildup'!$H34)^(S$3-1) -> 0 | T34: =($G34*Assumptions!T44)*(1+'Cost Buildup'!$H34)^(T$3-1) -> 0 | ... BT34: =($G34*Assumptions!BT44)*(1+'Cost Buildup'!$H34)^(BT$3-1) -> 0 | BV34: =SUMIF($M$3:$BT$3,BV$3,$M34:$BT34) -> 0 | BW34: =SUMIF($M$3:$BT$3,BW$3,$M34:$BT34) -> 0 | BX34: =SUMIF($M$3:$BT$3,BX$3,$M34:$BT34) -> 0 | BY34: =SUMIF($M$3:$BT$3,BY$3,$M34:$BT34) -> 0 | BZ34: =SUMIF($M$3:$BT$3,BZ$3,$M34:$BT34) -> 0
A35: =Assumptions!A45 -> ABC | F35: =Assumptions!F45 -> Monthly Salary/Headcount | G35: =Assumptions!G45 -> 0 | H35: =Assumptions!H45 -> 0.05 | I35: =Assumptions!I45 -> Annual Increment | M35: =($G35*Assumptions!M45)*(1+'Cost Buildup'!$H35)^(M$3-1) -> 0 | N35: =($G35*Assumptions!N45)*(1+'Cost Buildup'!$H35)^(N$3-1) -> 0 | O35: =($G35*Assumptions!O45)*(1+'Cost Buildup'!$H35)^(O$3-1) -> 0 | P35: =($G35*Assumptions!P45)*(1+'Cost Buildup'!$H35)^(P$3-1) -> 0 | Q35: =($G35*Assumptions!Q45)*(1+'Cost Buildup'!$H35)^(Q$3-1) -> 0 | R35: =($G35*Assumptions!R45)*(1+'Cost Buildup'!$H35)^(R$3-1) -> 0 | S35: =($G35*Assumptions!S45)*(1+'Cost Buildup'!$H35)^(S$3-1) -> 0 | T35: =($G35*Assumptions!T45)*(1+'Cost Buildup'!$H35)^(T$3-1) -> 0 | ... BT35: =($G35*Assumptions!BT45)*(1+'Cost Buildup'!$H35)^(BT$3-1) -> 0 | BV35: =SUMIF($M$3:$BT$3,BV$3,$M35:$BT35) -> 0 | BW35: =SUMIF($M$3:$BT$3,BW$3,$M35:$BT35) -> 0 | BX35: =SUMIF($M$3:$BT$3,BX$3,$M35:$BT35) -> 0 | BY35: =SUMIF($M$3:$BT$3,BY$3,$M35:$BT35) -> 0 | BZ35: =SUMIF($M$3:$BT$3,BZ$3,$M35:$BT35) -> 0
A36: =Assumptions!A46 -> ABC | F36: =Assumptions!F46 -> Monthly Salary/Headcount | G36: =Assumptions!G46 -> 0 | H36: =Assumptions!H46 -> 0.05 | I36: =Assumptions!I46 -> Annual Increment | M36: =($G36*Assumptions!M46)*(1+'Cost Buildup'!$H36)^(M$3-1) -> 0 | N36: =($G36*Assumptions!N46)*(1+'Cost Buildup'!$H36)^(N$3-1) -> 0 | O36: =($G36*Assumptions!O46)*(1+'Cost Buildup'!$H36)^(O$3-1) -> 0 | P36: =($G36*Assumptions!P46)*(1+'Cost Buildup'!$H36)^(P$3-1) -> 0 | Q36: =($G36*Assumptions!Q46)*(1+'Cost Buildup'!$H36)^(Q$3-1) -> 0 | R36: =($G36*Assumptions!R46)*(1+'Cost Buildup'!$H36)^(R$3-1) -> 0 | S36: =($G36*Assumptions!S46)*(1+'Cost Buildup'!$H36)^(S$3-1) -> 0 | T36: =($G36*Assumptions!T46)*(1+'Cost Buildup'!$H36)^(T$3-1) -> 0 | ... BT36: =($G36*Assumptions!BT46)*(1+'Cost Buildup'!$H36)^(BT$3-1) -> 0 | BV36: =SUMIF($M$3:$BT$3,BV$3,$M36:$BT36) -> 0 | BW36: =SUMIF($M$3:$BT$3,BW$3,$M36:$BT36) -> 0 | BX36: =SUMIF($M$3:$BT$3,BX$3,$M36:$BT36) -> 0 | BY36: =SUMIF($M$3:$BT$3,BY$3,$M36:$BT36) -> 0 | BZ36: =SUMIF($M$3:$BT$3,BZ$3,$M36:$BT36) -> 0
A37: =Assumptions!A47 -> ABC | F37: =Assumptions!F47 -> Monthly Salary/Headcount | G37: =Assumptions!G47 -> 0 | H37: =Assumptions!H47 -> 0.05 | I37: =Assumptions!I47 -> Annual Increment | M37: =($G37*Assumptions!M47)*(1+'Cost Buildup'!$H37)^(M$3-1) -> 0 | N37: =($G37*Assumptions!N47)*(1+'Cost Buildup'!$H37)^(N$3-1) -> 0 | O37: =($G37*Assumptions!O47)*(1+'Cost Buildup'!$H37)^(O$3-1) -> 0 | P37: =($G37*Assumptions!P47)*(1+'Cost Buildup'!$H37)^(P$3-1) -> 0 | Q37: =($G37*Assumptions!Q47)*(1+'Cost Buildup'!$H37)^(Q$3-1) -> 0 | R37: =($G37*Assumptions!R47)*(1+'Cost Buildup'!$H37)^(R$3-1) -> 0 | S37: =($G37*Assumptions!S47)*(1+'Cost Buildup'!$H37)^(S$3-1) -> 0 | T37: =($G37*Assumptions!T47)*(1+'Cost Buildup'!$H37)^(T$3-1) -> 0 | ... BT37: =($G37*Assumptions!BT47)*(1+'Cost Buildup'!$H37)^(BT$3-1) -> 0 | BV37: =SUMIF($M$3:$BT$3,BV$3,$M37:$BT37) -> 0 | BW37: =SUMIF($M$3:$BT$3,BW$3,$M37:$BT37) -> 0 | BX37: =SUMIF($M$3:$BT$3,BX$3,$M37:$BT37) -> 0 | BY37: =SUMIF($M$3:$BT$3,BY$3,$M37:$BT37) -> 0 | BZ37: =SUMIF($M$3:$BT$3,BZ$3,$M37:$BT37) -> 0
A38: =Assumptions!A48 -> ABC | F38: =Assumptions!F48 -> Monthly Salary/Headcount
A39: =Assumptions!A49 -> ABC | F39: =Assumptions!F49 -> Monthly Salary/Headcount
A40: Total Marketing Salary | M40: =SUM(M34:M37) -> 0 | N40: =SUM(N34:N37) -> 0 | O40: =SUM(O34:O37) -> 0 | P40: =SUM(P34:P37) -> 0 | Q40: =SUM(Q34:Q37) -> 0 | R40: =SUM(R34:R37) -> 0 | S40: =SUM(S34:S37) -> 0 | T40: =SUM(T34:T37) -> 0 | ... BT40: =SUM(BT34:BT37) -> 0 | BV40: =SUMIF($M$3:$BT$3,BV$3,$M40:$BT40) -> 0 | BW40: =SUMIF($M$3:$BT$3,BW$3,$M40:$BT40) -> 0 | BX40: =SUMIF($M$3:$BT$3,BX$3,$M40:$BT40) -> 0 | BY40: =SUMIF($M$3:$BT$3,BY$3,$M40:$BT40) -> 0 | BZ40: =SUMIF($M$3:$BT$3,BZ$3,$M40:$BT40) -> 0
A41: Total Marketing Expense | M41: =M40+M32 -> 600 | N41: =N40+N32 -> 600 | O41: =O40+O32 -> 600 | P41: =P40+P32 -> 600 | Q41: =Q40+Q32 -> 600 | R41: =R40+R32 -> 600 | S41: =S40+S32 -> 600 | T41: =T40+T32 -> 600 | ... BT41: =BT40+BT32 -> 840 | BV41: =SUMIF($M$3:$BT$3,BV$3,$M41:$BT41) -> 7200 | BW41: =SUMIF($M$3:$BT$3,BW$3,$M41:$BT41) -> 7200 | BX41: =SUMIF($M$3:$BT$3,BX$3,$M41:$BT41) -> 10080 | BY41: =SUMIF($M$3:$BT$3,BY$3,$M41:$BT41) -> 10080 | BZ41: =SUMIF($M$3:$BT$3,BZ$3,$M41:$BT41) -> 10080
A42: =Assumptions!A50 -> G&A
A43: =Assumptions!A51 -> Office Rent | F43: =Assumptions!F51 -> Chair/Employee/Monthly | G43: =Assumptions!G51 -> 82.188564 | H43: =Assumptions!H51 -> 109.98684 | M43: =Assumptions!M51*M97 -> 1068.4513 | N43: =Assumptions!N51*N97 -> 1074.5764 | O43: =Assumptions!O51*O97 -> 1080.7014 | P43: =Assumptions!P51*P97 -> 1086.8265 | Q43: =Assumptions!Q51*Q97 -> 1092.9515 | R43: =Assumptions!R51*R97 -> 1183.6209 | S43: =Assumptions!S51*S97 -> 1275.2326 | T43: =Assumptions!T51*T97 -> 1282.3 | ... BT43: =Assumptions!BT51*BT97 -> 3079.6315 | BV43: =SUMIF($M$3:$BT$3,BV$3,$M43:$BT43) -> 14344.534 | BW43: =SUMIF($M$3:$BT$3,BW$3,$M43:$BT43) -> 18817.772 | BX43: =SUMIF($M$3:$BT$3,BX$3,$M43:$BT43) -> 20853.623 | BY43: =SUMIF($M$3:$BT$3,BY$3,$M43:$BT43) -> 23714.035 | BZ43: =SUMIF($M$3:$BT$3,BZ$3,$M43:$BT43) -> 28619.966
A44: =Assumptions!A52 -> Utilities | F44: =Assumptions!F52 -> Emp/Monthly | G44: =Assumptions!G52 -> 58.706117 | H44: =Assumptions!H52 -> 78.562028 | M44: =Assumptions!M52*M97 -> 763.17952 | N44: =Assumptions!N52*N97 -> 767.55455 | O44: =Assumptions!O52*O97 -> 771.92959 | P44: =Assumptions!P52*P97 -> 776.30462 | Q44: =Assumptions!Q52*Q97 -> 780.67965 | R44: =Assumptions!R52*R97 -> 845.4435 | S44: =Assumptions!S52*S97 -> 910.88043 | T44: =Assumptions!T52*T97 -> 915.92855 | ... BT44: =Assumptions!BT52*BT97 -> 2199.7368 | BV44: =SUMIF($M$3:$BT$3,BV$3,$M44:$BT44) -> 10246.096 | BW44: =SUMIF($M$3:$BT$3,BW$3,$M44:$BT44) -> 13441.266 | BX44: =SUMIF($M$3:$BT$3,BX$3,$M44:$BT44) -> 14895.445 | BY44: =SUMIF($M$3:$BT$3,BY$3,$M44:$BT44) -> 16938.597 | BZ44: =SUMIF($M$3:$BT$3,BZ$3,$M44:$BT44) -> 20442.833
A45: =Assumptions!A53 -> Advisory | M45: =Assumptions!$G$53 -> 2583.0692 | N45: =Assumptions!$G$53 -> 2583.0692 | O45: =Assumptions!$G$53 -> 2583.0692 | P45: =Assumptions!$G$53 -> 2583.0692 | Q45: =Assumptions!$G$53 -> 2583.0692 | R45: =Assumptions!$G$53 -> 2583.0692 | S45: =Assumptions!$G$53 -> 2583.0692 | T45: =Assumptions!$G$53 -> 2583.0692 | ... BT45: =Assumptions!$G$53 -> 2583.0692 | BV45: =SUMIF($M$3:$BT$3,BV$3,$M45:$BT45) -> 30996.83 | BW45: =SUMIF($M$3:$BT$3,BW$3,$M45:$BT45) -> 30996.83 | BX45: =SUMIF($M$3:$BT$3,BX$3,$M45:$BT45) -> 30996.83 | BY45: =SUMIF($M$3:$BT$3,BY$3,$M45:$BT45) -> 30996.83 | BZ45: =SUMIF($M$3:$BT$3,BZ$3,$M45:$BT45) -> 30996.83
A46: =Assumptions!A54 -> G&A Team Roles & Headcount
A47: =Assumptions!A55 -> Account & Finance | F47: =Assumptions!F55 -> Monthly Salary/Headcount | G47: =Assumptions!G55 -> 469.64894 | H47: =Assumptions!H55 -> 0.05 | I47: =Assumptions!I55 -> Annual Increment | M47: =($G47*Assumptions!M55)*(1+'Cost Buildup'!$H47)^(M$3-1) -> 469.64894 | N47: =($G47*Assumptions!N55)*(1+'Cost Buildup'!$H47)^(N$3-1) -> 469.64894 | O47: =($G47*Assumptions!O55)*(1+'Cost Buildup'!$H47)^(O$3-1) -> 469.64894 | P47: =($G47*Assumptions!P55)*(1+'Cost Buildup'!$H47)^(P$3-1) -> 469.64894 | Q47: =($G47*Assumptions!Q55)*(1+'Cost Buildup'!$H47)^(Q$3-1) -> 469.64894 | R47: =($G47*Assumptions!R55)*(1+'Cost Buildup'!$H47)^(R$3-1) -> 469.64894 | S47: =($G47*Assumptions!S55)*(1+'Cost Buildup'!$H47)^(S$3-1) -> 469.64894 | T47: =($G47*Assumptions!T55)*(1+'Cost Buildup'!$H47)^(T$3-1) -> 469.64894 | ... BT47: =($G47*Assumptions!BT55)*(1+'Cost Buildup'!$H47)^(BT$3-1) -> 1141.7224 | BV47: =SUMIF($M$3:$BT$3,BV$3,$M47:$BT47) -> 5635.7872 | BW47: =SUMIF($M$3:$BT$3,BW$3,$M47:$BT47) -> 11835.153 | BX47: =SUMIF($M$3:$BT$3,BX$3,$M47:$BT47) -> 12426.911 | BY47: =SUMIF($M$3:$BT$3,BY$3,$M47:$BT47) -> 13048.256 | BZ47: =SUMIF($M$3:$BT$3,BZ$3,$M47:$BT47) -> 13700.669
A48: =Assumptions!A56 -> Legal | F48: =Assumptions!F56 -> Monthly Salary/Headcount | G48: =Assumptions!G56 -> 293.53059 | H48: =Assumptions!H56 -> 0 | I48: =Assumptions!I56 -> Annual Increment | M48: =($G48*Assumptions!M56)*(1+'Cost Buildup'!$H48)^(M$3-1) -> 293.53059 | N48: =($G48*Assumptions!N56)*(1+'Cost Buildup'!$H48)^(N$3-1) -> 293.53059 | O48: =($G48*Assumptions!O56)*(1+'Cost Buildup'!$H48)^(O$3-1) -> 293.53059 | P48: =($G48*Assumptions!P56)*(1+'Cost Buildup'!$H48)^(P$3-1) -> 293.53059 | Q48: =($G48*Assumptions!Q56)*(1+'Cost Buildup'!$H48)^(Q$3-1) -> 293.53059 | R48: =($G48*Assumptions!R56)*(1+'Cost Buildup'!$H48)^(R$3-1) -> 293.53059 | S48: =($G48*Assumptions!S56)*(1+'Cost Buildup'!$H48)^(S$3-1) -> 293.53059 | T48: =($G48*Assumptions!T56)*(1+'Cost Buildup'!$H48)^(T$3-1) -> 293.53059 | ... BT48: =($G48*Assumptions!BT56)*(1+'Cost Buildup'!$H48)^(BT$3-1) -> 587.06117 | BV48: =SUMIF($M$3:$BT$3,BV$3,$M48:$BT48) -> 3522.367 | BW48: =SUMIF($M$3:$BT$3,BW$3,$M48:$BT48) -> 7044.7341 | BX48: =SUMIF($M$3:$BT$3,BX$3,$M48:$BT48) -> 7044.7341 | BY48: =SUMIF($M$3:$BT$3,BY$3,$M48:$BT48) -> 7044.7341 | BZ48: =SUMIF($M$3:$BT$3,BZ$3,$M48:$BT48) -> 7044.7341
A49: =Assumptions!A57 -> HR | F49: =Assumptions!F57 -> Monthly Salary/Headcount | G49: =Assumptions!G57 -> 704.47341 | H49: =Assumptions!H57 -> 0.05 | I49: =Assumptions!I57 -> Annual Increment | M49: =($G49*Assumptions!M57)*(1+'Cost Buildup'!$H49)^(M$3-1) -> 0 | N49: =($G49*Assumptions!N57)*(1+'Cost Buildup'!$H49)^(N$3-1) -> 0 | O49: =($G49*Assumptions!O57)*(1+'Cost Buildup'!$H49)^(O$3-1) -> 0 | P49: =($G49*Assumptions!P57)*(1+'Cost Buildup'!$H49)^(P$3-1) -> 0 | Q49: =($G49*Assumptions!Q57)*(1+'Cost Buildup'!$H49)^(Q$3-1) -> 0 | R49: =($G49*Assumptions!R57)*(1+'Cost Buildup'!$H49)^(R$3-1) -> 0 | S49: =($G49*Assumptions!S57)*(1+'Cost Buildup'!$H49)^(S$3-1) -> 704.47341 | T49: =($G49*Assumptions!T57)*(1+'Cost Buildup'!$H49)^(T$3-1) -> 704.47341 | ... BT49: =($G49*Assumptions!BT57)*(1+'Cost Buildup'!$H49)^(BT$3-1) -> 856.29183 | BV49: =SUMIF($M$3:$BT$3,BV$3,$M49:$BT49) -> 4226.8404 | BW49: =SUMIF($M$3:$BT$3,BW$3,$M49:$BT49) -> 8876.3649 | BX49: =SUMIF($M$3:$BT$3,BX$3,$M49:$BT49) -> 9320.1832 | BY49: =SUMIF($M$3:$BT$3,BY$3,$M49:$BT49) -> 9786.1923 | BZ49: =SUMIF($M$3:$BT$3,BZ$3,$M49:$BT49) -> 10275.502
A50: =Assumptions!A58 -> Management-Co-Found | F50: =Assumptions!F58 -> Monthly Salary/Headcount | G50: =Assumptions!G58 -> 2583.0692 | H50: =Assumptions!H58 -> 0 | M50: =($G50*Assumptions!M58)*(1+'Cost Buildup'!$H50)^(M$3-1) -> 2583.0692 | N50: =($G50*Assumptions!N58)*(1+'Cost Buildup'!$H50)^(N$3-1) -> 2583.0692 | O50: =($G50*Assumptions!O58)*(1+'Cost Buildup'!$H50)^(O$3-1) -> 2583.0692 | P50: =($G50*Assumptions!P58)*(1+'Cost Buildup'!$H50)^(P$3-1) -> 2583.0692 | Q50: =($G50*Assumptions!Q58)*(1+'Cost Buildup'!$H50)^(Q$3-1) -> 2583.0692 | R50: =($G50*Assumptions!R58)*(1+'Cost Buildup'!$H50)^(R$3-1) -> 2583.0692 | S50: =($G50*Assumptions!S58)*(1+'Cost Buildup'!$H50)^(S$3-1) -> 2583.0692 | T50: =($G50*Assumptions!T58)*(1+'Cost Buildup'!$H50)^(T$3-1) -> 2583.0692 | ... BT50: =($G50*Assumptions!BT58)*(1+'Cost Buildup'!$H50)^(BT$3-1) -> 2583.0692
A51: =Assumptions!A59 -> Management-Co-Found | F51: =Assumptions!F59 -> Monthly Salary/Headcount | G51: =Assumptions!G59 -> 2583.0692 | H51: =Assumptions!H59 -> 0 | M51: =($G51*Assumptions!M59)*(1+'Cost Buildup'!$H51)^(M$3-1) -> 2583.0692 | N51: =($G51*Assumptions!N59)*(1+'Cost Buildup'!$H51)^(N$3-1) -> 2583.0692 | O51: =($G51*Assumptions!O59)*(1+'Cost Buildup'!$H51)^(O$3-1) -> 2583.0692 | P51: =($G51*Assumptions!P59)*(1+'Cost Buildup'!$H51)^(P$3-1) -> 2583.0692 | Q51: =($G51*Assumptions!Q59)*(1+'Cost Buildup'!$H51)^(Q$3-1) -> 2583.0692 | R51: =($G51*Assumptions!R59)*(1+'Cost Buildup'!$H51)^(R$3-1) -> 2583.0692 | S51: =($G51*Assumptions!S59)*(1+'Cost Buildup'!$H51)^(S$3-1) -> 2583.0692 | T51: =($G51*Assumptions!T59)*(1+'Cost Buildup'!$H51)^(T$3-1) -> 2583.0692 | ... BT51: =($G51*Assumptions!BT59)*(1+'Cost Buildup'!$H51)^(BT$3-1) -> 2583.0692
A52: Total G&A Salary | M52: =SUM(M47:M51) -> 5929.3178 | N52: =SUM(N47:N51) -> 5929.3178 | O52: =SUM(O47:O51) -> 5929.3178 | P52: =SUM(P47:P51) -> 5929.3178 | Q52: =SUM(Q47:Q51) -> 5929.3178 | R52: =SUM(R47:R51) -> 5929.3178 | S52: =SUM(S47:S51) -> 6633.7912 | T52: =SUM(T47:T51) -> 6633.7912 | ... BT52: =SUM(BT47:BT51) -> 7751.2137 | BV52: =SUMIF($M$3:$BT$3,BV$3,$M52:$BT52) -> 75378.654 | BW52: =SUMIF($M$3:$BT$3,BW$3,$M52:$BT52) -> 89749.912 | BX52: =SUMIF($M$3:$BT$3,BX$3,$M52:$BT52) -> 90785.488 | BY52: =SUMIF($M$3:$BT$3,BY$3,$M52:$BT52) -> 91872.843 | BZ52: =SUMIF($M$3:$BT$3,BZ$3,$M52:$BT52) -> 93014.565
A53: Total G&A Expense | M53: =M43+M44+M52+M45 -> 10344.018 | N53: =N43+N44+N52+N45 -> 10354.518 | O53: =O43+O44+O52+O45 -> 10365.018 | P53: =P43+P44+P52+P45 -> 10375.518 | Q53: =Q43+Q44+Q52+Q45 -> 10386.018 | R53: =R43+R44+R52+R45 -> 10541.451 | S53: =S43+S44+S52+S45 -> 11402.973 | T53: =T43+T44+T52+T45 -> 11415.089 | ... BT53: =BT43+BT44+BT52+BT45 -> 15613.651 | BV53: =SUMIF($M$3:$BT$3,BV$3,$M53:$BT53) -> 130966.11 | BW53: =SUMIF($M$3:$BT$3,BW$3,$M53:$BT53) -> 153005.78 | BX53: =SUMIF($M$3:$BT$3,BX$3,$M53:$BT53) -> 157531.38 | BY53: =SUMIF($M$3:$BT$3,BY$3,$M53:$BT53) -> 163522.3 | BZ53: =SUMIF($M$3:$BT$3,BZ$3,$M53:$BT53) -> 173074.19
A54: =Assumptions!A60 -> Product Development Expense
A55: =Assumptions!A61 -> Infrastructure | M55: =Assumptions!M61 -> 1585.0652 | N55: =Assumptions!N61 -> 1616.7665 | O55: =Assumptions!O61 -> 1649.1018 | P55: =Assumptions!P61 -> 1682.0838 | Q55: =Assumptions!Q61 -> 1715.7255 | R55: =Assumptions!R61 -> 1750.04 | S55: =Assumptions!S61 -> 1785.0408 | T55: =Assumptions!T61 -> 1820.7416 | ... BT55: =Assumptions!BT61 -> 5098.6741 | BV55: =SUMIF($M$3:$BT$3,BV$3,$M55:$BT55) -> 21259.036 | BW55: =SUMIF($M$3:$BT$3,BW$3,$M55:$BT55) -> 26961.598 | BX55: =SUMIF($M$3:$BT$3,BX$3,$M55:$BT55) -> 34193.826 | BY55: =SUMIF($M$3:$BT$3,BY$3,$M55:$BT55) -> 43366.039 | BZ55: =SUMIF($M$3:$BT$3,BZ$3,$M55:$BT55) -> 54998.623
A56: =Assumptions!A62 -> Product Development Team Roles & Headcount
A57: =Assumptions!A63 -> Project Manager | F57: =Assumptions!F63 -> Monthly Salary | G57: =Assumptions!G63 -> 2000 | H57: =Assumptions!H63 -> 0.1 | I57: =Assumptions!I63 -> Annual Increment | M57: =($G57*Assumptions!M63)*(1+'Cost Buildup'!$H57)^(M$3-1) -> 2000 | N57: =($G57*Assumptions!N63)*(1+'Cost Buildup'!$H57)^(N$3-1) -> 2000 | O57: =($G57*Assumptions!O63)*(1+'Cost Buildup'!$H57)^(O$3-1) -> 2000 | P57: =($G57*Assumptions!P63)*(1+'Cost Buildup'!$H57)^(P$3-1) -> 2000 | Q57: =($G57*Assumptions!Q63)*(1+'Cost Buildup'!$H57)^(Q$3-1) -> 2000 | R57: =($G57*Assumptions!R63)*(1+'Cost Buildup'!$H57)^(R$3-1) -> 2000 | S57: =($G57*Assumptions!S63)*(1+'Cost Buildup'!$H57)^(S$3-1) -> 2000 | T57: =($G57*Assumptions!T63)*(1+'Cost Buildup'!$H57)^(T$3-1) -> 2000 | ... BT57: =($G57*Assumptions!BT63)*(1+'Cost Buildup'!$H57)^(BT$3-1) -> 5856.4 | BV57: =SUMIF($M$3:$BT$3,BV$3,$M57:$BT57) -> 24000 | BW57: =SUMIF($M$3:$BT$3,BW$3,$M57:$BT57) -> 26400 | BX57: =SUMIF($M$3:$BT$3,BX$3,$M57:$BT57) -> 31460 | BY57: =SUMIF($M$3:$BT$3,BY$3,$M57:$BT57) -> 63888 | BZ57: =SUMIF($M$3:$BT$3,BZ$3,$M57:$BT57) -> 70276.8
A58: =Assumptions!A64 -> UI,UX Designer | F58: =Assumptions!F64 -> Monthly Salary | G58: =Assumptions!G64 -> 1408.9468 | H58: =Assumptions!H64 -> 0.1 | I58: =Assumptions!I64 -> Annual Increment | M58: =($G58*Assumptions!M64)*(1+'Cost Buildup'!$H58)^(M$3-1) -> 1408.9468 | N58: =($G58*Assumptions!N64)*(1+'Cost Buildup'!$H58)^(N$3-1) -> 1408.9468 | O58: =($G58*Assumptions!O64)*(1+'Cost Buildup'!$H58)^(O$3-1) -> 1408.9468 | P58: =($G58*Assumptions!P64)*(1+'Cost Buildup'!$H58)^(P$3-1) -> 1408.9468 | Q58: =($G58*Assumptions!Q64)*(1+'Cost Buildup'!$H58)^(Q$3-1) -> 1408.9468 | R58: =($G58*Assumptions!R64)*(1+'Cost Buildup'!$H58)^(R$3-1) -> 1408.9468 | S58: =($G58*Assumptions!S64)*(1+'Cost Buildup'!$H58)^(S$3-1) -> 1408.9468 | T58: =($G58*Assumptions!T64)*(1+'Cost Buildup'!$H58)^(T$3-1) -> 1408.9468 | ... BT58: =($G58*Assumptions!BT64)*(1+'Cost Buildup'!$H58)^(BT$3-1) -> 4125.6781
A59: =Assumptions!A65 -> Sr. Software | F59: =Assumptions!F65 -> Monthly Salary | G59: =Assumptions!G65 -> 2500 | H59: =Assumptions!H65 -> 0.1 | I59: =Assumptions!I65 -> Annual Increment | M59: =($G59*Assumptions!M65)*(1+'Cost Buildup'!$H59)^(M$3-1) -> 2500 | N59: =($G59*Assumptions!N65)*(1+'Cost Buildup'!$H59)^(N$3-1) -> 2500 | O59: =($G59*Assumptions!O65)*(1+'Cost Buildup'!$H59)^(O$3-1) -> 2500 | P59: =($G59*Assumptions!P65)*(1+'Cost Buildup'!$H59)^(P$3-1) -> 2500 | Q59: =($G59*Assumptions!Q65)*(1+'Cost Buildup'!$H59)^(Q$3-1) -> 2500 | R59: =($G59*Assumptions!R65)*(1+'Cost Buildup'!$H59)^(R$3-1) -> 2500 | S59: =($G59*Assumptions!S65)*(1+'Cost Buildup'!$H59)^(S$3-1) -> 2500 | T59: =($G59*Assumptions!T65)*(1+'Cost Buildup'!$H59)^(T$3-1) -> 2500 | ... BT59: =($G59*Assumptions!BT65)*(1+'Cost Buildup'!$H59)^(BT$3-1) -> 7320.5
A60: =Assumptions!A66 -> Solution Architect | F60: =Assumptions!F66 -> Monthly Salary | G60: =Assumptions!G66 -> 3000 | H60: =Assumptions!H66 -> 0.1 | I60: =Assumptions!I66 -> Annual Increment | M60: =($G60*Assumptions!M66)*(1+'Cost Buildup'!$H60)^(M$3-1) -> 3000 | N60: =($G60*Assumptions!N66)*(1+'Cost Buildup'!$H60)^(N$3-1) -> 3000 | O60: =($G60*Assumptions!O66)*(1+'Cost Buildup'!$H60)^(O$3-1) -> 3000 | P60: =($G60*Assumptions!P66)*(1+'Cost Buildup'!$H60)^(P$3-1) -> 3000 | Q60: =($G60*Assumptions!Q66)*(1+'Cost Buildup'!$H60)^(Q$3-1) -> 3000 | R60: =($G60*Assumptions!R66)*(1+'Cost Buildup'!$H60)^(R$3-1) -> 3000 | S60: =($G60*Assumptions!S66)*(1+'Cost Buildup'!$H60)^(S$3-1) -> 3000 | T60: =($G60*Assumptions!T66)*(1+'Cost Buildup'!$H60)^(T$3-1) -> 3000 | ... BT60: =($G60*Assumptions!BT66)*(1+'Cost Buildup'!$H60)^(BT$3-1) -> 8784.6
A61: =Assumptions!A67 -> Test Er | F61: =Assumptions!F67 -> Monthly Salary | G61: =Assumptions!G67 -> 1174.1223 | H61: =Assumptions!H67 -> 0.1 | I61: =Assumptions!I67 -> Annual Increment | M61: =($G61*Assumptions!M67)*(1+'Cost Buildup'!$H61)^(M$3-1) -> 1174.1223 | N61: =($G61*Assumptions!N67)*(1+'Cost Buildup'!$H61)^(N$3-1) -> 1174.1223 | O61: =($G61*Assumptions!O67)*(1+'Cost Buildup'!$H61)^(O$3-1) -> 1174.1223 | P61: =($G61*Assumptions!P67)*(1+'Cost Buildup'!$H61)^(P$3-1) -> 1174.1223 | Q61: =($G61*Assumptions!Q67)*(1+'Cost Buildup'!$H61)^(Q$3-1) -> 1174.1223 | R61: =($G61*Assumptions!R67)*(1+'Cost Buildup'!$H61)^(R$3-1) -> 1174.1223 | S61: =($G61*Assumptions!S67)*(1+'Cost Buildup'!$H61)^(S$3-1) -> 1174.1223 | T61: =($G61*Assumptions!T67)*(1+'Cost Buildup'!$H61)^(T$3-1) -> 1174.1223 | ... BT61: =($G61*Assumptions!BT67)*(1+'Cost Buildup'!$H61)^(BT$3-1) -> 3438.065
A62: =Assumptions!A68 -> Jr. Test Er | F62: =Assumptions!F68 -> Monthly Salary | G62: =Assumptions!G68 -> 821.88564 | H62: =Assumptions!H68 -> 0.1 | I62: =Assumptions!I68 -> Annual Increment | M62: =($G62*Assumptions!M68)*(1+'Cost Buildup'!$H62)^(M$3-1) -> 821.88564 | N62: =($G62*Assumptions!N68)*(1+'Cost Buildup'!$H62)^(N$3-1) -> 821.88564 | O62: =($G62*Assumptions!O68)*(1+'Cost Buildup'!$H62)^(O$3-1) -> 821.88564 | P62: =($G62*Assumptions!P68)*(1+'Cost Buildup'!$H62)^(P$3-1) -> 821.88564 | Q62: =($G62*Assumptions!Q68)*(1+'Cost Buildup'!$H62)^(Q$3-1) -> 821.88564 | R62: =($G62*Assumptions!R68)*(1+'Cost Buildup'!$H62)^(R$3-1) -> 821.88564 | S62: =($G62*Assumptions!S68)*(1+'Cost Buildup'!$H62)^(S$3-1) -> 821.88564 | T62: =($G62*Assumptions!T68)*(1+'Cost Buildup'!$H62)^(T$3-1) -> 821.88564 | ... BT62: =($G62*Assumptions!BT68)*(1+'Cost Buildup'!$H62)^(BT$3-1) -> 2406.6455
A63: =Assumptions!A69 -> Infra Er | F63: =Assumptions!F69 -> Monthly Salary | G63: =Assumptions!G69 -> 1408.9468 | H63: =Assumptions!H69 -> 0.1 | I63: =Assumptions!I69 -> Annual Increment | M63: =($G63*Assumptions!M69)*(1+'Cost Buildup'!$H63)^(M$3-1) -> 1408.9468 | N63: =($G63*Assumptions!N69)*(1+'Cost Buildup'!$H63)^(N$3-1) -> 1408.9468 | O63: =($G63*Assumptions!O69)*(1+'Cost Buildup'!$H63)^(O$3-1) -> 1408.9468 | P63: =($G63*Assumptions!P69)*(1+'Cost Buildup'!$H63)^(P$3-1) -> 1408.9468 | Q63: =($G63*Assumptions!Q69)*(1+'Cost Buildup'!$H63)^(Q$3-1) -> 1408.9468 | R63: =($G63*Assumptions!R69)*(1+'Cost Buildup'!$H63)^(R$3-1) -> 1408.9468 | S63: =($G63*Assumptions!S69)*(1+'Cost Buildup'!$H63)^(S$3-1) -> 1408.9468 | T63: =($G63*Assumptions!T69)*(1+'Cost Buildup'!$H63)^(T$3-1) -> 1408.9468 | ... BT63: =($G63*Assumptions!BT69)*(1+'Cost Buildup'!$H63)^(BT$3-1) -> 4125.6781
A64: =Assumptions!A70 -> Jr. Infra Er | F64: =Assumptions!F70 -> Monthly Salary | G64: =Assumptions!G70 -> 763.17952 | H64: =Assumptions!H70 -> 0.1 | I64: =Assumptions!I70 -> Annual Increment | M64: =($G64*Assumptions!M70)*(1+'Cost Buildup'!$H64)^(M$3-1) -> 763.17952 | N64: =($G64*Assumptions!N70)*(1+'Cost Buildup'!$H64)^(N$3-1) -> 763.17952 | O64: =($G64*Assumptions!O70)*(1+'Cost Buildup'!$H64)^(O$3-1) -> 763.17952 | P64: =($G64*Assumptions!P70)*(1+'Cost Buildup'!$H64)^(P$3-1) -> 763.17952 | Q64: =($G64*Assumptions!Q70)*(1+'Cost Buildup'!$H64)^(Q$3-1) -> 763.17952 | R64: =($G64*Assumptions!R70)*(1+'Cost Buildup'!$H64)^(R$3-1) -> 763.17952 | S64: =($G64*Assumptions!S70)*(1+'Cost Buildup'!$H64)^(S$3-1) -> 763.17952 | T64: =($G64*Assumptions!T70)*(1+'Cost Buildup'!$H64)^(T$3-1) -> 763.17952 | ... BT64: =($G64*Assumptions!BT70)*(1+'Cost Buildup'!$H64)^(BT$3-1) -> 2234.7423
A65: =Assumptions!A71 -> Frontend Developer | F65: =Assumptions!F71 -> Monthly Salary | G65: =Assumptions!G71 -> 1000 | H65: =Assumptions!H71 -> 0.1 | I65: =Assumptions!I71 -> Annual Increment | M65: =($G65*Assumptions!M71)*(1+'Cost Buildup'!$H65)^(M$3-1) -> 1000 | N65: =($G65*Assumptions!N71)*(1+'Cost Buildup'!$H65)^(N$3-1) -> 1000 | O65: =($G65*Assumptions!O71)*(1+'Cost Buildup'!$H65)^(O$3-1) -> 1000 | P65: =($G65*Assumptions!P71)*(1+'Cost Buildup'!$H65)^(P$3-1) -> 1000 | Q65: =($G65*Assumptions!Q71)*(1+'Cost Buildup'!$H65)^(Q$3-1) -> 1000 | R65: =($G65*Assumptions!R71)*(1+'Cost Buildup'!$H65)^(R$3-1) -> 1000 | S65: =($G65*Assumptions!S71)*(1+'Cost Buildup'!$H65)^(S$3-1) -> 1000 | T65: =($G65*Assumptions!T71)*(1+'Cost Buildup'!$H65)^(T$3-1) -> 1000 | ... BT65: =($G65*Assumptions!BT71)*(1+'Cost Buildup'!$H65)^(BT$3-1) -> 2928.2
A66: =Assumptions!A72 -> Backend Developer | F66: =Assumptions!F72 -> Monthly Salary | G66: =Assumptions!G72 -> 1000 | H66: =Assumptions!H72 -> 0.1 | I66: =Assumptions!I72 -> Annual Increment | M66: =($G66*Assumptions!M72)*(1+'Cost Buildup'!$H66)^(M$3-1) -> 1000 | N66: =($G66*Assumptions!N72)*(1+'Cost Buildup'!$H66)^(N$3-1) -> 1000 | O66: =($G66*Assumptions!O72)*(1+'Cost Buildup'!$H66)^(O$3-1) -> 1000 | P66: =($G66*Assumptions!P72)*(1+'Cost Buildup'!$H66)^(P$3-1) -> 1000 | Q66: =($G66*Assumptions!Q72)*(1+'Cost Buildup'!$H66)^(Q$3-1) -> 1000 | R66: =($G66*Assumptions!R72)*(1+'Cost Buildup'!$H66)^(R$3-1) -> 1000 | S66: =($G66*Assumptions!S72)*(1+'Cost Buildup'!$H66)^(S$3-1) -> 1000 | T66: =($G66*Assumptions!T72)*(1+'Cost Buildup'!$H66)^(T$3-1) -> 1000 | ... BT66: =($G66*Assumptions!BT72)*(1+'Cost Buildup'!$H66)^(BT$3-1) -> 2928.2
A67: Total Product Development Salary | M67: =SUM(M57:M66) -> 15077.081 | N67: =SUM(N57:N66) -> 15077.081 | O67: =SUM(O57:O66) -> 15077.081 | P67: =SUM(P57:P66) -> 15077.081 | Q67: =SUM(Q57:Q66) -> 15077.081 | R67: =SUM(R57:R66) -> 15077.081 | S67: =SUM(S57:S66) -> 15077.081 | T67: =SUM(T57:T66) -> 15077.081 | ... BT67: =SUM(BT57:BT66) -> 44148.709
A68: Total Product Development Expense | M68: =M55+M67 -> 16662.146 | N68: =N55+N67 -> 16693.848 | O68: =O55+O67 -> 16726.183 | P68: =P55+P67 -> 16759.165 | Q68: =Q55+Q67 -> 16792.807 | R68: =R55+R67 -> 16827.121 | S68: =S55+S67 -> 16862.122 | T68: =T55+T67 -> 16897.823 | ... BT68: =BT55+BT67 -> 49247.383 | BV68: =SUMIF($M$3:$BT$3,BV$3,$M68:$BT68) -> 202184.01 | BW68: =SUMIF($M$3:$BT$3,BW$3,$M68:$BT68) -> 225979.07 | BX68: =SUMIF($M$3:$BT$3,BX$3,$M68:$BT68) -> 255533.04 | BY68: =SUMIF($M$3:$BT$3,BY$3,$M68:$BT68) -> 316121.18 | BZ68: =SUMIF($M$3:$BT$3,BZ$3,$M68:$BT68) -> 412467.74
A69: Employees Benefit Expense
A70: Head Count
A71: =A10 -> Customer Support | M71: =M10 -> 0 | N71: =N10 -> 0 | O71: =O10 -> 0 | P71: =P10 -> 0 | Q71: =Q10 -> 0 | R71: =R10 -> 1 | S71: =S10 -> 1 | T71: =T10 -> 1 | ... BT71: =BT10 -> 4 | BV71: =INDEX($M71:$BT71,MATCH(BV$4,$M$4:$BT$4,0)) -> 1 | BW71: =INDEX($M71:$BT71,MATCH(BW$4,$M$4:$BT$4,0)) -> 2 | BX71: =INDEX($M71:$BT71,MATCH(BX$4,$M$4:$BT$4,0)) -> 2 | BY71: =INDEX($M71:$BT71,MATCH(BY$4,$M$4:$BT$4,0)) -> 3 | BZ71: =INDEX($M71:$BT71,MATCH(BZ$4,$M$4:$BT$4,0)) -> 4
A72: =Assumptions!A35 -> Sales Team-Headcount | M72: =SUM(M73:M74) -> 1 | N72: =SUM(N73:N74) -> 1 | O72: =SUM(O73:O74) -> 1 | P72: =SUM(P73:P74) -> 1 | Q72: =SUM(Q73:Q74) -> 1 | R72: =SUM(R73:R74) -> 1 | S72: =SUM(S73:S74) -> 1 | T72: =SUM(T73:T74) -> 1 | ... BT72: =SUM(BT73:BT74) -> 1 | BV72: =INDEX($M72:$BT72,MATCH(BV$4,$M$4:$BT$4,0)) -> 1 | BW72: =INDEX($M72:$BT72,MATCH(BW$4,$M$4:$BT$4,0)) -> 1 | BX72: =INDEX($M72:$BT72,MATCH(BX$4,$M$4:$BT$4,0)) -> 1 | BY72: =INDEX($M72:$BT72,MATCH(BY$4,$M$4:$BT$4,0)) -> 1 | BZ72: =INDEX($M72:$BT72,MATCH(BZ$4,$M$4:$BT$4,0)) -> 1
A73: =Assumptions!A36 -> Client Success Manager | M73: =CEILING('Revenue Buildup'!M$6,Assumptions!M$36)/Assumptions!M$36 -> 1 | N73: =CEILING('Revenue Buildup'!N$6,Assumptions!N$36)/Assumptions!N$36 -> 1 | O73: =CEILING('Revenue Buildup'!O$6,Assumptions!O$36)/Assumptions!O$36 -> 1 | P73: =CEILING('Revenue Buildup'!P$6,Assumptions!P$36)/Assumptions!P$36 -> 1 | Q73: =CEILING('Revenue Buildup'!Q$6,Assumptions!Q$36)/Assumptions!Q$36 -> 1 | R73: =CEILING('Revenue Buildup'!R$6,Assumptions!R$36)/Assumptions!R$36 -> 1 | S73: =CEILING('Revenue Buildup'!S$6,Assumptions!S$36)/Assumptions!S$36 -> 1 | T73: =CEILING('Revenue Buildup'!T$6,Assumptions!T$36)/Assumptions!T$36 -> 1 | ... BT73: =CEILING('Revenue Buildup'!BT$6,Assumptions!BT$36)/Assumptions!BT$36 -> 1
A74: =Assumptions!A37 -> XYZ(For any additional role) | M74: =Assumptions!M37 -> 0 | N74: =Assumptions!N37 -> 0 | O74: =Assumptions!O37 -> 0 | P74: =Assumptions!P37 -> 0 | Q74: =Assumptions!Q37 -> 0 | R74: =Assumptions!R37 -> 0 | S74: =Assumptions!S37 -> 0 | T74: =Assumptions!T37 -> 0 | ... BT74: =Assumptions!BT37 -> 0
A75: Marketing | M75: =SUM(M76:M81) -> 0 | N75: =SUM(N76:N81) -> 0 | O75: =SUM(O76:O81) -> 0 | P75: =SUM(P76:P81) -> 0 | Q75: =SUM(Q76:Q81) -> 0 | R75: =SUM(R76:R81) -> 0 | S75: =SUM(S76:S81) -> 0 | T75: =SUM(T76:T81) -> 0 | ... BT75: =SUM(BT76:BT81) -> 0 | BV75: =INDEX($M75:$BT75,MATCH(BV$4,$M$4:$BT$4,0)) -> 0 | BW75: =INDEX($M75:$BT75,MATCH(BW$4,$M$4:$BT$4,0)) -> 0 | BX75: =INDEX($M75:$BT75,MATCH(BX$4,$M$4:$BT$4,0)) -> 0 | BY75: =INDEX($M75:$BT75,MATCH(BY$4,$M$4:$BT$4,0)) -> 0 | BZ75: =INDEX($M75:$BT75,MATCH(BZ$4,$M$4:$BT$4,0)) -> 0
A76: =Assumptions!A44 -> ABC | M76: =Assumptions!M44 -> 0 | N76: =Assumptions!N44 -> 0 | O76: =Assumptions!O44 -> 0 | P76: =Assumptions!P44 -> 0 | Q76: =Assumptions!Q44 -> 0 | R76: =Assumptions!R44 -> 0 | S76: =Assumptions!S44 -> 0 | T76: =Assumptions!T44 -> 0 | ... BT76: =Assumptions!BT44 -> 0
A77: =Assumptions!A45 -> ABC | M77: =Assumptions!M45 -> 0 | N77: =Assumptions!N45 -> 0 | O77: =Assumptions!O45 -> 0 | P77: =Assumptions!P45 -> 0 | Q77: =Assumptions!Q45 -> 0 | R77: =Assumptions!R45 -> 0 | S77: =Assumptions!S45 -> 0 | T77: =Assumptions!T45 -> 0 | ... BT77: =Assumptions!BT45 -> 0
A78: =Assumptions!A46 -> ABC | M78: =Assumptions!M46 -> 0 | N78: =Assumptions!N46 -> 0 | O78: =Assumptions!O46 -> 0 | P78: =Assumptions!P46 -> 0 | Q78: =Assumptions!Q46 -> 0 | R78: =Assumptions!R46 -> 0 | S78: =Assumptions!S46 -> 0 | T78: =Assumptions!T46 -> 0 | ... BT78: =Assumptions!BT46 -> 0
A79: =Assumptions!A47 -> ABC | M79: =Assumptions!M47 -> 0 | N79: =Assumptions!N47 -> 0 | O79: =Assumptions!O47 -> 0 | P79: =Assumptions!P47 -> 0 | Q79: =Assumptions!Q47 -> 0 | R79: =Assumptions!R47 -> 0 | S79: =Assumptions!S47 -> 0 | T79: =Assumptions!T47 -> 0 | ... BT79: =Assumptions!BT47 -> 0
A80: =Assumptions!A48 -> ABC | M80: =Assumptions!M48 -> 0 | N80: =Assumptions!N48 -> 0 | O80: =Assumptions!O48 -> 0 | P80: =Assumptions!P48 -> 0 | Q80: =Assumptions!Q48 -> 0 | R80: =Assumptions!R48 -> 0 | S80: =Assumptions!S48 -> 0 | T80: =Assumptions!T48 -> 0 | ... BT80: =Assumptions!BT48 -> 0
A81: =Assumptions!A49 -> ABC | M81: =Assumptions!M49 -> 0 | N81: =Assumptions!N49 -> 0 | O81: =Assumptions!O49 -> 0 | P81: =Assumptions!P49 -> 0 | Q81: =Assumptions!Q49 -> 0 | R81: =Assumptions!R49 -> 0 | S81: =Assumptions!S49 -> 0 | T81: =Assumptions!T49 -> 0 | ... BT81: =Assumptions!BT49 -> 0
A82: =Assumptions!A50 -> G&A | M82: =SUM(M83:M87) -> 4 | N82: =SUM(N83:N87) -> 4 | O82: =SUM(O83:O87) -> 4 | P82: =SUM(P83:P87) -> 4 | Q82: =SUM(Q83:Q87) -> 4 | R82: =SUM(R83:R87) -> 4 | S82: =SUM(S83:S87) -> 5 | T82: =SUM(T83:T87) -> 5 | ... BT82: =SUM(BT83:BT87) -> 7 | BV82: =INDEX($M82:$BT82,MATCH(BV$4,$M$4:$BT$4,0)) -> 5 | BW82: =INDEX($M82:$BT82,MATCH(BW$4,$M$4:$BT$4,0)) -> 7 | BX82: =INDEX($M82:$BT82,MATCH(BX$4,$M$4:$BT$4,0)) -> 7 | BY82: =INDEX($M82:$BT82,MATCH(BY$4,$M$4:$BT$4,0)) -> 7 | BZ82: =INDEX($M82:$BT82,MATCH(BZ$4,$M$4:$BT$4,0)) -> 7
A83: =Assumptions!A55 -> Account & Finance | M83: =Assumptions!M55 -> 1 | N83: =Assumptions!N55 -> 1 | O83: =Assumptions!O55 -> 1 | P83: =Assumptions!P55 -> 1 | Q83: =Assumptions!Q55 -> 1 | R83: =Assumptions!R55 -> 1 | S83: =Assumptions!S55 -> 1 | T83: =Assumptions!T55 -> 1 | ... BT83: =Assumptions!BT55 -> 2
A84: =Assumptions!A56 -> Legal | M84: =Assumptions!M56 -> 1 | N84: =Assumptions!N56 -> 1 | O84: =Assumptions!O56 -> 1 | P84: =Assumptions!P56 -> 1 | Q84: =Assumptions!Q56 -> 1 | R84: =Assumptions!R56 -> 1 | S84: =Assumptions!S56 -> 1 | T84: =Assumptions!T56 -> 1 | ... BT84: =Assumptions!BT56 -> 2
A85: =Assumptions!A57 -> HR | M85: =Assumptions!M57 -> 0 | N85: =Assumptions!N57 -> 0 | O85: =Assumptions!O57 -> 0 | P85: =Assumptions!P57 -> 0 | Q85: =Assumptions!Q57 -> 0 | R85: =Assumptions!R57 -> 0 | S85: =Assumptions!S57 -> 1 | T85: =Assumptions!T57 -> 1 | ... BT85: =Assumptions!BT57 -> 1
A86: =Assumptions!A58 -> Management-Co-Found | M86: =Assumptions!M58 -> 1 | N86: =Assumptions!N58 -> 1 | O86: =Assumptions!O58 -> 1 | P86: =Assumptions!P58 -> 1 | Q86: =Assumptions!Q58 -> 1 | R86: =Assumptions!R58 -> 1 | S86: =Assumptions!S58 -> 1 | T86: =Assumptions!T58 -> 1 | ... BT86: =Assumptions!BT58 -> 1
A87: =Assumptions!A59 -> Management-Co-Found | M87: =Assumptions!M59 -> 1 | N87: =Assumptions!N59 -> 1 | O87: =Assumptions!O59 -> 1 | P87: =Assumptions!P59 -> 1 | Q87: =Assumptions!Q59 -> 1 | R87: =Assumptions!R59 -> 1 | S87: =Assumptions!S59 -> 1 | T87: =Assumptions!T59 -> 1 | ... BT87: =Assumptions!BT59 -> 1
A88: Product Development | M88: =SUM(M89:M96) -> 8 | N88: =SUM(N89:N96) -> 8 | O88: =SUM(O89:O96) -> 8 | P88: =SUM(P89:P96) -> 8 | Q88: =SUM(Q89:Q96) -> 8 | R88: =SUM(R89:R96) -> 8 | S88: =SUM(S89:S96) -> 8 | T88: =SUM(T89:T96) -> 8 | ... BT88: =SUM(BT89:BT96) -> 16 | BV88: =INDEX($M88:$BT88,MATCH(BV$4,$M$4:$BT$4,0)) -> 8 | BW88: =INDEX($M88:$BT88,MATCH(BW$4,$M$4:$BT$4,0)) -> 8 | BX88: =INDEX($M88:$BT88,MATCH(BX$4,$M$4:$BT$4,0)) -> 9 | BY88: =INDEX($M88:$BT88,MATCH(BY$4,$M$4:$BT$4,0)) -> 9 | BZ88: =INDEX($M88:$BT88,MATCH(BZ$4,$M$4:$BT$4,0)) -> 16
A89: =Assumptions!A63 -> Project Manager | M89: =Assumptions!M63 -> 1 | N89: =Assumptions!N63 -> 1 | O89: =Assumptions!O63 -> 1 | P89: =Assumptions!P63 -> 1 | Q89: =Assumptions!Q63 -> 1 | R89: =Assumptions!R63 -> 1 | S89: =Assumptions!S63 -> 1 | T89: =Assumptions!T63 -> 1 | ... BT89: =Assumptions!BT63 -> 2
A90: =Assumptions!A64 -> UI,UX Designer | M90: =Assumptions!M64 -> 1 | N90: =Assumptions!N64 -> 1 | O90: =Assumptions!O64 -> 1 | P90: =Assumptions!P64 -> 1 | Q90: =Assumptions!Q64 -> 1 | R90: =Assumptions!R64 -> 1 | S90: =Assumptions!S64 -> 1 | T90: =Assumptions!T64 -> 1 | ... BT90: =Assumptions!BT64 -> 2
A91: =Assumptions!A65 -> Sr. Software | M91: =Assumptions!M65 -> 1 | N91: =Assumptions!N65 -> 1 | O91: =Assumptions!O65 -> 1 | P91: =Assumptions!P65 -> 1 | Q91: =Assumptions!Q65 -> 1 | R91: =Assumptions!R65 -> 1 | S91: =Assumptions!S65 -> 1 | T91: =Assumptions!T65 -> 1 | ... BT91: =Assumptions!BT65 -> 2
A92: =Assumptions!A66 -> Solution Architect | M92: =Assumptions!M66 -> 1 | N92: =Assumptions!N66 -> 1 | O92: =Assumptions!O66 -> 1 | P92: =Assumptions!P66 -> 1 | Q92: =Assumptions!Q66 -> 1 | R92: =Assumptions!R66 -> 1 | S92: =Assumptions!S66 -> 1 | T92: =Assumptions!T66 -> 1 | ... BT92: =Assumptions!BT66 -> 2
A93: =Assumptions!A67 -> Test Er | M93: =Assumptions!M67 -> 1 | N93: =Assumptions!N67 -> 1 | O93: =Assumptions!O67 -> 1 | P93: =Assumptions!P67 -> 1 | Q93: =Assumptions!Q67 -> 1 | R93: =Assumptions!R67 -> 1 | S93: =Assumptions!S67 -> 1 | T93: =Assumptions!T67 -> 1 | ... BT93: =Assumptions!BT67 -> 2
A94: =Assumptions!A68 -> Jr. Test Er | M94: =Assumptions!M68 -> 1 | N94: =Assumptions!N68 -> 1 | O94: =Assumptions!O68 -> 1 | P94: =Assumptions!P68 -> 1 | Q94: =Assumptions!Q68 -> 1 | R94: =Assumptions!R68 -> 1 | S94: =Assumptions!S68 -> 1 | T94: =Assumptions!T68 -> 1 | ... BT94: =Assumptions!BT68 -> 2
A95: =Assumptions!A69 -> Infra Er | M95: =Assumptions!M69 -> 1 | N95: =Assumptions!N69 -> 1 | O95: =Assumptions!O69 -> 1 | P95: =Assumptions!P69 -> 1 | Q95: =Assumptions!Q69 -> 1 | R95: =Assumptions!R69 -> 1 | S95: =Assumptions!S69 -> 1 | T95: =Assumptions!T69 -> 1 | ... BT95: =Assumptions!BT69 -> 2
A96: =Assumptions!A70 -> Jr. Infra Er | M96: =Assumptions!M70 -> 1 | N96: =Assumptions!N70 -> 1 | O96: =Assumptions!O70 -> 1 | P96: =Assumptions!P70 -> 1 | Q96: =Assumptions!Q70 -> 1 | R96: =Assumptions!R70 -> 1 | S96: =Assumptions!S70 -> 1 | T96: =Assumptions!T70 -> 1 | ... BT96: =Assumptions!BT70 -> 2
A97: Total Headcount | M97: =M88+M82+M75+M72+M71 -> 13 | N97: =N88+N82+N75+N72+N71 -> 13 | O97: =O88+O82+O75+O72+O71 -> 13 | P97: =P88+P82+P75+P72+P71 -> 13 | Q97: =Q88+Q82+Q75+Q72+Q71 -> 13 | R97: =R88+R82+R75+R72+R71 -> 14 | S97: =S88+S82+S75+S72+S71 -> 15 | T97: =T88+T82+T75+T72+T71 -> 15 | ... BT97: =BT88+BT82+BT75+BT72+BT71 -> 28 | BV97: =INDEX($M97:$BT97,MATCH(BV$4,$M$4:$BT$4,0)) -> 15 | BW97: =INDEX($M97:$BT97,MATCH(BW$4,$M$4:$BT$4,0)) -> 18 | BX97: =INDEX($M97:$BT97,MATCH(BX$4,$M$4:$BT$4,0)) -> 19 | BY97: =INDEX($M97:$BT97,MATCH(BY$4,$M$4:$BT$4,0)) -> 20 | BZ97: =INDEX($M97:$BT97,MATCH(BZ$4,$M$4:$BT$4,0)) -> 28

Sheet FAS
A1: Fixed Asset Schedule
A2: Cells in Orange are assumptions | M2: MONTHLY | BV2: YEARLY
A3: Year | M3: 1 | N3: 1 | O3: 1 | P3: 1 | Q3: 1 | R3: 1 | S3: 1 | T3: 1 | U3: 1 | V3: 1 | W3: 1 | X3: 1 | Y3: =X3+1 -> 2 | Z3: =Y3 -> 2 | AA3: =Z3 -> 2 | AB3: =AA3 -> 2 | AC3: =AB3 -> 2 | AD3: =AC3 -> 2 | AE3: =AD3 -> 2 | AF3: =AE3 -> 2 | AG3: =AF3 -> 2 | ... AJ3: =AI3 -> 2 | AK3: 3 | AL3: 3 | AM3: 3 | AN3: 3 | AO3: 3 | AP3: 3 | AQ3: 3 | AR3: 3 | AS3: 3 | AT3: 3 | AU3: 3 | AV3: 3 | AW3: 4 | AX3: 4 | AY3: 4 | AZ3: 4 | BA3: 4 | BB3: 4 | BC3: 4 | BD3: 4 | BE3: 4 | BF3: 4 | BG3: 4 | BH3: 4 | BI3: 5 | BJ3: 5 | BK3: 5 | BL3: 5 | BM3: 5 | BN3: 5 | BO3: 5 | BP3: 5 | BQ3: 5 | BR3: 5 | BS3: 5 | BT3: 5 | BV3: 1 | BW3: 2 | BX3: 3 | BY3: 4 | BZ3: 5
A4: Months | M4: 1 | N4: =M4+1 -> 2 | O4: =N4+1 -> 3 | P4: =O4+1 -> 4 | Q4: =P4+1 -> 5 | R4: =Q4+1 -> 6 | S4: =R4+1 -> 7 | T4: =S4+1 -> 8 | U4: =T4+1 -> 9 | ... BT4: =BS4+1 -> 60 | BV4: 12 | BW4: 24 | BX4: 36 | BY4: 48 | BZ4: 60

Sheet IS
A1: Income Statement
A2: Cells in Orange are assumptions | M2: MONTHLY | BV2: YEARLY | CB2: Common Size Statement
A3: Year | M3: 1 | N3: 1 | O3: 1 | P3: 1 | Q3: 1 | R3: 1 | S3: 1 | T3: 1 | U3: 1 | V3: 1 | W3: 1 | X3: 1 | Y3: =X3+1 -> 2 | Z3: =Y3 -> 2 | AA3: =Z3 -> 2 | AB3: =AA3 -> 2 | AC3: =AB3 -> 2 | AD3: =AC3 -> 2 | AE3: =AD3 -> 2 | AF3: =AE3 -> 2 | AG3: =AF3 -> 2 | ... AJ3: =AI3 -> 2 | AK3: 3 | AL3: 3 | AM3: 3 | AN3: 3 | AO3: 3 | AP3: 3 | AQ3: 3 | AR3: 3 | AS3: 3 | AT3: 3 | AU3: 3 | AV3: 3 | AW3: 4 | AX3: 4 | AY3: 4 | AZ3: 4 | BA3: 4 | BB3: 4 | BC3: 4 | BD3: 4 | BE3: 4 | BF3: 4 | BG3: 4 | BH3: 4 | BI3: 5 | BJ3: 5 | BK3: 5 | BL3: 5 | BM3: 5 | BN3: 5 | BO3: 5 | BP3: 5 | BQ3: 5 | BR3: 5 | BS3: 5 | BT3: 5 | BV3: 1 | BW3: 2 | BX3: 3 | BY3: 4 | BZ3: 5 | CB3: 1 | CC3: 2 | CD3: 3 | CE3: 4 | CF3: 5
A4: Months | M4: 1 | N4: =M4+1 -> 2 | O4: =N4+1 -> 3 | P4: =O4+1 -> 4 | Q4: =P4+1 -> 5 | R4: =Q4+1 -> 6 | S4: =R4+1 -> 7 | T4: =S4+1 -> 8 | U4: =T4+1 -> 9 | ... BT4: =BS4+1 -> 60 | BV4: 12 | BW4: 24 | BX4: 36 | BY4: 48 | BZ4: 60 | CB4: 12 | CC4: 24 | CD4: 36 | CE4: 48 | CF4: 60
A5: Revenues
B6: Active Clients | M6: ='Revenue Buildup'!M11 -> 1 | N6: ='Revenue Buildup'!N11 -> 1 | O6: ='Revenue Buildup'!O11 -> 2 | P6: ='Revenue Buildup'!P11 -> 2 | Q6: ='Revenue Buildup'!Q11 -> 2 | R6: ='Revenue Buildup'!R11 -> 3 | S6: ='Revenue Buildup'!S11 -> 3 | T6: ='Revenue Buildup'!T11 -> 3 | ... BT6: ='Revenue Buildup'!BT11 -> 20 | BV6: =INDEX($M6:$BT6,MATCH(BV$4,$M$4:$BT$4,0)) -> 5 | BW6: =INDEX($M6:$BT6,MATCH(BW$4,$M$4:$BT$4,0)) -> 9 | BX6: =INDEX($M6:$BT6,MATCH(BX$4,$M$4:$BT$4,0)) -> 11 | BY6: =INDEX($M6:$BT6,MATCH(BY$4,$M$4:$BT$4,0)) -> 14 | BZ6: =INDEX($M6:$BT6,MATCH(BZ$4,$M$4:$BT$4,0)) -> 20
A7: [+] | B7: Revenue | M7: ='Revenue Buildup'!M16 -> 6250 | N7: ='Revenue Buildup'!N16 -> 6250 | O7: ='Revenue Buildup'!O16 -> 12500 | P7: ='Revenue Buildup'!P16 -> 12500 | Q7: ='Revenue Buildup'!Q16 -> 12500 | R7: ='Revenue Buildup'!R16 -> 18750 | S7: ='Revenue Buildup'!S16 -> 18750 | T7: ='Revenue Buildup'!T16 -> 18750 | ... BT7: ='Revenue Buildup'!BT16 -> 125000 | BV7: =SUMIF($M$3:$BT$3,BV$3,$M7:$BT7) -> 212500 | BW7: =SUMIF($M$3:$BT$3,BW$3,$M7:$BT7) -> 512500 | BX7: =SUMIF($M$3:$BT$3,BX$3,$M7:$BT7) -> 725000 | BY7: =SUMIF($M$3:$BT$3,BY$3,$M7:$BT7) -> 918750 | BZ7: =SUMIF($M$3:$BT$3,BZ$3,$M7:$BT7) -> 1275000 | CB7: =BV7/BV$7 -> 1 | CC7: =BW7/BW$7 -> 1 | CD7: =BX7/BX$7 -> 1 | CE7: =BY7/BY$7 -> 1 | CF7: =BZ7/BZ$7 -> 1
A8: Direct Expenses
A9: [-] | B9: ='Cost Buildup'!A6 -> Hosting & Infrastructure Costs | M9: ='Cost Buildup'!M6 -> 375 | N9: ='Cost Buildup'!N6 -> 375 | O9: ='Cost Buildup'!O6 -> 750 | P9: ='Cost Buildup'!P6 -> 750 | Q9: ='Cost Buildup'!Q6 -> 750 | R9: ='Cost Buildup'!R6 -> 1125 | S9: ='Cost Buildup'!S6 -> 1125 | T9: ='Cost Buildup'!T6 -> 1125 | ... BT9: ='Cost Buildup'!BT6 -> 7500 | BV9: =SUMIF($M$3:$BT$3,BV$3,$M9:$BT9) -> 12750 | BW9: =SUMIF($M$3:$BT$3,BW$3,$M9:$BT9) -> 30750 | BX9: =SUMIF($M$3:$BT$3,BX$3,$M9:$BT9) -> 43500 | BY9: =SUMIF($M$3:$BT$3,BY$3,$M9:$BT9) -> 55125 | BZ9: =SUMIF($M$3:$BT$3,BZ$3,$M9:$BT9) -> 76500 | CB9: =BV9/BV$7 -> 0.06 | CC9: =BW9/BW$7 -> 0.06 | CD9: =BX9/BX$7 -> 0.06 | CE9: =BY9/BY$7 -> 0.06 | CF9: =BZ9/BZ$7 -> 0.06
A10: [-] | B10: ='Cost Buildup'!A12 -> Customer Support | M10: ='Cost Buildup'!M12 -> 0 | N10: ='Cost Buildup'!N12 -> 0 | O10: ='Cost Buildup'!O12 -> 0 | P10: ='Cost Buildup'!P12 -> 0 | Q10: ='Cost Buildup'!Q12 -> 0 | R10: ='Cost Buildup'!R12 -> 821.88564 | S10: ='Cost Buildup'!S12 -> 821.88564 | T10: ='Cost Buildup'!T12 -> 821.88564 | ... BT10: ='Cost Buildup'!BT12 -> 3996.0285 | BV10: =SUMIF($M$3:$BT$3,BV$3,$M10:$BT10) -> 5753.1995 | BW10: =SUMIF($M$3:$BT$3,BW$3,$M10:$BT10) -> 13807.679 | BX10: =SUMIF($M$3:$BT$3,BX$3,$M10:$BT10) -> 21747.094 | BY10: =SUMIF($M$3:$BT$3,BY$3,$M10:$BT10) -> 27591.626 | BZ10: =SUMIF($M$3:$BT$3,BZ$3,$M10:$BT10) -> 40959.292 | CB10: =BV10/BV$7 -> 0.02707388 | CC10: =BW10/BW$7 -> 0.026941812 | CD10: =BX10/BX$7 -> 0.029995992 | CE10: =BY10/BY$7 -> 0.030031701 | CF10: =BZ10/BZ$7 -> 0.032124935
A11: COGS | M11: =SUM(M9:M10) -> 375 | N11: =SUM(N9:N10) -> 375 | O11: =SUM(O9:O10) -> 750 | P11: =SUM(P9:P10) -> 750 | Q11: =SUM(Q9:Q10) -> 750 | R11: =SUM(R9:R10) -> 1946.8856 | S11: =SUM(S9:S10) -> 1946.8856 | T11: =SUM(T9:T10) -> 1946.8856 | ... BT11: =SUM(BT9:BT10) -> 11496.029 | BV11: =SUMIF($M$3:$BT$3,BV$3,$M11:$BT11) -> 18503.199 | BW11: =SUMIF($M$3:$BT$3,BW$3,$M11:$BT11) -> 44557.679 | BX11: =SUMIF($M$3:$BT$3,BX$3,$M11:$BT11) -> 65247.094 | BY11: =SUMIF($M$3:$BT$3,BY$3,$M11:$BT11) -> 82716.626 | BZ11: =SUMIF($M$3:$BT$3,BZ$3,$M11:$BT11) -> 117459.29 | CB11: =BV11/BV$7 -> 0.08707388 | CC11: =BW11/BW$7 -> 0.086941812 | CD11: =BX11/BX$7 -> 0.089995992 | CE11: =BY11/BY$7 -> 0.090031701 | CF11: =BZ11/BZ$7 -> 0.092124935
B12: Gross Profit | M12: =M7-M11 -> 5875 | N12: =N7-N11 -> 5875 | O12: =O7-O11 -> 11750 | P12: =P7-P11 -> 11750 | Q12: =Q7-Q11 -> 11750 | R12: =R7-R11 -> 16803.114 | S12: =S7-S11 -> 16803.114 | T12: =T7-T11 -> 16803.114 | ... BT12: =BT7-BT11 -> 113503.97 | BV12: =BV7-BV11 -> 193996.8 | BW12: =BW7-BW11 -> 467942.32 | BX12: =BX7-BX11 -> 659752.91 | BY12: =BY7-BY11 -> 836033.37 | BZ12: =BZ7-BZ11 -> 1157540.7 | CB12: =BV12/BV$7 -> 0.91292612 | CC12: =BW12/BW$7 -> 0.91305819 | CD12: =BX12/BX$7 -> 0.91000401 | CE12: =BY12/BY$7 -> 0.9099683 | CF12: =BZ12/BZ$7 -> 0.90787506
B13: Gross Profit % | M13: =M12/M$7 -> 0.94 | N13: =N12/N$7 -> 0.94 | O13: =O12/O$7 -> 0.94 | P13: =P12/P$7 -> 0.94 | Q13: =Q12/Q$7 -> 0.94 | R13: =R12/R$7 -> 0.8961661 | S13: =S12/S$7 -> 0.8961661 | T13: =T12/T$7 -> 0.8961661 | ... BT13: =BT12/BT$7 -> 0.90803177 | BV13: =BV12/BV$7 -> 0.91292612 | BW13: =BW12/BW$7 -> 0.91305819 | BX13: =BX12/BX$7 -> 0.91000401 | BY13: =BY12/BY$7 -> 0.9099683 | BZ13: =BZ12/BZ$7 -> 0.90787506
A14: Operating Expenses
A15: [+] | B15: Sales & Marketing | M15: ='Cost Buildup'!M17+'Cost Buildup'!M20+'Cost Buildup'!M23+'Cost Buildup'!M32 -> 4200 | N15: ='Cost Buildup'!N17+'Cost Buildup'!N20+'Cost Buildup'!N23+'Cost Buildup'!N32 -> 4200 | O15: ='Cost Buildup'!O17+'Cost Buildup'!O20+'Cost Buildup'!O23+'Cost Buildup'!O32 -> 6450 | P15: ='Cost Buildup'!P17+'Cost Buildup'!P20+'Cost Buildup'!P23+'Cost Buildup'!P32 -> 4200 | Q15: ='Cost Buildup'!Q17+'Cost Buildup'!Q20+'Cost Buildup'!Q23+'Cost Buildup'!Q32 -> 4200 | R15: ='Cost Buildup'!R17+'Cost Buildup'!R20+'Cost Buildup'!R23+'Cost Buildup'!R32 -> 6450 | S15: ='Cost Buildup'!S17+'Cost Buildup'!S20+'Cost Buildup'!S23+'Cost Buildup'!S32 -> 4200 | T15: ='Cost Buildup'!T17+'Cost Buildup'!T20+'Cost Buildup'!T23+'Cost Buildup'!T32 -> 4200 | ... BT15: ='Cost Buildup'!BT17+'Cost Buildup'!BT20+'Cost Buildup'!BT23+'Cost Buildup'!BT32 -> 6690 | BV15: =SUMIF($M$3:$BT$3,BV$3,$M15:$BT15) -> 59400 | BW15: =SUMIF($M$3:$BT$3,BW$3,$M15:$BT15) -> 59400 | BX15: =SUMIF($M$3:$BT$3,BX$3,$M15:$BT15) -> 57780 | BY15: =SUMIF($M$3:$BT$3,BY$3,$M15:$BT15) -> 60030 | BZ15: =SUMIF($M$3:$BT$3,BZ$3,$M15:$BT15) -> 66780 | CB15: =BV15/BV$7 -> 0.27952941 | CC15: =BW15/BW$7 -> 0.11590244 | CD15: =BX15/BX$7 -> 0.079696552 | CE15: =BY15/BY$7 -> 0.065338776 | CF15: =BZ15/BZ$7 -> 0.052376471
A16: [+] | B16: G&A | M16: =SUM('Cost Buildup'!M43:M45) -> 4414.7 | N16: =SUM('Cost Buildup'!N43:N45) -> 4425.2001 | O16: =SUM('Cost Buildup'!O43:O45) -> 4435.7002 | P16: =SUM('Cost Buildup'!P43:P45) -> 4446.2002 | Q16: =SUM('Cost Buildup'!Q43:Q45) -> 4456.7003 | R16: =SUM('Cost Buildup'!R43:R45) -> 4612.1336 | S16: =SUM('Cost Buildup'!S43:S45) -> 4769.1822 | T16: =SUM('Cost Buildup'!T43:T45) -> 4781.2977 | ... BT16: =SUM('Cost Buildup'!BT43:BT45) -> 7862.4374 | BV16: =SUMIF($M$3:$BT$3,BV$3,$M16:$BT16) -> 55587.46 | BW16: =SUMIF($M$3:$BT$3,BW$3,$M16:$BT16) -> 63255.868 | BX16: =SUMIF($M$3:$BT$3,BX$3,$M16:$BT16) -> 66745.897 | BY16: =SUMIF($M$3:$BT$3,BY$3,$M16:$BT16) -> 71649.462 | BZ16: =SUMIF($M$3:$BT$3,BZ$3,$M16:$BT16) -> 80059.628 | CB16: =BV16/BV$7 -> 0.26158805 | CC16: =BW16/BW$7 -> 0.12342608 | CD16: =BX16/BX$7 -> 0.092063306 | CE16: =BY16/BY$7 -> 0.077985809 | CF16: =BZ16/BZ$7 -> 0.062791865
A17: [+] | B17: Product Development (Infra) | M17: ='Cost Buildup'!M55 -> 1585.0652 | N17: ='Cost Buildup'!N55 -> 1616.7665 | O17: ='Cost Buildup'!O55 -> 1649.1018 | P17: ='Cost Buildup'!P55 -> 1682.0838 | Q17: ='Cost Buildup'!Q55 -> 1715.7255 | R17: ='Cost Buildup'!R55 -> 1750.04 | S17: ='Cost Buildup'!S55 -> 1785.0408 | T17: ='Cost Buildup'!T55 -> 1820.7416 | ... BT17: ='Cost Buildup'!BT55 -> 5098.6741 | BV17: =SUMIF($M$3:$BT$3,BV$3,$M17:$BT17) -> 21259.036 | BW17: =SUMIF($M$3:$BT$3,BW$3,$M17:$BT17) -> 26961.598 | BX17: =SUMIF($M$3:$BT$3,BX$3,$M17:$BT17) -> 34193.826 | BY17: =SUMIF($M$3:$BT$3,BY$3,$M17:$BT17) -> 43366.039 | BZ17: =SUMIF($M$3:$BT$3,BZ$3,$M17:$BT17) -> 54998.623 | CB17: =BV17/BV$7 -> 0.10004252 | CC17: =BW17/BW$7 -> 0.052607997 | CD17: =BX17/BX$7 -> 0.047163898 | CE17: =BY17/BY$7 -> 0.047201131 | CF17: =BZ17/BZ$7 -> 0.043136175
A18: [+] | B18: Employees Benefit Expense | M18: =SUM(M19:M22) -> 22206.399 | N18: =SUM(N19:N22) -> 22206.399 | O18: =SUM(O19:O22) -> 22206.399 | P18: =SUM(P19:P22) -> 22206.399 | Q18: =SUM(Q19:Q22) -> 22206.399 | R18: =SUM(R19:R22) -> 22206.399 | S18: =SUM(S19:S22) -> 22910.872 | T18: =SUM(T19:T22) -> 22910.872 | ... BT18: =SUM(BT19:BT22) -> 53358.53 | BV18: =SUMIF($M$3:$BT$3,BV$3,$M18:$BT18) -> 270703.63 | BW18: =SUMIF($M$3:$BT$3,BW$3,$M18:$BT18) -> 303887.38 | BX18: =SUMIF($M$3:$BT$3,BX$3,$M18:$BT18) -> 328000.71 | BY18: =SUMIF($M$3:$BT$3,BY$3,$M18:$BT18) -> 381297.78 | BZ18: =SUMIF($M$3:$BT$3,BZ$3,$M18:$BT18) -> 467986.97 | CB18: =BV18/BV$7 -> 1.2738994 | CC18: =BW18/BW$7 -> 0.59295099 | CD18: =BX18/BX$7 -> 0.45241477 | CE18: =BY18/BY$7 -> 0.41501799 | CF18: =BZ18/BZ$7 -> 0.36704861
A19: [+] | B19: Sales | M19: ='Cost Buildup'!M29 -> 1200 | N19: ='Cost Buildup'!N29 -> 1200 | O19: ='Cost Buildup'!O29 -> 1200 | P19: ='Cost Buildup'!P29 -> 1200 | Q19: ='Cost Buildup'!Q29 -> 1200 | R19: ='Cost Buildup'!R29 -> 1200 | S19: ='Cost Buildup'!S29 -> 1200 | T19: ='Cost Buildup'!T29 -> 1200 | ... BT19: ='Cost Buildup'!BT29 -> 1458.6075 | BV19: =SUMIF($M$3:$BT$3,BV$3,$M19:$BT19) -> 14400 | BW19: =SUMIF($M$3:$BT$3,BW$3,$M19:$BT19) -> 15120 | BX19: =SUMIF($M$3:$BT$3,BX$3,$M19:$BT19) -> 15876 | BY19: =SUMIF($M$3:$BT$3,BY$3,$M19:$BT19) -> 16669.8 | BZ19: =SUMIF($M$3:$BT$3,BZ$3,$M19:$BT19) -> 17503.29 | CB19: =BV19/BV$7 -> 0.067764706 | CC19: =BW19/BW$7 -> 0.029502439 | CD19: =BX19/BX$7 -> 0.021897931 | CE19: =BY19/BY$7 -> 0.018144 | CF19: =BZ19/BZ$7 -> 0.013728071
A20: [+] | B20: Marketing | M20: ='Cost Buildup'!M40 -> 0 | N20: ='Cost Buildup'!N40 -> 0 | O20: ='Cost Buildup'!O40 -> 0 | P20: ='Cost Buildup'!P40 -> 0 | Q20: ='Cost Buildup'!Q40 -> 0 | R20: ='Cost Buildup'!R40 -> 0 | S20: ='Cost Buildup'!S40 -> 0 | T20: ='Cost Buildup'!T40 -> 0 | ... BT20: ='Cost Buildup'!BT40 -> 0 | BV20: =SUMIF($M$3:$BT$3,BV$3,$M20:$BT20) -> 0 | BW20: =SUMIF($M$3:$BT$3,BW$3,$M20:$BT20) -> 0 | BX20: =SUMIF($M$3:$BT$3,BX$3,$M20:$BT20) -> 0 | BY20: =SUMIF($M$3:$BT$3,BY$3,$M20:$BT20) -> 0 | BZ20: =SUMIF($M$3:$BT$3,BZ$3,$M20:$BT20) -> 0 | CB20: =BV20/BV$7 -> 0 | CC20: =BW20/BW$7 -> 0 | CD20: =BX20/BX$7 -> 0 | CE20: =BY20/BY$7 -> 0 | CF20: =BZ20/BZ$7 -> 0
A21: [+] | B21: G&A | M21: ='Cost Buildup'!M52 -> 5929.3178 | N21: ='Cost Buildup'!N52 -> 5929.3178 | O21: ='Cost Buildup'!O52 -> 5929.3178 | P21: ='Cost Buildup'!P52 -> 5929.3178 | Q21: ='Cost Buildup'!Q52 -> 5929.3178 | R21: ='Cost Buildup'!R52 -> 5929.3178 | S21: ='Cost Buildup'!S52 -> 6633.7912 | T21: ='Cost Buildup'!T52 -> 6633.7912 | ... BT21: ='Cost Buildup'!BT52 -> 7751.2137 | BV21: =SUMIF($M$3:$BT$3,BV$3,$M21:$BT21) -> 75378.654 | BW21: =SUMIF($M$3:$BT$3,BW$3,$M21:$BT21) -> 89749.912 | BX21: =SUMIF($M$3:$BT$3,BX$3,$M21:$BT21) -> 90785.488 | BY21: =SUMIF($M$3:$BT$3,BY$3,$M21:$BT21) -> 91872.843 | BZ21: =SUMIF($M$3:$BT$3,BZ$3,$M21:$BT21) -> 93014.565 | CB21: =BV21/BV$7 -> 0.35472308 | CC21: =BW21/BW$7 -> 0.17512178 | CD21: =BX21/BX$7 -> 0.12522136 | CE21: =BY21/BY$7 -> 0.099997652 | CF21: =BZ21/BZ$7 -> 0.0729526
A22: [+] | B22: Product Development | M22: ='Cost Buildup'!M67 -> 15077.081 | N22: ='Cost Buildup'!N67 -> 15077.081 | O22: ='Cost Buildup'!O67 -> 15077.081 | P22: ='Cost Buildup'!P67 -> 15077.081 | Q22: ='Cost Buildup'!Q67 -> 15077.081 | R22: ='Cost Buildup'!R67 -> 15077.081 | S22: ='Cost Buildup'!S67 -> 15077.081 | T22: ='Cost Buildup'!T67 -> 15077.081 | ... BT22: ='Cost Buildup'!BT67 -> 44148.709 | BV22: =SUMIF($M$3:$BT$3,BV$3,$M22:$BT22) -> 180924.97 | BW22: =SUMIF($M$3:$BT$3,BW$3,$M22:$BT22) -> 199017.47 | BX22: =SUMIF($M$3:$BT$3,BX$3,$M22:$BT22) -> 221339.22 | BY22: =SUMIF($M$3:$BT$3,BY$3,$M22:$BT22) -> 272755.14 | BZ22: =SUMIF($M$3:$BT$3,BZ$3,$M22:$BT22) -> 357469.12 | CB22: =BV22/BV$7 -> 0.85141164 | CC22: =BW22/BW$7 -> 0.38832677 | CD22: =BX22/BX$7 -> 0.30529547 | CE22: =BY22/BY$7 -> 0.29687634 | CF22: =BZ22/BZ$7 -> 0.28036794
A23: Total Operating Expense | M23: =SUM(M15:M18) -> 32406.164 | N23: =SUM(N15:N18) -> 32448.366 | O23: =SUM(O15:O18) -> 34741.201 | P23: =SUM(P15:P18) -> 32534.683 | Q23: =SUM(Q15:Q18) -> 32578.825 | R23: =SUM(R15:R18) -> 35018.573 | S23: =SUM(S15:S18) -> 33665.095 | T23: =SUM(T15:T18) -> 33712.912 | ... BT23: =SUM(BT15:BT18) -> 73009.642 | BV23: =SUMIF($M$3:$BT$3,BV$3,$M23:$BT23) -> 406950.12 | BW23: =SUMIF($M$3:$BT$3,BW$3,$M23:$BT23) -> 453504.85 | BX23: =SUMIF($M$3:$BT$3,BX$3,$M23:$BT23) -> 486720.43 | BY23: =SUMIF($M$3:$BT$3,BY$3,$M23:$BT23) -> 556343.28 | BZ23: =SUMIF($M$3:$BT$3,BZ$3,$M23:$BT23) -> 669825.22 | CB23: =BV23/BV$7 -> 1.9150594 | CC23: =BW23/BW$7 -> 0.88488751 | CD23: =BX23/BX$7 -> 0.67133852 | CE23: =BY23/BY$7 -> 0.60554371 | CF23: =BZ23/BZ$7 -> 0.52535312
CB24: =BV24/BV$7 -> 0 | CC24: =BW24/BW$7 -> 0
B25: EBITDA | M25: =M12-M23 -> -26531.164 | N25: =N12-N23 -> -26573.366 | O25: =O12-O23 -> -22991.201 | P25: =P12-P23 -> -20784.683 | Q25: =Q12-Q23 -> -20828.825 | R25: =R12-R23 -> -18215.458 | S25: =S12-S23 -> -16861.981 | T25: =T12-T23 -> -16909.797 | ... BT25: =BT12-BT23 -> 40494.33 | BV25: =BV12-BV23 -> -212953.32 | BW25: =BW12-BW23 -> 14437.473 | BX25: =BX12-BX23 -> 173032.48 | BY25: =BY12-BY23 -> 279690.09 | BZ25: =BZ12-BZ23 -> 487715.48 | CB25: =BV25/BV$7 -> -1.0021333 | CC25: =BW25/BW$7 -> 0.028170678 | CD25: =BX25/BX$7 -> 0.23866549 | CE25: =BY25/BY$7 -> 0.30442459 | CF25: =BZ25/BZ$7 -> 0.38252195
B26: EBITDA% | M26: =M25/M$7 -> -4.2449863 | N26: =N25/N$7 -> -4.2517385 | O26: =O25/O$7 -> -1.8392961 | P26: =P25/P$7 -> -1.6627746 | Q26: =Q25/Q$7 -> -1.666306 | R26: =R25/R$7 -> -0.9714911 | S26: =S25/S$7 -> -0.89930566 | T26: =T25/T$7 -> -0.90185586 | ... BT26: =BT25/BT$7 -> 0.32395464 | BV26: =BV25/BV$7 -> -1.0021333 | BW26: =BW25/BW$7 -> 0.028170678 | BX26: =BX25/BX$7 -> 0.23866549 | BY26: =BY25/BY$7 -> 0.30442459 | BZ26: =BZ25/BZ$7 -> 0.38252195
A28: [-] | B28: Depreciation and Amortization | BV28: =SUMIF($M$3:$BT$3,BV$3,$M28:$BT28) -> 0 | BW28: =SUMIF($M$3:$BT$3,BW$3,$M28:$BT28) -> 0 | BX28: =SUMIF($M$3:$BT$3,BX$3,$M28:$BT28) -> 0 | BY28: =SUMIF($M$3:$BT$3,BY$3,$M28:$BT28) -> 0 | BZ28: =SUMIF($M$3:$BT$3,BZ$3,$M28:$BT28) -> 0 | CB28: =BV28/BV$7 -> 0 | CC28: =BW28/BW$7 -> 0 | CD28: =BX28/BX$7 -> 0 | CE28: =BY28/BY$7 -> 0 | CF28: =BZ28/BZ$7 -> 0
A29: [-] | B29: Interest Expense | BV29: =SUMIF($M$3:$BT$3,BV$3,$M29:$BT29) -> 0 | BW29: =SUMIF($M$3:$BT$3,BW$3,$M29:$BT29) -> 0 | BX29: =SUMIF($M$3:$BT$3,BX$3,$M29:$BT29) -> 0 | BY29: =SUMIF($M$3:$BT$3,BY$3,$M29:$BT29) -> 0 | BZ29: =SUMIF($M$3:$BT$3,BZ$3,$M29:$BT29) -> 0 | CB29: =BV29/BV$7 -> 0 | CC29: =BW29/BW$7 -> 0 | CD29: =BX29/BX$7 -> 0 | CE29: =BY29/BY$7 -> 0 | CF29: =BZ29/BZ$7 -> 0
B31: EBT | M31: =M25-M28-M29 -> -26531.164 | N31: =N25-N28-N29 -> -26573.366 | O31: =O25-O28-O29 -> -22991.201 | P31: =P25-P28-P29 -> -20784.683 | Q31: =Q25-Q28-Q29 -> -20828.825 | R31: =R25-R28-R29 -> -18215.458 | S31: =S25-S28-S29 -> -16861.981 | T31: =T25-T28-T29 -> -16909.797 | ... BT31: =BT25-BT28-BT29 -> 40494.33 | BV31: =BV25-BV28-BV29 -> -212953.32 | BW31: =BW25-BW28-BW29 -> 14437.473 | BX31: =BX25-BX28-BX29 -> 173032.48 | BY31: =BY25-BY28-BY29 -> 279690.09 | BZ31: =BZ25-BZ28-BZ29 -> 487715.48 | CB31: =BV31/BV$7 -> -1.0021333 | CC31: =BW31/BW$7 -> 0.028170678 | CD31: =BX31/BX$7 -> 0.23866549 | CE31: =BY31/BY$7 -> 0.30442459 | CF31: =BZ31/BZ$7 -> 0.38252195
B32: EBT % | M32: =M31/M$7 -> -4.2449863 | N32: =N31/N$7 -> -4.2517385 | O32: =O31/O$7 -> -1.8392961 | P32: =P31/P$7 -> -1.6627746 | Q32: =Q31/Q$7 -> -1.666306 | R32: =R31/R$7 -> -0.9714911 | S32: =S31/S$7 -> -0.89930566 | T32: =T31/T$7 -> -0.90185586 | ... BT32: =BT31/BT$7 -> 0.32395464 | BV32: =BV31/BV$7 -> -1.0021333 | BW32: =BW31/BW$7 -> 0.028170678 | BX32: =BX31/BX$7 -> 0.23866549 | BY32: =BY31/BY$7 -> 0.30442459 | BZ32: =BZ31/BZ$7 -> 0.38252195
A33: [-] | B33: Tax Expense | F33: 0.25 | BV33: =SUMIF($M$3:$BT$3,BV$3,$M33:$BT33) -> 0 | BW33: =SUMIF($M$3:$BT$3,BW$3,$M33:$BT33) -> 0 | BX33: =SUMIF($M$3:$BT$3,BX$3,$M33:$BT33) -> 0 | BY33: =SUMIF($M$3:$BT$3,BY$3,$M33:$BT33) -> 0 | BZ33: =SUMIF($M$3:$BT$3,BZ$3,$M33:$BT33) -> 0 | CB33: =BV33/BV$7 -> 0 | CC33: =BW33/BW$7 -> 0 | CD33: =BX33/BX$7 -> 0 | CE33: =BY33/BY$7 -> 0 | CF33: =BZ33/BZ$7 -> 0
B35: EAT | M35: =M31-M33 -> -26531.164 | N35: =N31-N33 -> -26573.366 | O35: =O31-O33 -> -22991.201 | P35: =P31-P33 -> -20784.683 | Q35: =Q31-Q33 -> -20828.825 | R35: =R31-R33 -> -18215.458 | S35: =S31-S33 -> -16861.981 | T35: =T31-T33 -> -16909.797 | ... BT35: =BT31-BT33 -> 40494.33 | BV35: =BV31-BV33 -> -212953.32 | BW35: =BW31-BW33 -> 14437.473 | BX35: =BX31-BX33 -> 173032.48 | BY35: =BY31-BY33 -> 279690.09 | BZ35: =BZ31-BZ33 -> 487715.48 | CB35: =BV35/BV$7 -> -1.0021333 | CC35: =BW35/BW$7 -> 0.028170678 | CD35: =BX35/BX$7 -> 0.23866549 | CE35: =BY35/BY$7 -> 0.30442459 | CF35: =BZ35/BZ$7 -> 0.38252195
B36: EAT% | M36: =M35/M$7 -> -4.2449863 | N36: =N35/N$7 -> -4.2517385 | O36: =O35/O$7 -> -1.8392961 | P36: =P35/P$7 -> -1.6627746 | Q36: =Q35/Q$7 -> -1.666306 | R36: =R35/R$7 -> -0.9714911 | S36: =S35/S$7 -> -0.89930566 | T36: =T35/T$7 -> -0.90185586 | ... BT36: =BT35/BT$7 -> 0.32395464 | BV36: =BV35/BV$7 -> -1.0021333 | BW36: =BW35/BW$7 -> 0.028170678 | BX36: =BX35/BX$7 -> 0.23866549 | BY36: =BY35/BY$7 -> 0.30442459 | BZ36: =BZ35/BZ$7 -> 0.38252195
A39: Treatment of Tax
A40: Taxable Income
A41: Cumulative Taxable Income

Sheet BS
A1: Balance Sheet
A2: Cells in Orange are assumptions | M2: MONTHLY | BV2: YEARLY
A3: Year | M3: 1 | N3: 1 | O3: 1 | P3: 1 | Q3: 1 | R3: 1 | S3: 1 | T3: 1 | U3: 1 | V3: 1 | W3: 1 | X3: 1 | Y3: =X3+1 -> 2 | Z3: =Y3 -> 2 | AA3: =Z3 -> 2 | AB3: =AA3 -> 2 | AC3: =AB3 -> 2 | AD3: =AC3 -> 2 | AE3: =AD3 -> 2 | AF3: =AE3 -> 2 | AG3: =AF3 -> 2 | ... AJ3: =AI3 -> 2 | AK3: 3 | AL3: 3 | AM3: 3 | AN3: 3 | AO3: 3 | AP3: 3 | AQ3: 3 | AR3: 3 | AS3: 3 | AT3: 3 | AU3: 3 | AV3: 3 | AW3: 4 | AX3: 4 | AY3: 4 | AZ3: 4 | BA3: 4 | BB3: 4 | BC3: 4 | BD3: 4 | BE3: 4 | BF3: 4 | BG3: 4 | BH3: 4 | BI3: 5 | BJ3: 5 | BK3: 5 | BL3: 5 | BM3: 5 | BN3: 5 | BO3: 5 | BP3: 5 | BQ3: 5 | BR3: 5 | BS3: 5 | BT3: 5 | BV3: 1 | BW3: 2 | BX3: 3 | BY3: 4 | BZ3: 5
A4: Months | M4: 1 | N4: =M4+1 -> 2 | O4: =N4+1 -> 3 | P4: =O4+1 -> 4 | Q4: =P4+1 -> 5 | R4: =Q4+1 -> 6 | S4: =R4+1 -> 7 | T4: =S4+1 -> 8 | U4: =T4+1 -> 9 | ... BT4: =BS4+1 -> 60 | BV4: 12 | BW4: 24 | BX4: 36 | BY4: 48 | BZ4: 60
A5: I. Equity & Liabilities
A6: Shareholders' Fund
A7: [+] | B7: Share Capital
A8: [+] | B8: Reserves & Surplus | M8: =L8+IS!M35 -> -26531.164 | N8: =M8+IS!N35 -> -53104.53 | O8: =N8+IS!O35 -> -76095.731 | P8: =O8+IS!P35 -> -96880.414 | Q8: =P8+IS!Q35 -> -117709.24 | R8: =Q8+IS!R35 -> -135924.7 | S8: =R8+IS!S35 -> -152786.68 | T8: =S8+IS!T35 -> -169696.47 | ... BT8: =BS8+IS!BT35 -> 741922.2 | BV8: =INDEX($M8:$BT8,MATCH(BV$4,$M$4:$BT$4,0)) -> -212953.32 | BW8: =INDEX($M8:$BT8,MATCH(BW$4,$M$4:$BT$4,0)) -> -198515.85 | BX8: =INDEX($M8:$BT8,MATCH(BX$4,$M$4:$BT$4,0)) -> -25483.374 | BY8: =INDEX($M8:$BT8,MATCH(BY$4,$M$4:$BT$4,0)) -> 254206.72 | BZ8: =INDEX($M8:$BT8,MATCH(BZ$4,$M$4:$BT$4,0)) -> 741922.2
B9: TOTAL Shareholders Funds | M9: =SUM(M7:M8) -> -26531.164 | N9: =SUM(N7:N8) -> -53104.53 | O9: =SUM(O7:O8) -> -76095.731 | P9: =SUM(P7:P8) -> -96880.414 | Q9: =SUM(Q7:Q8) -> -117709.24 | R9: =SUM(R7:R8) -> -135924.7 | S9: =SUM(S7:S8) -> -152786.68 | T9: =SUM(T7:T8) -> -169696.47 | ... BT9: =SUM(BT7:BT8) -> 741922.2 | BV9: =INDEX($M9:$BT9,MATCH(BV$4,$M$4:$BT$4,0)) -> -212953.32 | BW9: =INDEX($M9:$BT9,MATCH(BW$4,$M$4:$BT$4,0)) -> -198515.85 | BX9: =INDEX($M9:$BT9,MATCH(BX$4,$M$4:$BT$4,0)) -> -25483.374 | BY9: =INDEX($M9:$BT9,MATCH(BY$4,$M$4:$BT$4,0)) -> 254206.72 | BZ9: =INDEX($M9:$BT9,MATCH(BZ$4,$M$4:$BT$4,0)) -> 741922.2
A11: Liabilities
A12: Non-current liabilities
B13: Long-term borrowings | BV13: =INDEX($M13:$BT13,MATCH(BV$4,$M$4:$BT$4,0)) -> 0 | BW13: =INDEX($M13:$BT13,MATCH(BW$4,$M$4:$BT$4,0)) -> 0 | BX13: =INDEX($M13:$BT13,MATCH(BX$4,$M$4:$BT$4,0)) -> 0 | BY13: =INDEX($M13:$BT13,MATCH(BY$4,$M$4:$BT$4,0)) -> 0 | BZ13: =INDEX($M13:$BT13,MATCH(BZ$4,$M$4:$BT$4,0)) -> 0
A14: Current Liabilities
A15: [+] | B15: Deferred Revenue
A16: [+] | B16: Trade Payables | BV16: =INDEX($M16:$BT16,MATCH(BV$4,$M$4:$BT$4,0)) -> 0 | BW16: =INDEX($M16:$BT16,MATCH(BW$4,$M$4:$BT$4,0)) -> 0 | BX16: =INDEX($M16:$BT16,MATCH(BX$4,$M$4:$BT$4,0)) -> 0 | BY16: =INDEX($M16:$BT16,MATCH(BY$4,$M$4:$BT$4,0)) -> 0 | BZ16: =INDEX($M16:$BT16,MATCH(BZ$4,$M$4:$BT$4,0)) -> 0
A17: [+] | B17: Other current liabilities | BV17: =INDEX($M17:$BT17,MATCH(BV$4,$M$4:$BT$4,0)) -> 0 | BW17: =INDEX($M17:$BT17,MATCH(BW$4,$M$4:$BT$4,0)) -> 0 | BX17: =INDEX($M17:$BT17,MATCH(BX$4,$M$4:$BT$4,0)) -> 0 | BY17: =INDEX($M17:$BT17,MATCH(BY$4,$M$4:$BT$4,0)) -> 0 | BZ17: =INDEX($M17:$BT17,MATCH(BZ$4,$M$4:$BT$4,0)) -> 0
B18: TOTAL Liabilities | M18: =SUM(M13,M15:M17) -> 0 | N18: =SUM(N13,N15:N17) -> 0 | O18: =SUM(O13,O15:O17) -> 0 | P18: =SUM(P13,P15:P17) -> 0 | Q18: =SUM(Q13,Q15:Q17) -> 0 | R18: =SUM(R13,R15:R17) -> 0 | S18: =SUM(S13,S15:S17) -> 0 | T18: =SUM(T13,T15:T17) -> 0 | ... BT18: =SUM(BT13,BT15:BT17) -> 0 | BV18: =INDEX($M18:$BT18,MATCH(BV$4,$M$4:$BT$4,0)) -> 0 | BW18: =INDEX($M18:$BT18,MATCH(BW$4,$M$4:$BT$4,0)) -> 0 | BX18: =INDEX($M18:$BT18,MATCH(BX$4,$M$4:$BT$4,0)) -> 0 | BY18: =INDEX($M18:$BT18,MATCH(BY$4,$M$4:$BT$4,0)) -> 0 | BZ18: =INDEX($M18:$BT18,MATCH(BZ$4,$M$4:$BT$4,0)) -> 0
B20: TOTAL Equity and Liabilities | M20: =M9+M18 -> -26531.164 | N20: =N9+N18 -> -53104.53 | O20: =O9+O18 -> -76095.731 | P20: =P9+P18 -> -96880.414 | Q20: =Q9+Q18 -> -117709.24 | R20: =R9+R18 -> -135924.7 | S20: =S9+S18 -> -152786.68 | T20: =T9+T18 -> -169696.47 | ... BT20: =BT9+BT18 -> 741922.2 | BV20: =BV9+BV18 -> -212953.32 | BW20: =BW9+BW18 -> -198515.85 | BX20: =BX9+BX18 -> -25483.374 | BY20: =BY9+BY18 -> 254206.72 | BZ20: =BZ9+BZ18 -> 741922.2
A22: II. Assets
A23: Non-Current Assets
A24: Fixed Assets
A25: [+] | B25: Tangible assets | BV25: =INDEX($M25:$BT25,MATCH(BV$4,$M$4:$BT$4,0)) -> 0 | BW25: =INDEX($M25:$BT25,MATCH(BW$4,$M$4:$BT$4,0)) -> 0 | BX25: =INDEX($M25:$BT25,MATCH(BX$4,$M$4:$BT$4,0)) -> 0 | BY25: =INDEX($M25:$BT25,MATCH(BY$4,$M$4:$BT$4,0)) -> 0 | BZ25: =INDEX($M25:$BT25,MATCH(BZ$4,$M$4:$BT$4,0)) -> 0
A26: [+] | B26: Intangible assets | BV26: =INDEX($M26:$BT26,MATCH(BV$4,$M$4:$BT$4,0)) -> 0 | BW26: =INDEX($M26:$BT26,MATCH(BW$4,$M$4:$BT$4,0)) -> 0 | BX26: =INDEX($M26:$BT26,MATCH(BX$4,$M$4:$BT$4,0)) -> 0 | BY26: =INDEX($M26:$BT26,MATCH(BY$4,$M$4:$BT$4,0)) -> 0 | BZ26: =INDEX($M26:$BT26,MATCH(BZ$4,$M$4:$BT$4,0)) -> 0
A27: [+] | B27: Other Non Current Asset | BV27: =INDEX($M27:$BT27,MATCH(BV$4,$M$4:$BT$4,0)) -> 0 | BW27: =INDEX($M27:$BT27,MATCH(BW$4,$M$4:$BT$4,0)) -> 0 | BX27: =INDEX($M27:$BT27,MATCH(BX$4,$M$4:$BT$4,0)) -> 0 | BY27: =INDEX($M27:$BT27,MATCH(BY$4,$M$4:$BT$4,0)) -> 0 | BZ27: =INDEX($M27:$BT27,MATCH(BZ$4,$M$4:$BT$4,0)) -> 0
B28: Total Non Current Assets | M28: =SUM(M25:M27) -> 0 | N28: =SUM(N25:N27) -> 0 | O28: =SUM(O25:O27) -> 0 | P28: =SUM(P25:P27) -> 0 | Q28: =SUM(Q25:Q27) -> 0 | R28: =SUM(R25:R27) -> 0 | S28: =SUM(S25:S27) -> 0 | T28: =SUM(T25:T27) -> 0 | ... BT28: =SUM(BT25:BT27) -> 0 | BV28: =SUM(BV25:BV27) -> 0 | BW28: =SUM(BW25:BW27) -> 0 | BX28: =SUM(BX25:BX27) -> 0 | BY28: =SUM(BY25:BY27) -> 0 | BZ28: =SUM(BZ25:BZ27) -> 0
A30: Current Assets
A31: [+] | B31: Trade Receivables | BV31: =INDEX($M31:$BT31,MATCH(BV$4,$M$4:$BT$4,0)) -> 0 | BW31: =INDEX($M31:$BT31,MATCH(BW$4,$M$4:$BT$4,0)) -> 0 | BX31: =INDEX($M31:$BT31,MATCH(BX$4,$M$4:$BT$4,0)) -> 0 | BY31: =INDEX($M31:$BT31,MATCH(BY$4,$M$4:$BT$4,0)) -> 0 | BZ31: =INDEX($M31:$BT31,MATCH(BZ$4,$M$4:$BT$4,0)) -> 0
A32: [+] | B32: Inventory | BV32: =INDEX($M32:$BT32,MATCH(BV$4,$M$4:$BT$4,0)) -> 0 | BW32: =INDEX($M32:$BT32,MATCH(BW$4,$M$4:$BT$4,0)) -> 0 | BX32: =INDEX($M32:$BT32,MATCH(BX$4,$M$4:$BT$4,0)) -> 0 | BY32: =INDEX($M32:$BT32,MATCH(BY$4,$M$4:$BT$4,0)) -> 0 | BZ32: =INDEX($M32:$BT32,MATCH(BZ$4,$M$4:$BT$4,0)) -> 0
A33: [+] | B33: Cash and Cash Equivalents | M33: =CFS!M43 -> -26531.164 | N33: =CFS!N43 -> -53104.53 | O33: =CFS!O43 -> -76095.731 | P33: =CFS!P43 -> -96880.414 | Q33: =CFS!Q43 -> -117709.24 | R33: =CFS!R43 -> -135924.7 | S33: =CFS!S43 -> -152786.68 | T33: =CFS!T43 -> -169696.47 | ... BT33: =CFS!BT43 -> 741922.2 | BV33: =INDEX($M33:$BT33,MATCH(BV$4,$M$4:$BT$4,0)) -> -212953.32 | BW33: =INDEX($M33:$BT33,MATCH(BW$4,$M$4:$BT$4,0)) -> -198515.85 | BX33: =INDEX($M33:$BT33,MATCH(BX$4,$M$4:$BT$4,0)) -> -25483.374 | BY33: =INDEX($M33:$BT33,MATCH(BY$4,$M$4:$BT$4,0)) -> 254206.72 | BZ33: =INDEX($M33:$BT33,MATCH(BZ$4,$M$4:$BT$4,0)) -> 741922.2
A34: [+] | B34: Short Term Loans and Advances | BV34: =INDEX($M34:$BT34,MATCH(BV$4,$M$4:$BT$4,0)) -> 0 | BW34: =INDEX($M34:$BT34,MATCH(BW$4,$M$4:$BT$4,0)) -> 0 | BX34: =INDEX($M34:$BT34,MATCH(BX$4,$M$4:$BT$4,0)) -> 0 | BY34: =INDEX($M34:$BT34,MATCH(BY$4,$M$4:$BT$4,0)) -> 0 | BZ34: =INDEX($M34:$BT34,MATCH(BZ$4,$M$4:$BT$4,0)) -> 0
B35: Total Current Assets | M35: =SUM(M31:M34) -> -26531.164 | N35: =SUM(N31:N34) -> -53104.53 | O35: =SUM(O31:O34) -> -76095.731 | P35: =SUM(P31:P34) -> -96880.414 | Q35: =SUM(Q31:Q34) -> -117709.24 | R35: =SUM(R31:R34) -> -135924.7 | S35: =SUM(S31:S34) -> -152786.68 | T35: =SUM(T31:T34) -> -169696.47 | ... BT35: =SUM(BT31:BT34) -> 741922.2 | BV35: =SUM(BV31:BV34) -> -212953.32 | BW35: =SUM(BW31:BW34) -> -198515.85 | BX35: =SUM(BX31:BX34) -> -25483.374 | BY35: =SUM(BY31:BY34) -> 254206.72 | BZ35: =SUM(BZ31:BZ34) -> 741922.2
B37: Total Assets | M37: =M28+M35 -> -26531.164 | N37: =N28+N35 -> -53104.53 | O37: =O28+O35 -> -76095.731 | P37: =P28+P35 -> -96880.414 | Q37: =Q28+Q35 -> -117709.24 | R37: =R28+R35 -> -135924.7 | S37: =S28+S35 -> -152786.68 | T37: =T28+T35 -> -169696.47 | ... BT37: =BT28+BT35 -> 741922.2 | BV37: =BV28+BV35 -> -212953.32 | BW37: =BW28+BW35 -> -198515.85 | BX37: =BX28+BX35 -> -25483.374 | BY37: =BY28+BY35 -> 254206.72 | BZ37: =BZ28+BZ35 -> 741922.2
A38: Check | M38: =M37-M20 -> 0 | N38: =N37-N20 -> 0 | O38: =O37-O20 -> 0 | P38: =P37-P20 -> 0 | Q38: =Q37-Q20 -> 0 | R38: =R37-R20 -> 0 | S38: =S37-S20 -> 0 | T38: =T37-T20 -> 0 | ... BT38: =BT37-BT20 -> 0 | BV38: =BV37-BV20 -> 0 | BW38: =BW37-BW20 -> 0 | BX38: =BX37-BX20 -> 0 | BY38: =BY37-BY20 -> 0 | BZ38: =BZ37-BZ20 -> 0

Sheet CFS
A1: Cash Flow Statement
A2: Cells in Orange are assumptions | M2: MONTHLY | BV2: YEARLY
A3: Year | M3: 1 | N3: 1 | O3: 1 | P3: 1 | Q3: 1 | R3: 1 | S3: 1 | T3: 1 | U3: 1 | V3: 1 | W3: 1 | X3: 1 | Y3: =X3+1 -> 2 | Z3: =Y3 -> 2 | AA3: =Z3 -> 2 | AB3: =AA3 -> 2 | AC3: =AB3 -> 2 | AD3: =AC3 -> 2 | AE3: =AD3 -> 2 | AF3: =AE3 -> 2 | AG3: =AF3 -> 2 | ... AJ3: =AI3 -> 2 | AK3: 3 | AL3: 3 | AM3: 3 | AN3: 3 | AO3: 3 | AP3: 3 | AQ3: 3 | AR3: 3 | AS3: 3 | AT3: 3 | AU3: 3 | AV3: 3 | AW3: 4 | AX3: 4 | AY3: 4 | AZ3: 4 | BA3: 4 | BB3: 4 | BC3: 4 | BD3: 4 | BE3: 4 | BF3: 4 | BG3: 4 | BH3: 4 | BI3: 5 | BJ3: 5 | BK3: 5 | BL3: 5 | BM3: 5 | BN3: 5 | BO3: 5 | BP3: 5 | BQ3: 5 | BR3: 5 | BS3: 5 | BT3: 5 | BV3: 1 | BW3: 2 | BX3: 3 | BY3: 4 | BZ3: 5
A4: Months | M4: 1 | N4: =M4+1 -> 2 | O4: =N4+1 -> 3 | P4: =O4+1 -> 4 | Q4: =P4+1 -> 5 | R4: =Q4+1 -> 6 | S4: =R4+1 -> 7 | T4: =S4+1 -> 8 | U4: =T4+1 -> 9 | ... BT4: =BS4+1 -> 60 | BV4: 12 | BW4: 24 | BX4: 36 | BY4: 48 | BZ4: 60
A5: Cash Flow from Operations-
B6: Profit After Tax | M6: =IS!M35 -> -26531.164 | N6: =IS!N35 -> -26573.366 | O6: =IS!O35 -> -22991.201 | P6: =IS!P35 -> -20784.683 | Q6: =IS!Q35 -> -20828.825 | R6: =IS!R35 -> -18215.458 | S6: =IS!S35 -> -16861.981 | T6: =IS!T35 -> -16909.797 | ... BT6: =IS!BT35 -> 40494.33 | BV6: =SUMIF($M$3:$BT$3,BV$3,$M6:$BT6) -> -212953.32 | BW6: =SUMIF($M$3:$BT$3,BW$3,$M6:$BT6) -> 14437.473 | BX6: =SUMIF($M$3:$BT$3,BX$3,$M6:$BT6) -> 173032.48 | BY6: =SUMIF($M$3:$BT$3,BY$3,$M6:$BT6) -> 279690.09 | BZ6: =SUMIF($M$3:$BT$3,BZ$3,$M6:$BT6) -> 487715.48
A8: [+] | B8: Depreciation and Amortization Expenses | M8: 0 | N8: 0 | O8: 0 | P8: 0 | Q8: 0 | R8: 0 | S8: 0 | T8: 0 | U8: 0 | V8: 0 | W8: 0 | X8: 0 | Y8: 0 | Z8: 0 | AA8: 0 | AB8: 0 | AC8: 0 | AD8: 0 | AE8: 0 | AF8: 0 | AG8: 0 | AH8: 0 | AI8: 0 | AJ8: 0 | AK8: 0 | AL8: 0 | AM8: 0 | AN8: 0 | AO8: 0 | AP8: 0 | AQ8: 0 | AR8: 0 | AS8: 0 | AT8: 0 | AU8: 0 | AV8: 0 | AW8: 0 | AX8: 0 | AY8: 0 | AZ8: 0 | BA8: 0 | BB8: 0 | BC8: 0 | BD8: 0 | BE8: 0 | BF8: 0 | BG8: 0 | BH8: 0 | BI8: 0 | BJ8: 0 | BK8: 0 | BL8: 0 | BM8: 0 | BN8: 0 | BO8: 0 | BP8: 0 | BQ8: 0 | BR8: 0 | BS8: 0 | BT8: 0 | BV8: =SUMIF($M$3:$BT$3,BV$3,$M8:$BT8) -> 0 | BW8: =SUMIF($M$3:$BT$3,BW$3,$M8:$BT8) -> 0 | BX8: =SUMIF($M$3:$BT$3,BX$3,$M8:$BT8) -> 0 | BY8: =SUMIF($M$3:$BT$3,BY$3,$M8:$BT8) -> 0 | BZ8: =SUMIF($M$3:$BT$3,BZ$3,$M8:$BT8) -> 0
A9: [+] | B9: Interest Expenses
A10: [+] | B10: Preliminary Expenses written off
A11: [+] | B11: Interest Received
A12: [+] | B12: Loss/Profit on Sale of Assets
A13: [+] | B13: Liabilities written off
B14: Operating Profit before Working Capital Changes | M14: =SUM(M6:M13) -> -26531.164 | N14: =SUM(N6:N13) -> -26573.366 | O14: =SUM(O6:O13) -> -22991.201 | P14: =SUM(P6:P13) -> -20784.683 | Q14: =SUM(Q6:Q13) -> -20828.825 | R14: =SUM(R6:R13) -> -18215.458 | S14: =SUM(S6:S13) -> -16861.981 | T14: =SUM(T6:T13) -> -16909.797 | ... BT14: =SUM(BT6:BT13) -> 40494.33 | BV14: =SUM(BV6:BV13) -> -212953.32 | BW14: =SUM(BW6:BW13) -> 14437.473 | BX14: =SUM(BX6:BX13) -> 173032.48 | BY14: =SUM(BY6:BY13) -> 279690.09 | BZ14: =SUM(BZ6:BZ13) -> 487715.48
A15: Changes in working Capital | M15: =SUM(M16:M19,M21:M23) -> 0 | N15: =SUM(N16:N19,N21:N23) -> 0 | O15: =SUM(O16:O19,O21:O23) -> 0 | P15: =SUM(P16:P19,P21:P23) -> 0 | Q15: =SUM(Q16:Q19,Q21:Q23) -> 0 | R15: =SUM(R16:R19,R21:R23) -> 0 | S15: =SUM(S16:S19,S21:S23) -> 0 | T15: =SUM(T16:T19,T21:T23) -> 0 | ... BT15: =SUM(BT16:BT19,BT21:BT23) -> 0 | BV15: =SUMIF($M$3:$BT$3,BV$3,$M15:$BT15) -> 0 | BW15: =SUMIF($M$3:$BT$3,BW$3,$M15:$BT15) -> 0 | BX15: =SUMIF($M$3:$BT$3,BX$3,$M15:$BT15) -> 0 | BY15: =SUMIF($M$3:$BT$3,BY$3,$M15:$BT15) -> 0 | BZ15: =SUMIF($M$3:$BT$3,BZ$3,$M15:$BT15) -> 0
A16: [-] | B16: Trade Receivables | BV16: =SUMIF($M$3:$BT$3,BV$3,$M16:$BT16) -> 0 | BW16: =SUMIF($M$3:$BT$3,BW$3,$M16:$BT16) -> 0 | BX16: =SUMIF($M$3:$BT$3,BX$3,$M16:$BT16) -> 0 | BY16: =SUMIF($M$3:$BT$3,BY$3,$M16:$BT16) -> 0 | BZ16: =SUMIF($M$3:$BT$3,BZ$3,$M16:$BT16) -> 0
A17: [-] | B17: Inventories | BV17: =SUMIF($M$3:$BT$3,BV$3,$M17:$BT17) -> 0 | BW17: =SUMIF($M$3:$BT$3,BW$3,$M17:$BT17) -> 0 | BX17: =SUMIF($M$3:$BT$3,BX$3,$M17:$BT17) -> 0 | BY17: =SUMIF($M$3:$BT$3,BY$3,$M17:$BT17) -> 0 | BZ17: =SUMIF($M$3:$BT$3,BZ$3,$M17:$BT17) -> 0
A18: [-] | B18: Short Term Loans and Advances | BV18: =SUMIF($M$3:$BT$3,BV$3,$M18:$BT18) -> 0 | BW18: =SUMIF($M$3:$BT$3,BW$3,$M18:$BT18) -> 0 | BX18: =SUMIF($M$3:$BT$3,BX$3,$M18:$BT18) -> 0 | BY18: =SUMIF($M$3:$BT$3,BY$3,$M18:$BT18) -> 0 | BZ18: =SUMIF($M$3:$BT$3,BZ$3,$M18:$BT18) -> 0
A19: [-] | B19: Other Current Assets | BV19: =SUMIF($M$3:$BT$3,BV$3,$M19:$BT19) -> 0 | BW19: =SUMIF($M$3:$BT$3,BW$3,$M19:$BT19) -> 0 | BX19: =SUMIF($M$3:$BT$3,BX$3,$M19:$BT19) -> 0 | BY19: =SUMIF($M$3:$BT$3,BY$3,$M19:$BT19) -> 0 | BZ19: =SUMIF($M$3:$BT$3,BZ$3,$M19:$BT19) -> 0
A21: [+] | B21: Deferred Revenue | M21: =BS!M15-BS!L15 -> 0 | N21: =BS!N15-BS!M15 -> 0 | O21: =BS!O15-BS!N15 -> 0 | P21: =BS!P15-BS!O15 -> 0 | Q21: =BS!Q15-BS!P15 -> 0 | R21: =BS!R15-BS!Q15 -> 0 | S21: =BS!S15-BS!R15 -> 0 | T21: =BS!T15-BS!S15 -> 0 | ... BT21: =BS!BT15-BS!BS15 -> 0 | BV21: =SUMIF($M$3:$BT$3,BV$3,$M21:$BT21) -> 0 | BW21: =SUMIF($M$3:$BT$3,BW$3,$M21:$BT21) -> 0 | BX21: =SUMIF($M$3:$BT$3,BX$3,$M21:$BT21) -> 0 | BY21: =SUMIF($M$3:$BT$3,BY$3,$M21:$BT21) -> 0 | BZ21: =SUMIF($M$3:$BT$3,BZ$3,$M21:$BT21) -> 0
A22: [+] | B22: Trade Payables | BV22: =SUMIF($M$3:$BT$3,BV$3,$M22:$BT22) -> 0 | BW22: =SUMIF($M$3:$BT$3,BW$3,$M22:$BT22) -> 0 | BX22: =SUMIF($M$3:$BT$3,BX$3,$M22:$BT22) -> 0 | BY22: =SUMIF($M$3:$BT$3,BY$3,$M22:$BT22) -> 0 | BZ22: =SUMIF($M$3:$BT$3,BZ$3,$M22:$BT22) -> 0
A23: [+] | B23: Other Current Liabilities | BV23: =SUMIF($M$3:$BT$3,BV$3,$M23:$BT23) -> 0 | BW23: =SUMIF($M$3:$BT$3,BW$3,$M23:$BT23) -> 0 | BX23: =SUMIF($M$3:$BT$3,BX$3,$M23:$BT23) -> 0 | BY23: =SUMIF($M$3:$BT$3,BY$3,$M23:$BT23) -> 0 | BZ23: =SUMIF($M$3:$BT$3,BZ$3,$M23:$BT23) -> 0
B25: Change in Cash Flow from Operations | M25: =SUM(M14:M15) -> -26531.164 | N25: =SUM(N14:N15) -> -26573.366 | O25: =SUM(O14:O15) -> -22991.201 | P25: =SUM(P14:P15) -> -20784.683 | Q25: =SUM(Q14:Q15) -> -20828.825 | R25: =SUM(R14:R15) -> -18215.458 | S25: =SUM(S14:S15) -> -16861.981 | T25: =SUM(T14:T15) -> -16909.797 | ... BT25: =SUM(BT14:BT15) -> 40494.33 | BV25: =SUM(BV14,BV16:BV23) -> -212953.32 | BW25: =SUM(BW14,BW16:BW23) -> 14437.473 | BX25: =SUM(BX14,BX16:BX23) -> 173032.48 | BY25: =SUM(BY14,BY16:BY23) -> 279690.09 | BZ25: =SUM(BZ14,BZ16:BZ23) -> 487715.48
A27: Cash Flow from Investing Activities-
B28: Purchase/sale of Non current Assets | BV28: =SUMIF($M$3:$BT$3,BV$3,$M28:$BT28) -> 0 | BW28: =SUMIF($M$3:$BT$3,BW$3,$M28:$BT28) -> 0 | BX28: =SUMIF($M$3:$BT$3,BX$3,$M28:$BT28) -> 0 | BY28: =SUMIF($M$3:$BT$3,BY$3,$M28:$BT28) -> 0 | BZ28: =SUMIF($M$3:$BT$3,BZ$3,$M28:$BT28) -> 0
A29: [+] | B29: Purchase/sale of Other Non Current Asset | BV29: =SUMIF($M$3:$BT$3,BV$3,$M29:$BT29) -> 0 | BW29: =SUMIF($M$3:$BT$3,BW$3,$M29:$BT29) -> 0 | BX29: =SUMIF($M$3:$BT$3,BX$3,$M29:$BT29) -> 0 | BY29: =SUMIF($M$3:$BT$3,BY$3,$M29:$BT29) -> 0 | BZ29: =SUMIF($M$3:$BT$3,BZ$3,$M29:$BT29) -> 0
B31: Changes in Cash Flow from Investing | M31: =SUM(M28:M29) -> 0 | N31: =SUM(N28:N29) -> 0 | O31: =SUM(O28:O29) -> 0 | P31: =SUM(P28:P29) -> 0 | Q31: =SUM(Q28:Q29) -> 0 | R31: =SUM(R28:R29) -> 0 | S31: =SUM(S28:S29) -> 0 | T31: =SUM(T28:T29) -> 0 | ... BT31: =SUM(BT28:BT29) -> 0 | BV31: =SUM(BV28:BV29) -> 0 | BW31: =SUM(BW28:BW29) -> 0 | BX31: =SUM(BX28:BX29) -> 0 | BY31: =SUM(BY28:BY29) -> 0 | BZ31: =SUM(BZ28:BZ29) -> 0
A33: Cash Flow from Financing Activities-
A34: [+] | B34: Increase/Decrease in Share Capital | BV34: =SUMIF($M$3:$BT$3,BV$3,$M34:$BT34) -> 0 | BW34: =SUMIF($M$3:$BT$3,BW$3,$M34:$BT34) -> 0 | BX34: =SUMIF($M$3:$BT$3,BX$3,$M34:$BT34) -> 0 | BY34: =SUMIF($M$3:$BT$3,BY$3,$M34:$BT34) -> 0 | BZ34: =SUMIF($M$3:$BT$3,BZ$3,$M34:$BT34) -> 0
A35: [+] | B35: Premium Collected on issue of Shares | BV35: =SUMIF($M$3:$BT$3,BV$3,$M35:$BT35) -> 0 | BW35: =SUMIF($M$3:$BT$3,BW$3,$M35:$BT35) -> 0 | BX35: =SUMIF($M$3:$BT$3,BX$3,$M35:$BT35) -> 0 | BY35: =SUMIF($M$3:$BT$3,BY$3,$M35:$BT35) -> 0 | BZ35: =SUMIF($M$3:$BT$3,BZ$3,$M35:$BT35) -> 0
A36: [-] | B36: Interest Expenses | BV36: =SUMIF($M$3:$BT$3,BV$3,$M36:$BT36) -> 0 | BW36: =SUMIF($M$3:$BT$3,BW$3,$M36:$BT36) -> 0 | BX36: =SUMIF($M$3:$BT$3,BX$3,$M36:$BT36) -> 0 | BY36: =SUMIF($M$3:$BT$3,BY$3,$M36:$BT36) -> 0 | BZ36: =SUMIF($M$3:$BT$3,BZ$3,$M36:$BT36) -> 0
A37: [+] | B37: Increase/Decrease in Long Term Borrowings | BV37: =SUMIF($M$3:$BT$3,BV$3,$M37:$BT37) -> 0 | BW37: =SUMIF($M$3:$BT$3,BW$3,$M37:$BT37) -> 0 | BX37: =SUMIF($M$3:$BT$3,BX$3,$M37:$BT37) -> 0 | BY37: =SUMIF($M$3:$BT$3,BY$3,$M37:$BT37) -> 0 | BZ37: =SUMIF($M$3:$BT$3,BZ$3,$M37:$BT37) -> 0
A38: [+] | B38: Increase/Decrease in Other Short Term Borrowings | BV38: =SUMIF($M$3:$BT$3,BV$3,$M38:$BT38) -> 0 | BW38: =SUMIF($M$3:$BT$3,BW$3,$M38:$BT38) -> 0 | BX38: =SUMIF($M$3:$BT$3,BX$3,$M38:$BT38) -> 0 | BY38: =SUMIF($M$3:$BT$3,BY$3,$M38:$BT38) -> 0 | BZ38: =SUMIF($M$3:$BT$3,BZ$3,$M38:$BT38) -> 0
B39: Changes in Cash Flow from Financing | M39: =SUM(M34:M38) -> 0 | N39: =SUM(N34:N38) -> 0 | O39: =SUM(O34:O38) -> 0 | P39: =SUM(P34:P38) -> 0 | Q39: =SUM(Q34:Q38) -> 0 | R39: =SUM(R34:R38) -> 0 | S39: =SUM(S34:S38) -> 0 | T39: =SUM(T34:T38) -> 0 | ... BT39: =SUM(BT34:BT38) -> 0 | BV39: =SUM(BV34:BV38) -> 0 | BW39: =SUM(BW34:BW38) -> 0 | BX39: =SUM(BX34:BX38) -> 0 | BY39: =SUM(BY34:BY38) -> 0 | BZ39: =SUM(BZ34:BZ38) -> 0
B41: Net Changes in Cash & Cash Equivalents | M41: =M39+M31+M25 -> -26531.164 | N41: =N39+N31+N25 -> -26573.366 | O41: =O39+O31+O25 -> -22991.201 | P41: =P39+P31+P25 -> -20784.683 | Q41: =Q39+Q31+Q25 -> -20828.825 | R41: =R39+R31+R25 -> -18215.458 | S41: =S39+S31+S25 -> -16861.981 | T41: =T39+T31+T25 -> -16909.797 | ... BT41: =BT39+BT31+BT25 -> 40494.33 | BV41: =BV39+BV31+BV25 -> -212953.32 | BW41: =BW39+BW31+BW25 -> 14437.473 | BX41: =BX39+BX31+BX25 -> 173032.48 | BY41: =BY39+BY31+BY25 -> 279690.09 | BZ41: =BZ39+BZ31+BZ25 -> 487715.48
B42: Cash Opening balance | M42: 0 | N42: =M43 -> -26531.164 | O42: =N43 -> -53104.53 | P42: =O43 -> -76095.731 | Q42: =P43 -> -96880.414 | R42: =Q43 -> -117709.24 | S42: =R43 -> -135924.7 | T42: =S43 -> -152786.68 | U42: =T43 -> -169696.47 | ... BT42: =BS43 -> 701427.87 | BV42: =M42 -> 0 | BW42: =BV43 -> -212953.32 | BX42: =BW43 -> -198515.85 | BY42: =BX43 -> -25483.374 | BZ42: =BY43 -> 254206.72
B43: Cash Closing Balance | M43: =M42+M41 -> -26531.164 | N43: =N42+N41 -> -53104.53 | O43: =O42+O41 -> -76095.731 | P43: =P42+P41 -> -96880.414 | Q43: =Q42+Q41 -> -117709.24 | R43: =R42+R41 -> -135924.7 | S43: =S42+S41 -> -152786.68 | T43: =T42+T41 -> -169696.47 | ... BT43: =BT42+BT41 -> 741922.2 | BV43: =BV42+BV41 -> -212953.32 | BW43: =BW42+BW41 -> -198515.85 | BX43: =BX42+BX41 -> -25483.374 | BY43: =BY42+BY41 -> 254206.72 | BZ43: =BZ42+BZ41 -> 741922.2
A45: Year 1 | B45: Cash Burn 12 M | D45: =X43 -> -212953.32

Sheet Valuation
A1: VANTLOGIX TECHNOLOGIES PRIVATE LIMITED - Venture Capital Method Valuation
A2: INR:USD | B2: =Assumptions!G7 -> 85.17
A3: Precedent Transaction Analysis
A5: Industry Name | B5: Number of firms | C5: Price/Sales | D5: Net Margin | E5: EV/Sales | F5: Pre-tax Operating Margin | T5: https://pages.stern.nyu.edu/~adamodar/New_Home_Page/datafile/psdata.html
A6: Software (Entertainment) | B6: 81 | C6: 7.3 | D6: 0.2743 | E6: 7.35 | F6: 0.3216
A7: Software (Internet) | B7: 29 | C7: 7.01 | D7: -0.026 | E7: 7.59 | F7: 0.0205
A8: Software (System & Application) | B8: 333 | C8: 11.2 | D8: 0.2294 | E8: 11.54 | F8: 0.2877
D13: EV/Revenue Multiple
C14: Industry Median | D14: 11.54
D16: (In $ Mn)
C17: ARR (60th Month) | D17: ='Revenue Buildup'!BT17/10^6 -> 1.5
C18: EV | D18: 15.579
C20: Discount Rate | D20: 0.5
C21: Post Money Valuation | D21: =D18/(1+D20)^5 -> 2.0515556
C22: Total Investment | D22: =ABS(CFS!D45)/10^6 -> 0.21295332
C23: Pre Money Valuation | D23: =D21-D22 -> 1.8386022
C24: Funding Round Stake sale | D24: =D22/D21 -> 0.10380091
C27: Sensitivity Analysis
E30: Multiple
D31: =D21 -> 2.0515556 | E31: 9.54 | F31: 10.54 | G31: 11.54 | H31: 12.54 | I31: 13.54
C32: Post Money Valuation | D32: 0.4 | E32: 2.8966725 | F32: 2.8966725 | G32: 2.8966725 | H32: 2.8966725 | I32: 2.8966725
D33: 0.45 | E33: 2.4305221 | F33: 2.4305221 | G33: 2.4305221 | H33: 2.4305221 | I33: 2.4305221
D34: 0.5 | E34: 2.0515556 | F34: 2.0515556 | G34: 2.0515556 | H34: 2.0515556 | I34: 2.0515556
D35: 0.55 | E35: 1.74133 | F35: 1.74133 | G35: 1.74133 | H35: 1.74133 | I35: 1.74133
D36: 0.6 | E36: 1.4857292 | F36: 1.4857292 | G36: 1.4857292 | H36: 1.4857292 | I36: 1.4857292
C38: Pre Money Valuation | D38: =D32 -> 0.4 | E38: =E32-$E$29 -> 2.8966725 | F38: =F32-$E$29 -> 2.8966725 | G38: =G32-$E$29 -> 2.8966725 | H38: =H32-$E$29 -> 2.8966725 | I38: =I32-$E$29 -> 2.8966725
D39: =D33 -> 0.45 | E39: =E33-$E$29 -> 2.4305221 | F39: =F33-$E$29 -> 2.4305221 | G39: =G33-$E$29 -> 2.4305221 | H39: =H33-$E$29 -> 2.4305221 | I39: =I33-$E$29 -> 2.4305221
D40: =D34 -> 0.5 | E40: =E34-$E$29 -> 2.0515556 | F40: =F34-$E$29 -> 2.0515556 | G40: =G34-$E$29 -> 2.0515556 | H40: =H34-$E$29 -> 2.0515556 | I40: =I34-$E$29 -> 2.0515556
D41: =D35 -> 0.55 | E41: =E35-$E$29 -> 1.74133 | F41: =F35-$E$29 -> 1.74133 | G41: =G35-$E$29 -> 1.74133 | H41: =H35-$E$29 -> 1.74133 | I41: =I35-$E$29 -> 1.74133
D42: =D36 -> 0.6 | E42: =E36-$E$29 -> 1.4857292 | F42: =F36-$E$29 -> 1.4857292 | G42: =G36-$E$29 -> 1.4857292 | H42: =H36-$E$29 -> 1.4857292 | I42: =I36-$E$29 -> 1.4857292
C44: Funding Round Stake Sale | D44: =D32 -> 0.4 | E44: =$D$22/E32 -> 0.073516534 | F44: =$D$22/F32 -> 0.073516534 | G44: =$D$22/G32 -> 0.073516534 | H44: =$D$22/H32 -> 0.073516534 | I44: =$D$22/I32 -> 0.073516534
D45: =D33 -> 0.45 | E45: =$D$22/E33 -> 0.087616289 | F45: =$D$22/F33 -> 0.087616289 | G45: =$D$22/G33 -> 0.087616289 | H45: =$D$22/H33 -> 0.087616289 | I45: =$D$22/I33 -> 0.087616289
D46: =D34 -> 0.5 | E46: =$D$22/E34 -> 0.10380091 | F46: =$D$22/F34 -> 0.10380091 | G46: =$D$22/G34 -> 0.10380091 | H46: =$D$22/H34 -> 0.10380091 | I46: =$D$22/I34 -> 0.10380091
D47: =D35 -> 0.55 | E47: =$D$22/E35 -> 0.12229349 | F47: =$D$22/F35 -> 0.12229349 | G47: =$D$22/G35 -> 0.12229349 | H47: =$D$22/H35 -> 0.12229349 | I47: =$D$22/I35 -> 0.12229349
D48: =D36 -> 0.6 | E48: =$D$22/E36 -> 0.14333253 | F48: =$D$22/F36 -> 0.14333253 | G48: =$D$22/G36 -> 0.14333253 | H48: =$D$22/H36 -> 0.14333253 | I48: =$D$22/I36 -> 0.14333253

Sheet Sheet10
A1: Direct Costs (COGS) for a B2B SaaS Business
A3: COGS includes all direct costs required to deliver the software service. These typically include:
A5: Hosting & Infrastructure Costs
A7: Cloud services (AWS, Google Cloud, Azure)
A8: Database and storage (e.g., Amazon RDS, MongoDB Atlas)
A9: Content delivery networks (CDN)
A10: Load balancers and networking costs
A12: Third-Party Software & API Costs
A14: Payment gateway fees (e.g., Stripe, Razorpay)
A15: AI/ML APIs (e.g., OpenAI, Google Cloud APIs)
A16: Email/SMS services (e.g., SendGrid, Twilio)
A17: Security services (e.g., Cloudflare, Auth0)
... A37: Software licenses for development tools used in maintaining the SaaS product

Sheet Sheet1
A1: 1. Marketing Team Structure & Roles
A3: Role | B3: Responsibilities | C3: Headcount (Early, Growth, Scale)
A4: Chief Marketing Officer | B4: Owns marketing strategy, brand positioning & demand generation. | C4: 1 (Growth)
A5: Content Marketing Manager | B5: Creates blogs, case studies, whitepapers, and e-books. | C5: 1 (Early) → 3+ (Scale)
A6: SEO & Organic Growth Specialist | B6: Handles website traffic, keyword ranking & link-building. | C6: 1 (Growth) → 2+ (Scale)
A7: Performance Marketing Manager (PPC) | B7: Runs Google Ads, LinkedIn Ads & paid acquisition campaigns. | C7: 1 (Growth) → 3+ (Scale)
A8: Marketing Automation Specialist | B8: Manages email campaigns, drip sequences & CRM workflows. | C8: 1 (Growth) → 2+ (Scale)
A9: Social Media & Community Manager | B9: Builds brand presence on LinkedIn, Twitter & Slack communities. | C9: 1 (Early) → 2+ (Scale)
A10: PR & Media Relations Manager | B10: Handles press releases, thought leadership & industry outreach. | C10: 1 (Growth)
A11: Event & Webinar Marketing Manager | B11: Plans conferences, virtual events, and speaking engagements. | C11: 1 (Growth)
A12: Video Content Creator | B12: Produces product demos, testimonials & video ads. | C12: 1 (Growth) → 2+ (Scale)
A13: Partner & Affiliate Marketing Manager | B13: Develops strategic alliances & referral programs. | C13: 1 (Growth)
A16: Head of Marketing (1)
A17: ✔ Growth Team (2) → Growth Marketing Manager, SEO/Automation Specialist
A18: ✔ Brand & Community (2) → PR Manager, Social Media Manager
A19: ✔ Content & Creative (2) → Content Manager, Video Designer
